Workbook

Sheet Customers
A1: customer_id | B1: customer_unique_id | C1: customer_zip_code_prefix | D1: customer_city | E1: customer_state | F1: CustomerName | G1: Region | H1: ProvinceCity | I1: Email | J1: Phone | K1: RegisteredDate | L1: owner_id | M1: CustomerStatus | N1: CustomerSegment
A2: CUS00001 | B2: KH0001 | C2: 55000 | D2: Đà Nẵng | E2: DN | F2: Phạm Văn Hải | G2: Miền Trung | H2: Đà Nẵng | I2: kh0001@example.vn | J2: 0960 351 958 | K2: 45421 | L2: EMP001 | M2: Active | N2: Tiềm năng
A3: CUS00002 | B3: KH0002 | C3: 10000 | D3: Hà Nội | E3: HN | F3: Huỳnh Quốc Ngân | G3: Miền Bắc | H3: Hà Nội | I3: kh0002@example.vn | J3: 0931 115 592 | K3: 44962 | L3: EMP002 | M3: Active | N3: Tiềm năng
A4: CUS00003 | B4: KH0003 | C4: 56000 | D4: Quảng Nam | E4: QNA | F4: Võ Thị Mai | G4: Miền Trung | H4: Quảng Nam | I4: kh0003@example.vn | J4: 0956 296 045 | K4: 45643 | L4: EMP003 | M4: Active | N4: Tiềm năng cao
A5: CUS00004 | B5: KH0004 | C5: 25000 | D5: Thái Nguyên | E5: TN | F5: Trần Quốc Hạnh | G5: Miền Bắc | H5: Thái Nguyên | I5: kh0004@example.vn | J5: 0964 011 841 | K5: 45172 | L5: EMP004 | M5: Active | N5: Thông thường
A6: CUS00005 | B6: KH0005 | C6: 25000 | D6: Thái Nguyên | E6: TN | F6: Nguyễn Thị Hải | G6: Miền Bắc | H6: Thái Nguyên | I6: kh0005@example.vn | J6: 0928 246 491 | K6: 45040 | L6: EMP005 | M6: Active | N6: Thông thường
A7: CUS00006 | B7: KH0006 | C7: 25000 | D7: Thái Nguyên | E7: TN | F7: Trần Thị Hùng | G7: Miền Bắc | H7: Thái Nguyên | I7: kh0006@example.vn | J7: 0987 510 567 | K7: 45293 | L7: EMP006 | M7: Active | N7: Tiềm năng
A8: CUS00007 | B8: KH0007 | C8: 18000 | D8: Hải Phòng | E8: HP | F8: Nguyễn Ngọc Hùng | G8: Miền Bắc | H8: Hải Phòng | I8: kh0007@example.vn | J8: 0907 383 466 | K8: 45566 | L8: EMP007 | M8: Active | N8: Thông thường
A9: CUS00008 | B9: KH0008 | C9: 65000 | D9: Khánh Hòa | E9: KH | F9: Lê Ngọc Lan | G9: Miền Trung | H9: Khánh Hòa | I9: kh0008@example.vn | J9: 0961 580 884 | K9: 45263 | L9: EMP008 | M9: Active | N9: Tiềm năng
A10: CUS00009 | B10: KH0009 | C10: 16000 | D10: Bắc Ninh | E10: BN | F10: Huỳnh Quốc Bảo | G10: Miền Bắc | H10: Bắc Ninh | I10: kh0009@example.vn | J10: 0984 807 255 | K10: 45075 | L10: EMP001 | M10: Active | N10: Tiềm năng
A11: CUS00010 | B11: KH0010 | C11: 78000 | D11: Bà Rịa - Vũng Tàu | E11: BRVT | F11: Võ Minh Quân | G11: Miền Nam | H11: Bà Rịa - Vũng Tàu | I11: kh0010@example.vn | J11: 0944 109 467 | K11: 45177 | L11: EMP002 | M11: Active | N11: Thông thường
A12: CUS00011 | B12: KH0011 | C12: 18000 | D12: Hải Phòng | E12: HP | F12: Bùi Gia Long | G12: Miền Bắc | H12: Hải Phòng | I12: kh0011@example.vn | J12: 0914 998 960 | K12: 45428 | L12: EMP003 | M12: Active | N12: Chưa đủ dữ liệu
A13: CUS00012 | B13: KH0012 | C13: 20000 | D13: Quảng Ninh | E13: QN | F13: Trần Ngọc Lan | G13: Miền Bắc | H13: Quảng Ninh | I13: kh0012@example.vn | J13: 0915 503 813 | K13: 44992 | L13: EMP004 | M13: Active | N13: Tiềm năng
... A81: CUS00080 | B81: KH0080 | C81: 90000 | D81: Cần Thơ | E81: CT | F81: Nguyễn Quốc Châu | G81: Miền Nam | H81: Cần Thơ | I81: kh0080@example.vn | J81: 0966 439 551 | K81: 45055 | L81: EMP008 | M81: Active | N81: Chưa đủ dữ liệu

Sheet Products
A1: product_id | B1: product_category_name | C1: product_name_lenght | D1: product_description_lenght | E1: product_photos_qty | F1: product_weight_g | G1: product_length_cm | H1: product_height_cm | I1: product_width_cm | J1: Description | K1: ProductCategory | L1: ListPrice | M1: Currency | N1: ProductStatus
A2: SP001 | B2: dien_tu | C2: 18 | D2: 296 | E2: 1 | F2: 150 | G2: 8 | H2: 3 | I2: 8 | J2: Tai nghe Bluetooth | K2: Điện tử | L2: 440500 | M2: VNĐ | N2: Active
A3: SP002 | B3: dien_tu | C3: 15 | D3: 260 | E3: 2 | F3: 323 | G3: 15 | H3: 8 | I3: 19 | J3: Chuột không dây | K3: Điện tử | L3: 212300 | M3: VNĐ | N3: Active
A4: SP003 | B4: dien_tu | C4: 18 | D4: 296 | E4: 3 | F4: 496 | G4: 22 | H4: 13 | I4: 30 | J4: Loa Bluetooth mini | K4: Điện tử | L4: 380333 | M4: VNĐ | N4: Active
A5: SP004 | B5: dien_tu | C5: 16 | D5: 272 | E5: 4 | F5: 669 | G5: 29 | H5: 18 | I5: 41 | J5: Bàn phím cơ mini | K5: Điện tử | L5: 763867 | M5: VNĐ | N5: Active
A6: SP005 | B6: thoi_trang | C6: 14 | D6: 248 | E6: 5 | F6: 842 | G6: 36 | H6: 23 | I6: 52 | J6: Áo thun cotton | K6: Thời trang | L6: 177429 | M6: VNĐ | N6: Active
A7: SP006 | B7: thoi_trang | C7: 12 | D7: 224 | E7: 1 | F7: 1015 | G7: 43 | H7: 3 | I7: 13 | J7: Túi đeo chéo | K7: Thời trang | L7: 316571 | M7: VNĐ | N7: Active
A8: SP007 | B8: thoi_trang | C8: 12 | D8: 224 | E8: 2 | F8: 1188 | G8: 50 | H8: 8 | I8: 24 | J8: Mũ lưỡi trai | K8: Thời trang | L8: 142333 | M8: VNĐ | N8: Active
A9: SP008 | B9: thoi_trang | C9: 13 | D9: 236 | E9: 3 | F9: 1361 | G9: 57 | H9: 13 | I9: 35 | J9: Ví da nhỏ gọn | K9: Thời trang | L9: 279125 | M9: VNĐ | N9: Active
A10: SP009 | B10: my_pham | C10: 19 | D10: 308 | E10: 4 | F10: 1534 | G10: 9 | H10: 18 | I10: 46 | J10: Sữa rửa mặt dịu nhẹ | K10: Mỹ phẩm | L10: 159000 | M10: VNĐ | N10: Active
A11: SP010 | B11: my_pham | C11: 13 | D11: 236 | E11: 5 | F11: 1707 | G11: 16 | H11: 23 | I11: 57 | J11: Son dưỡng môi | K11: Mỹ phẩm | L11: 92800 | M11: VNĐ | N11: Active
A12: SP011 | B12: my_pham | C12: 20 | D12: 320 | E12: 1 | F12: 1880 | G12: 23 | H12: 3 | I12: 18 | J12: Kem chống nắng SPF50 | K12: Mỹ phẩm | L12: 275375 | M12: VNĐ | N12: Active
A13: SP012 | B13: my_pham | C13: 14 | D13: 248 | E13: 2 | F13: 2053 | G13: 30 | H13: 8 | I13: 29 | J13: Nước tẩy trang | K13: Mỹ phẩm | L13: 191455 | M13: VNĐ | N13: Active
... A41: SP040 | B41: phu_kien | C41: 20 | D41: 320 | E41: 5 | F41: 2097 | G41: 61 | H41: 23 | I41: 37 | J41: Túi chống sốc laptop | K41: Phụ kiện | L41: 254583 | M41: VNĐ | N41: Active

Sheet Orders
A1: order_id | B1: customer_id | C1: order_status | D1: order_purchase_timestamp | E1: order_approved_at | F1: order_delivered_carrier_date | G1: order_delivered_customer_date | H1: order_estimated_delivery_date | I1: CustomerID | J1: SalesChannel | K1: PaymentMethod | L1: Region | M1: ProvinceCity | N1: owner_id | O1: OrderSubtotal | P1: FreightTotal | Q1: DiscountTotal | R1: OrderTotal | S1: Currency | T1: IsValidForRFM
A2: DH00001 | B2: CUS00057 | C2: delivered | D2: 45905.313 | E2: 45905.397 | F2: 45907.313 | G2: 45911.313 | H2: 45913.313 | I2: KH0057 | J2: Cửa hàng | K2: Chuyển khoản | L2: Miền Bắc | M2: Thái Nguyên | N2: =IFERROR(VLOOKUP(I2,Customers!$B$2:$L$81,11,FALSE),"") -> EMP001 | O2: =SUMIF(OderItems!$A$2:$A$510,A2,OderItems!$L$2:$L$510) -> 3384000 | P2: =SUMIF(OderItems!$A$2:$A$510,A2,OderItems!$G$2:$G$510) -> 57000 | Q2: =SUMIF(OderItems!$A$2:$A$510,A2,OderItems!$K$2:$K$510) -> 0 | R2: =O2+P2-Q2 -> 3441000 | S2: VNĐ | T2: =AND(C2="delivered",I2<>"",R2>0) -> TRUE
A3: DH00002 | B3: CUS00056 | C3: delivered | D3: 46135.772 | E3: 46135.855 | F3: 46137.772 | G3: 46141.772 | H3: 46143.772 | I3: KH0056 | J3: Cửa hàng | K3: COD | L3: Miền Nam | M3: TP. Hồ Chí Minh | N3: =IFERROR(VLOOKUP(I3,Customers!$B$2:$L$81,11,FALSE),"") -> EMP008 | O3: =SUMIF(OderItems!$A$2:$A$510,A3,OderItems!$L$2:$L$510) -> 2806000 | P3: =SUMIF(OderItems!$A$2:$A$510,A3,OderItems!$G$2:$G$510) -> 45000 | Q3: =SUMIF(OderItems!$A$2:$A$510,A3,OderItems!$K$2:$K$510) -> 0 | R3: =O3+P3-Q3 -> 2851000 | S3: VNĐ | T3: =AND(C3="delivered",I3<>"",R3>0) -> TRUE
A4: DH00003 | B4: CUS00026 | C4: delivered | D4: 45805.419 | E4: 45805.503 | F4: 45807.419 | G4: 45811.419 | H4: 45813.419 | I4: KH0026 | J4: Ứng dụng | K4: Ví điện tử | L4: Miền Trung | M4: Bình Định | N4: =IFERROR(VLOOKUP(I4,Customers!$B$2:$L$81,11,FALSE),"") -> EMP002 | O4: =SUMIF(OderItems!$A$2:$A$510,A4,OderItems!$L$2:$L$510) -> 618000 | P4: =SUMIF(OderItems!$A$2:$A$510,A4,OderItems!$G$2:$G$510) -> 12000 | Q4: =SUMIF(OderItems!$A$2:$A$510,A4,OderItems!$K$2:$K$510) -> 0 | R4: =O4+P4-Q4 -> 630000 | S4: VNĐ | T4: =AND(C4="delivered",I4<>"",R4>0) -> TRUE
A5: DH00004 | B5: CUS00033 | C5: delivered | D5: 46121.639 | E5: 46121.722 | F5: 46123.639 | G5: 46127.639 | H5: 46129.639 | I5: KH0033 | J5: Website | K5: Thẻ ngân hàng | L5: Miền Bắc | M5: Bắc Ninh | N5: =IFERROR(VLOOKUP(I5,Customers!$B$2:$L$81,11,FALSE),"") -> EMP001 | O5: =SUMIF(OderItems!$A$2:$A$510,A5,OderItems!$L$2:$L$510) -> 1155000 | P5: =SUMIF(OderItems!$A$2:$A$510,A5,OderItems!$G$2:$G$510) -> 30000 | Q5: =SUMIF(OderItems!$A$2:$A$510,A5,OderItems!$K$2:$K$510) -> 0 | R5: =O5+P5-Q5 -> 1185000 | S5: VNĐ | T5: =AND(C5="delivered",I5<>"",R5>0) -> TRUE
A6: DH00005 | B6: CUS00078 | C6: delivered | D6: 46196.926 | E6: 46197.009 | F6: 46198.926 | G6: 46202.926 | H6: 46204.926 | I6: KH0078 | J6: Sàn thương mại điện tử | K6: COD | L6: Miền Trung | M6: Thừa Thiên Huế | N6: =IFERROR(VLOOKUP(I6,Customers!$B$2:$L$81,11,FALSE),"") -> EMP006 | O6: =SUMIF(OderItems!$A$2:$A$510,A6,OderItems!$L$2:$L$510) -> 2012000 | P6: =SUMIF(OderItems!$A$2:$A$510,A6,OderItems!$G$2:$G$510) -> 25000 | Q6: =SUMIF(OderItems!$A$2:$A$510,A6,OderItems!$K$2:$K$510) -> 0 | R6: =O6+P6-Q6 -> 2037000 | S6: VNĐ | T6: =AND(C6="delivered",I6<>"",R6>0) -> TRUE
A7: DH00006 | B7: CUS00053 | C7: delivered | D7: 45789.558 | E7: 45789.641 | F7: 45791.558 | G7: 45795.558 | H7: 45797.558 | I7: KH0053 | J7: Website | K7: Ví điện tử | L7: Miền Trung | M7: Thừa Thiên Huế | N7: =IFERROR(VLOOKUP(I7,Customers!$B$2:$L$81,11,FALSE),"") -> EMP005 | O7: =SUMIF(OderItems!$A$2:$A$510,A7,OderItems!$L$2:$L$510) -> 997000 | P7: =SUMIF(OderItems!$A$2:$A$510,A7,OderItems!$G$2:$G$510) -> 30000 | Q7: =SUMIF(OderItems!$A$2:$A$510,A7,OderItems!$K$2:$K$510) -> 0 | R7: =O7+P7-Q7 -> 1027000 | S7: VNĐ | T7: =AND(C7="delivered",I7<>"",R7>0) -> TRUE
A8: DH00007 | B8: CUS00041 | C8: delivered | D8: 45812.221 | E8: 45812.304 | F8: 45814.221 | G8: 45818.221 | H8: 45820.221 | I8: KH0041 | J8: Sàn thương mại điện tử | K8: Ví điện tử | L8: Miền Nam | M8: TP. Hồ Chí Minh | N8: =IFERROR(VLOOKUP(I8,Customers!$B$2:$L$81,11,FALSE),"") -> EMP001 | O8: =SUMIF(OderItems!$A$2:$A$510,A8,OderItems!$L$2:$L$510) -> 711000 | P8: =SUMIF(OderItems!$A$2:$A$510,A8,OderItems!$G$2:$G$510) -> 36000 | Q8: =SUMIF(OderItems!$A$2:$A$510,A8,OderItems!$K$2:$K$510) -> 0 | R8: =O8+P8-Q8 -> 747000 | S8: VNĐ | T8: =AND(C8="delivered",I8<>"",R8>0) -> TRUE
A9: DH00008 | B9: CUS00020 | C9: delivered | D9: 45522.834 | E9: 45522.917 | F9: 45524.834 | G9: 45528.834 | H9: 45530.834 | I9: KH0020 | J9: Website | K9: Ví điện tử | L9: Miền Nam | M9: Bà Rịa - Vũng Tàu | N9: =IFERROR(VLOOKUP(I9,Customers!$B$2:$L$81,11,FALSE),"") -> EMP004 | O9: =SUMIF(OderItems!$A$2:$A$510,A9,OderItems!$L$2:$L$510) -> 1905000 | P9: =SUMIF(OderItems!$A$2:$A$510,A9,OderItems!$G$2:$G$510) -> 42000 | Q9: =SUMIF(OderItems!$A$2:$A$510,A9,OderItems!$K$2:$K$510) -> 0 | R9: =O9+P9-Q9 -> 1947000 | S9: VNĐ | T9: =AND(C9="delivered",I9<>"",R9>0) -> TRUE
A10: DH00009 | B10: CUS00035 | C10: canceled | D10: 45335.874 | H10: 45343.874 | I10: KH0035 | J10: Cửa hàng | K10: Ví điện tử | L10: Miền Nam | M10: Bình Dương | N10: =IFERROR(VLOOKUP(I10,Customers!$B$2:$L$81,11,FALSE),"") -> EMP003 | O10: =SUMIF(OderItems!$A$2:$A$510,A10,OderItems!$L$2:$L$510) -> 1184000 | P10: =SUMIF(OderItems!$A$2:$A$510,A10,OderItems!$G$2:$G$510) -> 50000 | Q10: =SUMIF(OderItems!$A$2:$A$510,A10,OderItems!$K$2:$K$510) -> 0 | R10: =O10+P10-Q10 -> 1234000 | S10: VNĐ | T10: =AND(C10="delivered",I10<>"",R10>0) -> FALSE
A11: DH00010 | B11: CUS00036 | C11: delivered | D11: 45351.111 | E11: 45351.194 | F11: 45353.111 | G11: 45357.111 | H11: 45359.111 | I11: KH0036 | J11: Website | K11: Chuyển khoản | L11: Miền Trung | M11: Quảng Nam | N11: =IFERROR(VLOOKUP(I11,Customers!$B$2:$L$81,11,FALSE),"") -> EMP004 | O11: =SUMIF(OderItems!$A$2:$A$510,A11,OderItems!$L$2:$L$510) -> 198000 | P11: =SUMIF(OderItems!$A$2:$A$510,A11,OderItems!$G$2:$G$510) -> 12000 | Q11: =SUMIF(OderItems!$A$2:$A$510,A11,OderItems!$K$2:$K$510) -> 0 | R11: =O11+P11-Q11 -> 210000 | S11: VNĐ | T11: =AND(C11="delivered",I11<>"",R11>0) -> TRUE
A12: DH00011 | B12: CUS00022 | C12: delivered | D12: 45784.633 | E12: 45784.717 | F12: 45786.633 | G12: 45790.633 | H12: 45792.633 | I12: KH0022 | J12: Cửa hàng | K12: Chuyển khoản | L12: Miền Nam | M12: Đồng Nai | N12: =IFERROR(VLOOKUP(I12,Customers!$B$2:$L$81,11,FALSE),"") -> EMP006 | O12: =SUMIF(OderItems!$A$2:$A$510,A12,OderItems!$L$2:$L$510) -> 742000 | P12: =SUMIF(OderItems!$A$2:$A$510,A12,OderItems!$G$2:$G$510) -> 9000 | Q12: =SUMIF(OderItems!$A$2:$A$510,A12,OderItems!$K$2:$K$510) -> 0 | R12: =O12+P12-Q12 -> 751000 | S12: VNĐ | T12: =AND(C12="delivered",I12<>"",R12>0) -> TRUE
A13: DH00012 | B13: CUS00046 | C13: delivered | D13: 45376.16 | E13: 45376.244 | F13: 45378.16 | G13: 45382.16 | H13: 45384.16 | I13: KH0046 | J13: Ứng dụng | K13: Chuyển khoản | L13: Miền Nam | M13: Bà Rịa - Vũng Tàu | N13: =IFERROR(VLOOKUP(I13,Customers!$B$2:$L$81,11,FALSE),"") -> EMP006 | O13: =SUMIF(OderItems!$A$2:$A$510,A13,OderItems!$L$2:$L$510) -> 1841000 | P13: =SUMIF(OderItems!$A$2:$A$510,A13,OderItems!$G$2:$G$510) -> 27000 | Q13: =SUMIF(OderItems!$A$2:$A$510,A13,OderItems!$K$2:$K$510) -> 0 | R13: =O13+P13-Q13 -> 1868000 | S13: VNĐ | T13: =AND(C13="delivered",I13<>"",R13>0) -> TRUE
A14: DH00013 | B14: CUS00060 | C14: canceled | D14: 45614.794 | H14: 45622.794 | I14: KH0060 | J14: Cửa hàng | K14: Chuyển khoản | L14: Miền Bắc | M14: Thái Nguyên | N14: =IFERROR(VLOOKUP(I14,Customers!$B$2:$L$81,11,FALSE),"") -> EMP004 | O14: =SUMIF(OderItems!$A$2:$A$510,A14,OderItems!$L$2:$L$510) -> 1441000 | P14: =SUMIF(OderItems!$A$2:$A$510,A14,OderItems!$G$2:$G$510) -> 18000 | Q14: =SUMIF(OderItems!$A$2:$A$510,A14,OderItems!$K$2:$K$510) -> 0 | R14: =O14+P14-Q14 -> 1459000 | S14: VNĐ | T14: =AND(C14="delivered",I14<>"",R14>0) -> FALSE
A15: DH00014 | B15: CUS00006 | C15: delivered | D15: 45750.179 | E15: 45750.262 | F15: 45752.179 | G15: 45756.179 | H15: 45758.179 | I15: KH0006 | J15: Ứng dụng | K15: Chuyển khoản | L15: Miền Bắc | M15: Thái Nguyên | N15: =IFERROR(VLOOKUP(I15,Customers!$B$2:$L$81,11,FALSE),"") -> EMP006 | O15: =SUMIF(OderItems!$A$2:$A$510,A15,OderItems!$L$2:$L$510) -> 270000 | P15: =SUMIF(OderItems!$A$2:$A$510,A15,OderItems!$G$2:$G$510) -> 8000 | Q15: =SUMIF(OderItems!$A$2:$A$510,A15,OderItems!$K$2:$K$510) -> 0 | R15: =O15+P15-Q15 -> 278000 | S15: VNĐ | T15: =AND(C15="delivered",I15<>"",R15>0) -> TRUE
A16: DH00015 | B16: CUS00045 | C16: delivered | D16: 45785.099 | E16: 45785.182 | F16: 45787.099 | G16: 45791.099 | H16: 45793.099 | I16: KH0045 | J16: Cửa hàng | K16: Ví điện tử | L16: Miền Bắc | M16: Thái Nguyên | N16: =IFERROR(VLOOKUP(I16,Customers!$B$2:$L$81,11,FALSE),"") -> EMP005 | O16: =SUMIF(OderItems!$A$2:$A$510,A16,OderItems!$L$2:$L$510) -> 1186000 | P16: =SUMIF(OderItems!$A$2:$A$510,A16,OderItems!$G$2:$G$510) -> 25000 | Q16: =SUMIF(OderItems!$A$2:$A$510,A16,OderItems!$K$2:$K$510) -> 0 | R16: =O16+P16-Q16 -> 1211000 | S16: VNĐ | T16: =AND(C16="delivered",I16<>"",R16>0) -> TRUE
A17: DH00016 | B17: CUS00022 | C17: delivered | D17: 45315.592 | E17: 45315.676 | F17: 45317.592 | G17: 45321.592 | H17: 45323.592 | I17: KH0022 | J17: Ứng dụng | K17: Thẻ ngân hàng | L17: Miền Nam | M17: Đồng Nai | N17: =IFERROR(VLOOKUP(I17,Customers!$B$2:$L$81,11,FALSE),"") -> EMP006 | O17: =SUMIF(OderItems!$A$2:$A$510,A17,OderItems!$L$2:$L$510) -> 2404000 | P17: =SUMIF(OderItems!$A$2:$A$510,A17,OderItems!$G$2:$G$510) -> 57000 | Q17: =SUMIF(OderItems!$A$2:$A$510,A17,OderItems!$K$2:$K$510) -> 0 | R17: =O17+P17-Q17 -> 2461000 | S17: VNĐ | T17: =AND(C17="delivered",I17<>"",R17>0) -> TRUE
A18: DH00017 | B18: CUS00021 | C18: processing | D18: 46128.979 | E18: 46129.063 | H18: 46136.979 | I18: KH0021 | J18: Website | K18: Thẻ ngân hàng | L18: Miền Nam | M18: Cần Thơ | N18: =IFERROR(VLOOKUP(I18,Customers!$B$2:$L$81,11,FALSE),"") -> EMP005 | O18: =SUMIF(OderItems!$A$2:$A$510,A18,OderItems!$L$2:$L$510) -> 3528000 | P18: =SUMIF(OderItems!$A$2:$A$510,A18,OderItems!$G$2:$G$510) -> 31000 | Q18: =SUMIF(OderItems!$A$2:$A$510,A18,OderItems!$K$2:$K$510) -> 0 | R18: =O18+P18-Q18 -> 3559000 | S18: VNĐ | T18: =AND(C18="delivered",I18<>"",R18>0) -> FALSE
A19: DH00018 | B19: CUS00033 | C19: returned | D19: 45396.033 | E19: 45396.117 | F19: 45398.033 | G19: 45402.033 | H19: 45404.033 | I19: KH0033 | J19: Website | K19: COD | L19: Miền Bắc | M19: Bắc Ninh | N19: =IFERROR(VLOOKUP(I19,Customers!$B$2:$L$81,11,FALSE),"") -> EMP001 | O19: =SUMIF(OderItems!$A$2:$A$510,A19,OderItems!$L$2:$L$510) -> 1075000 | P19: =SUMIF(OderItems!$A$2:$A$510,A19,OderItems!$G$2:$G$510) -> 19000 | Q19: =SUMIF(OderItems!$A$2:$A$510,A19,OderItems!$K$2:$K$510) -> 0 | R19: =O19+P19-Q19 -> 1094000 | S19: VNĐ | T19: =AND(C19="delivered",I19<>"",R19>0) -> FALSE
A20: DH00019 | B20: CUS00021 | C20: canceled | D20: 45767.12 | H20: 45775.12 | I20: KH0021 | J20: Cửa hàng | K20: Ví điện tử | L20: Miền Nam | M20: Cần Thơ | N20: =IFERROR(VLOOKUP(I20,Customers!$B$2:$L$81,11,FALSE),"") -> EMP005 | O20: =SUMIF(OderItems!$A$2:$A$510,A20,OderItems!$L$2:$L$510) -> 1439000 | P20: =SUMIF(OderItems!$A$2:$A$510,A20,OderItems!$G$2:$G$510) -> 38000 | Q20: =SUMIF(OderItems!$A$2:$A$510,A20,OderItems!$K$2:$K$510) -> 0 | R20: =O20+P20-Q20 -> 1477000 | S20: VNĐ | T20: =AND(C20="delivered",I20<>"",R20>0) -> FALSE
A21: DH00020 | B21: CUS00017 | C21: delivered | D21: 45784.588 | E21: 45784.672 | F21: 45786.588 | G21: 45790.588 | H21: 45792.588 | I21: KH0017 | J21: Sàn thương mại điện tử | K21: Thẻ ngân hàng | L21: Miền Nam | M21: Bà Rịa - Vũng Tàu | N21: =IFERROR(VLOOKUP(I21,Customers!$B$2:$L$81,11,FALSE),"") -> EMP001 | O21: =SUMIF(OderItems!$A$2:$A$510,A21,OderItems!$L$2:$L$510) -> 770000 | P21: =SUMIF(OderItems!$A$2:$A$510,A21,OderItems!$G$2:$G$510) -> 17000 | Q21: =SUMIF(OderItems!$A$2:$A$510,A21,OderItems!$K$2:$K$510) -> 0 | R21: =O21+P21-Q21 -> 787000 | S21: VNĐ | T21: =AND(C21="delivered",I21<>"",R21>0) -> TRUE
A22: DH00021 | B22: CUS00060 | C22: delivered | D22: 46190.641 | E22: 46190.724 | F22: 46192.641 | G22: 46196.641 | H22: 46198.641 | I22: KH0060 | J22: Cửa hàng | K22: Ví điện tử | L22: Miền Bắc | M22: Thái Nguyên | N22: =IFERROR(VLOOKUP(I22,Customers!$B$2:$L$81,11,FALSE),"") -> EMP004 | O22: =SUMIF(OderItems!$A$2:$A$510,A22,OderItems!$L$2:$L$510) -> 580000 | P22: =SUMIF(OderItems!$A$2:$A$510,A22,OderItems!$G$2:$G$510) -> 12000 | Q22: =SUMIF(OderItems!$A$2:$A$510,A22,OderItems!$K$2:$K$510) -> 0 | R22: =O22+P22-Q22 -> 592000 | S22: VNĐ | T22: =AND(C22="delivered",I22<>"",R22>0) -> TRUE
A23: DH00022 | B23: CUS00050 | C23: delivered | D23: 45767.053 | E23: 45767.136 | F23: 45769.053 | G23: 45773.053 | H23: 45775.053 | I23: KH0050 | J23: Sàn thương mại điện tử | K23: Thẻ ngân hàng | L23: Miền Nam | M23: Cần Thơ | N23: =IFERROR(VLOOKUP(I23,Customers!$B$2:$L$81,11,FALSE),"") -> EMP002 | O23: =SUMIF(OderItems!$A$2:$A$510,A23,OderItems!$L$2:$L$510) -> 500000 | P23: =SUMIF(OderItems!$A$2:$A$510,A23,OderItems!$G$2:$G$510) -> 13000 | Q23: =SUMIF(OderItems!$A$2:$A$510,A23,OderItems!$K$2:$K$510) -> 0 | R23: =O23+P23-Q23 -> 513000 | S23: VNĐ | T23: =AND(C23="delivered",I23<>"",R23>0) -> TRUE
A24: DH00023 | B24: CUS00013 | C24: delivered | D24: 45794.691 | E24: 45794.775 | F24: 45796.691 | G24: 45800.691 | H24: 45802.691 | I24: KH0013 | J24: Sàn thương mại điện tử | K24: Chuyển khoản | L24: Miền Trung | M24: Đà Nẵng | N24: =IFERROR(VLOOKUP(I24,Customers!$B$2:$L$81,11,FALSE),"") -> EMP005 | O24: =SUMIF(OderItems!$A$2:$A$510,A24,OderItems!$L$2:$L$510) -> 3849000 | P24: =SUMIF(OderItems!$A$2:$A$510,A24,OderItems!$G$2:$G$510) -> 76000 | Q24: =SUMIF(OderItems!$A$2:$A$510,A24,OderItems!$K$2:$K$510) -> 0 | R24: =O24+P24-Q24 -> 3925000 | S24: VNĐ | T24: =AND(C24="delivered",I24<>"",R24>0) -> TRUE
A25: DH00024 | B25: CUS00032 | C25: canceled | D25: 46062.116 | H25: 46070.116 | I25: KH0032 | J25: Website | K25: Thẻ ngân hàng | L25: Miền Nam | M25: Bà Rịa - Vũng Tàu | N25: =IFERROR(VLOOKUP(I25,Customers!$B$2:$L$81,11,FALSE),"") -> EMP008 | O25: =SUMIF(OderItems!$A$2:$A$510,A25,OderItems!$L$2:$L$510) -> 1911000 | P25: =SUMIF(OderItems!$A$2:$A$510,A25,OderItems!$G$2:$G$510) -> 33000 | Q25: =SUMIF(OderItems!$A$2:$A$510,A25,OderItems!$K$2:$K$510) -> 0 | R25: =O25+P25-Q25 -> 1944000 | S25: VNĐ | T25: =AND(C25="delivered",I25<>"",R25>0) -> FALSE
A26: DH00025 | B26: CUS00017 | C26: delivered | D26: 45408.55 | E26: 45408.633 | F26: 45410.55 | G26: 45414.55 | H26: 45416.55 | I26: KH0017 | J26: Sàn thương mại điện tử | K26: COD | L26: Miền Nam | M26: Bà Rịa - Vũng Tàu | N26: =IFERROR(VLOOKUP(I26,Customers!$B$2:$L$81,11,FALSE),"") -> EMP001 | O26: =SUMIF(OderItems!$A$2:$A$510,A26,OderItems!$L$2:$L$510) -> 2710000 | P26: =SUMIF(OderItems!$A$2:$A$510,A26,OderItems!$G$2:$G$510) -> 47000 | Q26: =SUMIF(OderItems!$A$2:$A$510,A26,OderItems!$K$2:$K$510) -> 0 | R26: =O26+P26-Q26 -> 2757000 | S26: VNĐ | T26: =AND(C26="delivered",I26<>"",R26>0) -> TRUE
A27: DH00026 | B27: CUS00003 | C27: returned | D27: 45468.779 | E27: 45468.863 | F27: 45470.779 | G27: 45474.779 | H27: 45476.779 | I27: KH0003 | J27: Ứng dụng | K27: Thẻ ngân hàng | L27: Miền Trung | M27: Quảng Nam | N27: =IFERROR(VLOOKUP(I27,Customers!$B$2:$L$81,11,FALSE),"") -> EMP003 | O27: =SUMIF(OderItems!$A$2:$A$510,A27,OderItems!$L$2:$L$510) -> 1463000 | P27: =SUMIF(OderItems!$A$2:$A$510,A27,OderItems!$G$2:$G$510) -> 33000 | Q27: =SUMIF(OderItems!$A$2:$A$510,A27,OderItems!$K$2:$K$510) -> 0 | R27: =O27+P27-Q27 -> 1496000 | S27: VNĐ | T27: =AND(C27="delivered",I27<>"",R27>0) -> FALSE
A28: DH00027 | B28: CUS00047 | C28: delivered | D28: 46222.939 | E28: 46223.022 | F28: 46224.939 | G28: 46228.939 | H28: 46230.939 | I28: KH0047 | J28: Sàn thương mại điện tử | K28: COD | L28: Miền Bắc | M28: Hải Phòng | N28: =IFERROR(VLOOKUP(I28,Customers!$B$2:$L$81,11,FALSE),"") -> EMP007 | O28: =SUMIF(OderItems!$A$2:$A$510,A28,OderItems!$L$2:$L$510) -> 2329000 | P28: =SUMIF(OderItems!$A$2:$A$510,A28,OderItems!$G$2:$G$510) -> 48000 | Q28: =SUMIF(OderItems!$A$2:$A$510,A28,OderItems!$K$2:$K$510) -> 0 | R28: =O28+P28-Q28 -> 2377000 | S28: VNĐ | T28: =AND(C28="delivered",I28<>"",R28>0) -> TRUE
A29: DH00028 | B29: CUS00043 | C29: delivered | D29: 46098.255 | E29: 46098.338 | F29: 46100.255 | G29: 46104.255 | H29: 46106.255 | I29: KH0043 | J29: Ứng dụng | K29: Thẻ ngân hàng | L29: Miền Nam | M29: TP. Hồ Chí Minh | N29: =IFERROR(VLOOKUP(I29,Customers!$B$2:$L$81,11,FALSE),"") -> EMP003 | O29: =SUMIF(OderItems!$A$2:$A$510,A29,OderItems!$L$2:$L$510) -> 4420000 | P29: =SUMIF(OderItems!$A$2:$A$510,A29,OderItems!$G$2:$G$510) -> 61000 | Q29: =SUMIF(OderItems!$A$2:$A$510,A29,OderItems!$K$2:$K$510) -> 0 | R29: =O29+P29-Q29 -> 4481000 | S29: VNĐ | T29: =AND(C29="delivered",I29<>"",R29>0) -> TRUE
A30: DH00029 | B30: CUS00001 | C30: delivered | D30: 45617.08 | E30: 45617.164 | F30: 45619.08 | G30: 45623.08 | H30: 45625.08 | I30: KH0001 | J30: Cửa hàng | K30: COD | L30: Miền Trung | M30: Đà Nẵng | N30: =IFERROR(VLOOKUP(I30,Customers!$B$2:$L$81,11,FALSE),"") -> EMP001 | O30: =SUMIF(OderItems!$A$2:$A$510,A30,OderItems!$L$2:$L$510) -> 2250000 | P30: =SUMIF(OderItems!$A$2:$A$510,A30,OderItems!$G$2:$G$510) -> 32000 | Q30: =SUMIF(OderItems!$A$2:$A$510,A30,OderItems!$K$2:$K$510) -> 0 | R30: =O30+P30-Q30 -> 2282000 | S30: VNĐ | T30: =AND(C30="delivered",I30<>"",R30>0) -> TRUE
A31: DH00030 | B31: CUS00006 | C31: returned | D31: 45400.139 | E31: 45400.222 | F31: 45402.139 | G31: 45406.139 | H31: 45408.139 | I31: KH0006 | J31: Cửa hàng | K31: COD | L31: Miền Bắc | M31: Thái Nguyên | N31: =IFERROR(VLOOKUP(I31,Customers!$B$2:$L$81,11,FALSE),"") -> EMP006 | O31: =SUMIF(OderItems!$A$2:$A$510,A31,OderItems!$L$2:$L$510) -> 930000 | P31: =SUMIF(OderItems!$A$2:$A$510,A31,OderItems!$G$2:$G$510) -> 13000 | Q31: =SUMIF(OderItems!$A$2:$A$510,A31,OderItems!$K$2:$K$510) -> 0 | R31: =O31+P31-Q31 -> 943000 | S31: VNĐ | T31: =AND(C31="delivered",I31<>"",R31>0) -> FALSE
A32: DH00031 | B32: CUS00027 | C32: delivered | D32: 45412.909 | E32: 45412.992 | F32: 45414.909 | G32: 45418.909 | H32: 45420.909 | I32: KH0027 | J32: Sàn thương mại điện tử | K32: Thẻ ngân hàng | L32: Miền Nam | M32: Đồng Nai | N32: =IFERROR(VLOOKUP(I32,Customers!$B$2:$L$81,11,FALSE),"") -> EMP003 | O32: =SUMIF(OderItems!$A$2:$A$510,A32,OderItems!$L$2:$L$510) -> 2968000 | P32: =SUMIF(OderItems!$A$2:$A$510,A32,OderItems!$G$2:$G$510) -> 33000 | Q32: =SUMIF(OderItems!$A$2:$A$510,A32,OderItems!$K$2:$K$510) -> 0 | R32: =O32+P32-Q32 -> 3001000 | S32: VNĐ | T32: =AND(C32="delivered",I32<>"",R32>0) -> TRUE
A33: DH00032 | B33: CUS00056 | C33: delivered | D33: 45384.211 | E33: 45384.294 | F33: 45386.211 | G33: 45390.211 | H33: 45392.211 | I33: KH0056 | J33: Ứng dụng | K33: COD | L33: Miền Nam | M33: TP. Hồ Chí Minh | N33: =IFERROR(VLOOKUP(I33,Customers!$B$2:$L$81,11,FALSE),"") -> EMP008 | O33: =SUMIF(OderItems!$A$2:$A$510,A33,OderItems!$L$2:$L$510) -> 2661000 | P33: =SUMIF(OderItems!$A$2:$A$510,A33,OderItems!$G$2:$G$510) -> 44000 | Q33: =SUMIF(OderItems!$A$2:$A$510,A33,OderItems!$K$2:$K$510) -> 0 | R33: =O33+P33-Q33 -> 2705000 | S33: VNĐ | T33: =AND(C33="delivered",I33<>"",R33>0) -> TRUE
A34: DH00033 | B34: CUS00054 | C34: processing | D34: 46191.523 | E34: 46191.606 | H34: 46199.523 | I34: KH0054 | J34: Ứng dụng | K34: COD | L34: Miền Nam | M34: Cần Thơ | N34: =IFERROR(VLOOKUP(I34,Customers!$B$2:$L$81,11,FALSE),"") -> EMP006 | O34: =SUMIF(OderItems!$A$2:$A$510,A34,OderItems!$L$2:$L$510) -> 1430000 | P34: =SUMIF(OderItems!$A$2:$A$510,A34,OderItems!$G$2:$G$510) -> 20000 | Q34: =SUMIF(OderItems!$A$2:$A$510,A34,OderItems!$K$2:$K$510) -> 0 | R34: =O34+P34-Q34 -> 1450000 | S34: VNĐ | T34: =AND(C34="delivered",I34<>"",R34>0) -> FALSE
A35: DH00034 | B35: CUS00046 | C35: delivered | D35: 45988.34 | E35: 45988.423 | F35: 45990.34 | G35: 45994.34 | H35: 45996.34 | I35: KH0046 | J35: Ứng dụng | K35: Thẻ ngân hàng | L35: Miền Nam | M35: Bà Rịa - Vũng Tàu | N35: =IFERROR(VLOOKUP(I35,Customers!$B$2:$L$81,11,FALSE),"") -> EMP006 | O35: =SUMIF(OderItems!$A$2:$A$510,A35,OderItems!$L$2:$L$510) -> 1692000 | P35: =SUMIF(OderItems!$A$2:$A$510,A35,OderItems!$G$2:$G$510) -> 32000 | Q35: =SUMIF(OderItems!$A$2:$A$510,A35,OderItems!$K$2:$K$510) -> 0 | R35: =O35+P35-Q35 -> 1724000 | S35: VNĐ | T35: =AND(C35="delivered",I35<>"",R35>0) -> TRUE
A36: DH00035 | B36: CUS00010 | C36: delivered | D36: 45723.27 | E36: 45723.353 | F36: 45725.27 | G36: 45729.27 | H36: 45731.27 | I36: KH0010 | J36: Website | K36: Ví điện tử | L36: Miền Nam | M36: Bà Rịa - Vũng Tàu | N36: =IFERROR(VLOOKUP(I36,Customers!$B$2:$L$81,11,FALSE),"") -> EMP002 | O36: =SUMIF(OderItems!$A$2:$A$510,A36,OderItems!$L$2:$L$510) -> 1350000 | P36: =SUMIF(OderItems!$A$2:$A$510,A36,OderItems!$G$2:$G$510) -> 27000 | Q36: =SUMIF(OderItems!$A$2:$A$510,A36,OderItems!$K$2:$K$510) -> 0 | R36: =O36+P36-Q36 -> 1377000 | S36: VNĐ | T36: =AND(C36="delivered",I36<>"",R36>0) -> TRUE
A37: DH00036 | B37: CUS00015 | C37: canceled | D37: 45519.575 | H37: 45527.575 | I37: KH0015 | J37: Sàn thương mại điện tử | K37: Ví điện tử | L37: Miền Nam | M37: Long An | N37: =IFERROR(VLOOKUP(I37,Customers!$B$2:$L$81,11,FALSE),"") -> EMP007 | O37: =SUMIF(OderItems!$A$2:$A$510,A37,OderItems!$L$2:$L$510) -> 752000 | P37: =SUMIF(OderItems!$A$2:$A$510,A37,OderItems!$G$2:$G$510) -> 20000 | Q37: =SUMIF(OderItems!$A$2:$A$510,A37,OderItems!$K$2:$K$510) -> 0 | R37: =O37+P37-Q37 -> 772000 | S37: VNĐ | T37: =AND(C37="delivered",I37<>"",R37>0) -> FALSE
A38: DH00037 | B38: CUS00018 | C38: processing | D38: 45419.828 | E38: 45419.911 | H38: 45427.828 | I38: KH0018 | J38: Website | K38: Thẻ ngân hàng | L38: Miền Nam | M38: Long An | N38: =IFERROR(VLOOKUP(I38,Customers!$B$2:$L$81,11,FALSE),"") -> EMP002 | O38: =SUMIF(OderItems!$A$2:$A$510,A38,OderItems!$L$2:$L$510) -> 2056000 | P38: =SUMIF(OderItems!$A$2:$A$510,A38,OderItems!$G$2:$G$510) -> 29000 | Q38: =SUMIF(OderItems!$A$2:$A$510,A38,OderItems!$K$2:$K$510) -> 0 | R38: =O38+P38-Q38 -> 2085000 | S38: VNĐ | T38: =AND(C38="delivered",I38<>"",R38>0) -> FALSE
A39: DH00038 | B39: CUS00052 | C39: delivered | D39: 45918.197 | E39: 45918.28 | F39: 45920.197 | G39: 45924.197 | H39: 45926.197 | I39: KH0052 | J39: Website | K39: COD | L39: Miền Nam | M39: Bà Rịa - Vũng Tàu | N39: =IFERROR(VLOOKUP(I39,Customers!$B$2:$L$81,11,FALSE),"") -> EMP004 | O39: =SUMIF(OderItems!$A$2:$A$510,A39,OderItems!$L$2:$L$510) -> 1092000 | P39: =SUMIF(OderItems!$A$2:$A$510,A39,OderItems!$G$2:$G$510) -> 17000 | Q39: =SUMIF(OderItems!$A$2:$A$510,A39,OderItems!$K$2:$K$510) -> 0 | R39: =O39+P39-Q39 -> 1109000 | S39: VNĐ | T39: =AND(C39="delivered",I39<>"",R39>0) -> TRUE
A40: DH00039 | B40: CUS00040 | C40: processing | D40: 45768.864 | E40: 45768.947 | H40: 45776.864 | I40: KH0040 | J40: Ứng dụng | K40: Thẻ ngân hàng | L40: Miền Trung | M40: Đà Nẵng | N40: =IFERROR(VLOOKUP(I40,Customers!$B$2:$L$81,11,FALSE),"") -> EMP008 | O40: =SUMIF(OderItems!$A$2:$A$510,A40,OderItems!$L$2:$L$510) -> 1419000 | P40: =SUMIF(OderItems!$A$2:$A$510,A40,OderItems!$G$2:$G$510) -> 56000 | Q40: =SUMIF(OderItems!$A$2:$A$510,A40,OderItems!$K$2:$K$510) -> 0 | R40: =O40+P40-Q40 -> 1475000 | S40: VNĐ | T40: =AND(C40="delivered",I40<>"",R40>0) -> FALSE
A41: DH00040 | B41: CUS00046 | C41: returned | D41: 45836.629 | E41: 45836.712 | F41: 45838.629 | G41: 45842.629 | H41: 45844.629 | I41: KH0046 | J41: Cửa hàng | K41: Chuyển khoản | L41: Miền Nam | M41: Bà Rịa - Vũng Tàu | N41: =IFERROR(VLOOKUP(I41,Customers!$B$2:$L$81,11,FALSE),"") -> EMP006 | O41: =SUMIF(OderItems!$A$2:$A$510,A41,OderItems!$L$2:$L$510) -> 1668000 | P41: =SUMIF(OderItems!$A$2:$A$510,A41,OderItems!$G$2:$G$510) -> 27000 | Q41: =SUMIF(OderItems!$A$2:$A$510,A41,OderItems!$K$2:$K$510) -> 0 | R41: =O41+P41-Q41 -> 1695000 | S41: VNĐ | T41: =AND(C41="delivered",I41<>"",R41>0) -> FALSE
A42: DH00041 | B42: CUS00077 | C42: processing | D42: 45633.099 | E42: 45633.183 | H42: 45641.099 | I42: KH0077 | J42: Ứng dụng | K42: Chuyển khoản | L42: Miền Nam | M42: Đồng Nai | N42: =IFERROR(VLOOKUP(I42,Customers!$B$2:$L$81,11,FALSE),"") -> EMP005 | O42: =SUMIF(OderItems!$A$2:$A$510,A42,OderItems!$L$2:$L$510) -> 4145000 | P42: =SUMIF(OderItems!$A$2:$A$510,A42,OderItems!$G$2:$G$510) -> 44000 | Q42: =SUMIF(OderItems!$A$2:$A$510,A42,OderItems!$K$2:$K$510) -> 0 | R42: =O42+P42-Q42 -> 4189000 | S42: VNĐ | T42: =AND(C42="delivered",I42<>"",R42>0) -> FALSE
A43: DH00042 | B43: CUS00022 | C43: delivered | D43: 45442.865 | E43: 45442.949 | F43: 45444.865 | G43: 45448.865 | H43: 45450.865 | I43: KH0022 | J43: Sàn thương mại điện tử | K43: Thẻ ngân hàng | L43: Miền Nam | M43: Đồng Nai | N43: =IFERROR(VLOOKUP(I43,Customers!$B$2:$L$81,11,FALSE),"") -> EMP006 | O43: =SUMIF(OderItems!$A$2:$A$510,A43,OderItems!$L$2:$L$510) -> 504000 | P43: =SUMIF(OderItems!$A$2:$A$510,A43,OderItems!$G$2:$G$510) -> 5000 | Q43: =SUMIF(OderItems!$A$2:$A$510,A43,OderItems!$K$2:$K$510) -> 0 | R43: =O43+P43-Q43 -> 509000 | S43: VNĐ | T43: =AND(C43="delivered",I43<>"",R43>0) -> TRUE
A44: DH00043 | B44: CUS00027 | C44: delivered | D44: 45966.3 | E44: 45966.383 | F44: 45968.3 | G44: 45972.3 | H44: 45974.3 | I44: KH0027 | J44: Cửa hàng | K44: Ví điện tử | L44: Miền Nam | M44: Đồng Nai | N44: =IFERROR(VLOOKUP(I44,Customers!$B$2:$L$81,11,FALSE),"") -> EMP003 | O44: =SUMIF(OderItems!$A$2:$A$510,A44,OderItems!$L$2:$L$510) -> 2016000 | P44: =SUMIF(OderItems!$A$2:$A$510,A44,OderItems!$G$2:$G$510) -> 53000 | Q44: =SUMIF(OderItems!$A$2:$A$510,A44,OderItems!$K$2:$K$510) -> 0 | R44: =O44+P44-Q44 -> 2069000 | S44: VNĐ | T44: =AND(C44="delivered",I44<>"",R44>0) -> TRUE
A45: DH00044 | B45: CUS00016 | C45: delivered | D45: 45300.773 | E45: 45300.856 | F45: 45302.773 | G45: 45306.773 | H45: 45308.773 | I45: KH0016 | J45: Cửa hàng | K45: Thẻ ngân hàng | L45: Miền Nam | M45: Cần Thơ | N45: =IFERROR(VLOOKUP(I45,Customers!$B$2:$L$81,11,FALSE),"") -> EMP008 | O45: =SUMIF(OderItems!$A$2:$A$510,A45,OderItems!$L$2:$L$510) -> 902000 | P45: =SUMIF(OderItems!$A$2:$A$510,A45,OderItems!$G$2:$G$510) -> 14000 | Q45: =SUMIF(OderItems!$A$2:$A$510,A45,OderItems!$K$2:$K$510) -> 0 | R45: =O45+P45-Q45 -> 916000 | S45: VNĐ | T45: =AND(C45="delivered",I45<>"",R45>0) -> TRUE
A46: DH00045 | B46: CUS00014 | C46: delivered | D46: 46061.379 | E46: 46061.462 | F46: 46063.379 | G46: 46067.379 | H46: 46069.379 | I46: KH0014 | J46: Ứng dụng | K46: Ví điện tử | L46: Miền Trung | M46: Thừa Thiên Huế | N46: =IFERROR(VLOOKUP(I46,Customers!$B$2:$L$81,11,FALSE),"") -> EMP006 | O46: =SUMIF(OderItems!$A$2:$A$510,A46,OderItems!$L$2:$L$510) -> 971000 | P46: =SUMIF(OderItems!$A$2:$A$510,A46,OderItems!$G$2:$G$510) -> 21000 | Q46: =SUMIF(OderItems!$A$2:$A$510,A46,OderItems!$K$2:$K$510) -> 0 | R46: =O46+P46-Q46 -> 992000 | S46: VNĐ | T46: =AND(C46="delivered",I46<>"",R46>0) -> TRUE
A47: DH00046 | B47: CUS00025 | C47: returned | D47: 45400.533 | E47: 45400.616 | F47: 45402.533 | G47: 45406.533 | H47: 45408.533 | I47: KH0025 | J47: Cửa hàng | K47: COD | L47: Miền Bắc | M47: Hà Nội | N47: =IFERROR(VLOOKUP(I47,Customers!$B$2:$L$81,11,FALSE),"") -> EMP001 | O47: =SUMIF(OderItems!$A$2:$A$510,A47,OderItems!$L$2:$L$510) -> 900000 | P47: =SUMIF(OderItems!$A$2:$A$510,A47,OderItems!$G$2:$G$510) -> 18000 | Q47: =SUMIF(OderItems!$A$2:$A$510,A47,OderItems!$K$2:$K$510) -> 0 | R47: =O47+P47-Q47 -> 918000 | S47: VNĐ | T47: =AND(C47="delivered",I47<>"",R47>0) -> FALSE
A48: DH00047 | B48: CUS00008 | C48: delivered | D48: 45546.132 | E48: 45546.215 | F48: 45548.132 | G48: 45552.132 | H48: 45554.132 | I48: KH0008 | J48: Sàn thương mại điện tử | K48: Ví điện tử | L48: Miền Trung | M48: Khánh Hòa | N48: =IFERROR(VLOOKUP(I48,Customers!$B$2:$L$81,11,FALSE),"") -> EMP008 | O48: =SUMIF(OderItems!$A$2:$A$510,A48,OderItems!$L$2:$L$510) -> 447000 | P48: =SUMIF(OderItems!$A$2:$A$510,A48,OderItems!$G$2:$G$510) -> 7000 | Q48: =SUMIF(OderItems!$A$2:$A$510,A48,OderItems!$K$2:$K$510) -> 0 | R48: =O48+P48-Q48 -> 454000 | S48: VNĐ | T48: =AND(C48="delivered",I48<>"",R48>0) -> TRUE
A49: DH00048 | B49: CUS00013 | C49: delivered | D49: 45859.891 | E49: 45859.974 | F49: 45861.891 | G49: 45865.891 | H49: 45867.891 | I49: KH0013 | J49: Sàn thương mại điện tử | K49: Chuyển khoản | L49: Miền Trung | M49: Đà Nẵng | N49: =IFERROR(VLOOKUP(I49,Customers!$B$2:$L$81,11,FALSE),"") -> EMP005 | O49: =SUMIF(OderItems!$A$2:$A$510,A49,OderItems!$L$2:$L$510) -> 674000 | P49: =SUMIF(OderItems!$A$2:$A$510,A49,OderItems!$G$2:$G$510) -> 14000 | Q49: =SUMIF(OderItems!$A$2:$A$510,A49,OderItems!$K$2:$K$510) -> 0 | R49: =O49+P49-Q49 -> 688000 | S49: VNĐ | T49: =AND(C49="delivered",I49<>"",R49>0) -> TRUE
A50: DH00049 | B50: CUS00057 | C50: delivered | D50: 45378.459 | E50: 45378.542 | F50: 45380.459 | G50: 45384.459 | H50: 45386.459 | I50: KH0057 | J50: Ứng dụng | K50: Ví điện tử | L50: Miền Bắc | M50: Thái Nguyên | N50: =IFERROR(VLOOKUP(I50,Customers!$B$2:$L$81,11,FALSE),"") -> EMP001 | O50: =SUMIF(OderItems!$A$2:$A$510,A50,OderItems!$L$2:$L$510) -> 576000 | P50: =SUMIF(OderItems!$A$2:$A$510,A50,OderItems!$G$2:$G$510) -> 6000 | Q50: =SUMIF(OderItems!$A$2:$A$510,A50,OderItems!$K$2:$K$510) -> 0 | R50: =O50+P50-Q50 -> 582000 | S50: VNĐ | T50: =AND(C50="delivered",I50<>"",R50>0) -> TRUE
A51: DH00050 | B51: CUS00008 | C51: delivered | D51: 45467.874 | E51: 45467.957 | F51: 45469.874 | G51: 45473.874 | H51: 45475.874 | I51: KH0008 | J51: Cửa hàng | K51: Ví điện tử | L51: Miền Trung | M51: Khánh Hòa | N51: =IFERROR(VLOOKUP(I51,Customers!$B$2:$L$81,11,FALSE),"") -> EMP008 | O51: =SUMIF(OderItems!$A$2:$A$510,A51,OderItems!$L$2:$L$510) -> 3097000 | P51: =SUMIF(OderItems!$A$2:$A$510,A51,OderItems!$G$2:$G$510) -> 62000 | Q51: =SUMIF(OderItems!$A$2:$A$510,A51,OderItems!$K$2:$K$510) -> 0 | R51: =O51+P51-Q51 -> 3159000 | S51: VNĐ | T51: =AND(C51="delivered",I51<>"",R51>0) -> TRUE
A52: DH00051 | B52: CUS00032 | C52: canceled | D52: 45631.128 | H52: 45639.128 | I52: KH0032 | J52: Website | K52: Ví điện tử | L52: Miền Nam | M52: Bà Rịa - Vũng Tàu | N52: =IFERROR(VLOOKUP(I52,Customers!$B$2:$L$81,11,FALSE),"") -> EMP008 | O52: =SUMIF(OderItems!$A$2:$A$510,A52,OderItems!$L$2:$L$510) -> 2000000 | P52: =SUMIF(OderItems!$A$2:$A$510,A52,OderItems!$G$2:$G$510) -> 31000 | Q52: =SUMIF(OderItems!$A$2:$A$510,A52,OderItems!$K$2:$K$510) -> 0 | R52: =O52+P52-Q52 -> 2031000 | S52: VNĐ | T52: =AND(C52="delivered",I52<>"",R52>0) -> FALSE
A53: DH00052 | B53: CUS00035 | C53: delivered | D53: 46173.138 | E53: 46173.221 | F53: 46175.138 | G53: 46179.138 | H53: 46181.138 | I53: KH0035 | J53: Cửa hàng | K53: COD | L53: Miền Nam | M53: Bình Dương | N53: =IFERROR(VLOOKUP(I53,Customers!$B$2:$L$81,11,FALSE),"") -> EMP003 | O53: =SUMIF(OderItems!$A$2:$A$510,A53,OderItems!$L$2:$L$510) -> 1345000 | P53: =SUMIF(OderItems!$A$2:$A$510,A53,OderItems!$G$2:$G$510) -> 12000 | Q53: =SUMIF(OderItems!$A$2:$A$510,A53,OderItems!$K$2:$K$510) -> 0 | R53: =O53+P53-Q53 -> 1357000 | S53: VNĐ | T53: =AND(C53="delivered",I53<>"",R53>0) -> TRUE
A54: DH00053 | B54: CUS00026 | C54: returned | D54: 45790.635 | E54: 45790.718 | F54: 45792.635 | G54: 45796.635 | H54: 45798.635 | I54: KH0026 | J54: Sàn thương mại điện tử | K54: Chuyển khoản | L54: Miền Trung | M54: Bình Định | N54: =IFERROR(VLOOKUP(I54,Customers!$B$2:$L$81,11,FALSE),"") -> EMP002 | O54: =SUMIF(OderItems!$A$2:$A$510,A54,OderItems!$L$2:$L$510) -> 819000 | P54: =SUMIF(OderItems!$A$2:$A$510,A54,OderItems!$G$2:$G$510) -> 18000 | Q54: =SUMIF(OderItems!$A$2:$A$510,A54,OderItems!$K$2:$K$510) -> 0 | R54: =O54+P54-Q54 -> 837000 | S54: VNĐ | T54: =AND(C54="delivered",I54<>"",R54>0) -> FALSE
A55: DH00054 | B55: CUS00015 | C55: delivered | D55: 45506.396 | E55: 45506.479 | F55: 45508.396 | G55: 45512.396 | H55: 45514.396 | I55: KH0015 | J55: Sàn thương mại điện tử | K55: Thẻ ngân hàng | L55: Miền Nam | M55: Long An | N55: =IFERROR(VLOOKUP(I55,Customers!$B$2:$L$81,11,FALSE),"") -> EMP007 | O55: =SUMIF(OderItems!$A$2:$A$510,A55,OderItems!$L$2:$L$510) -> 440000 | P55: =SUMIF(OderItems!$A$2:$A$510,A55,OderItems!$G$2:$G$510) -> 7000 | Q55: =SUMIF(OderItems!$A$2:$A$510,A55,OderItems!$K$2:$K$510) -> 0 | R55: =O55+P55-Q55 -> 447000 | S55: VNĐ | T55: =AND(C55="delivered",I55<>"",R55>0) -> TRUE
A56: DH00055 | B56: CUS00031 | C56: delivered | D56: 45779.035 | E56: 45779.119 | F56: 45781.035 | G56: 45785.035 | H56: 45787.035 | I56: KH0031 | J56: Ứng dụng | K56: Ví điện tử | L56: Miền Nam | M56: Long An | N56: =IFERROR(VLOOKUP(I56,Customers!$B$2:$L$81,11,FALSE),"") -> EMP007 | O56: =SUMIF(OderItems!$A$2:$A$510,A56,OderItems!$L$2:$L$510) -> 980000 | P56: =SUMIF(OderItems!$A$2:$A$510,A56,OderItems!$G$2:$G$510) -> 16000 | Q56: =SUMIF(OderItems!$A$2:$A$510,A56,OderItems!$K$2:$K$510) -> 0 | R56: =O56+P56-Q56 -> 996000 | S56: VNĐ | T56: =AND(C56="delivered",I56<>"",R56>0) -> TRUE
A57: DH00056 | B57: CUS00029 | C57: delivered | D57: 45359.129 | E57: 45359.213 | F57: 45361.129 | G57: 45365.129 | H57: 45367.129 | I57: KH0029 | J57: Ứng dụng | K57: Thẻ ngân hàng | L57: Miền Nam | M57: Cần Thơ | N57: =IFERROR(VLOOKUP(I57,Customers!$B$2:$L$81,11,FALSE),"") -> EMP005 | O57: =SUMIF(OderItems!$A$2:$A$510,A57,OderItems!$L$2:$L$510) -> 1385000 | P57: =SUMIF(OderItems!$A$2:$A$510,A57,OderItems!$G$2:$G$510) -> 26000 | Q57: =SUMIF(OderItems!$A$2:$A$510,A57,OderItems!$K$2:$K$510) -> 0 | R57: =O57+P57-Q57 -> 1411000 | S57: VNĐ | T57: =AND(C57="delivered",I57<>"",R57>0) -> TRUE
A58: DH00057 | B58: CUS00018 | C58: delivered | D58: 45937.755 | E58: 45937.838 | F58: 45939.755 | G58: 45943.755 | H58: 45945.755 | I58: KH0018 | J58: Cửa hàng | K58: Thẻ ngân hàng | L58: Miền Nam | M58: Long An | N58: =IFERROR(VLOOKUP(I58,Customers!$B$2:$L$81,11,FALSE),"") -> EMP002 | O58: =SUMIF(OderItems!$A$2:$A$510,A58,OderItems!$L$2:$L$510) -> 2380000 | P58: =SUMIF(OderItems!$A$2:$A$510,A58,OderItems!$G$2:$G$510) -> 48000 | Q58: =SUMIF(OderItems!$A$2:$A$510,A58,OderItems!$K$2:$K$510) -> 0 | R58: =O58+P58-Q58 -> 2428000 | S58: VNĐ | T58: =AND(C58="delivered",I58<>"",R58>0) -> TRUE
A59: DH00058 | B59: CUS00050 | C59: delivered | D59: 45679.5 | E59: 45679.583 | F59: 45681.5 | G59: 45685.5 | H59: 45687.5 | I59: KH0050 | J59: Sàn thương mại điện tử | K59: Chuyển khoản | L59: Miền Nam | M59: Cần Thơ | N59: =IFERROR(VLOOKUP(I59,Customers!$B$2:$L$81,11,FALSE),"") -> EMP002 | O59: =SUMIF(OderItems!$A$2:$A$510,A59,OderItems!$L$2:$L$510) -> 3000000 | P59: =SUMIF(OderItems!$A$2:$A$510,A59,OderItems!$G$2:$G$510) -> 39000 | Q59: =SUMIF(OderItems!$A$2:$A$510,A59,OderItems!$K$2:$K$510) -> 0 | R59: =O59+P59-Q59 -> 3039000 | S59: VNĐ | T59: =AND(C59="delivered",I59<>"",R59>0) -> TRUE
A60: DH00059 | B60: CUS00013 | C60: delivered | D60: 46148.116 | E60: 46148.199 | F60: 46150.116 | G60: 46154.116 | H60: 46156.116 | I60: KH0013 | J60: Ứng dụng | K60: Ví điện tử | L60: Miền Trung | M60: Đà Nẵng | N60: =IFERROR(VLOOKUP(I60,Customers!$B$2:$L$81,11,FALSE),"") -> EMP005 | O60: =SUMIF(OderItems!$A$2:$A$510,A60,OderItems!$L$2:$L$510) -> 702000 | P60: =SUMIF(OderItems!$A$2:$A$510,A60,OderItems!$G$2:$G$510) -> 15000 | Q60: =SUMIF(OderItems!$A$2:$A$510,A60,OderItems!$K$2:$K$510) -> 0 | R60: =O60+P60-Q60 -> 717000 | S60: VNĐ | T60: =AND(C60="delivered",I60<>"",R60>0) -> TRUE
A61: DH00060 | B61: CUS00053 | C61: canceled | D61: 46127.367 | H61: 46135.367 | I61: KH0053 | J61: Website | K61: COD | L61: Miền Trung | M61: Thừa Thiên Huế | N61: =IFERROR(VLOOKUP(I61,Customers!$B$2:$L$81,11,FALSE),"") -> EMP005 | O61: =SUMIF(OderItems!$A$2:$A$510,A61,OderItems!$L$2:$L$510) -> 2171000 | P61: =SUMIF(OderItems!$A$2:$A$510,A61,OderItems!$G$2:$G$510) -> 38000 | Q61: =SUMIF(OderItems!$A$2:$A$510,A61,OderItems!$K$2:$K$510) -> 0 | R61: =O61+P61-Q61 -> 2209000 | S61: VNĐ | T61: =AND(C61="delivered",I61<>"",R61>0) -> FALSE
A62: DH00061 | B62: CUS00052 | C62: delivered | D62: 45769.128 | E62: 45769.212 | F62: 45771.128 | G62: 45775.128 | H62: 45777.128 | I62: KH0052 | J62: Sàn thương mại điện tử | K62: Thẻ ngân hàng | L62: Miền Nam | M62: Bà Rịa - Vũng Tàu | N62: =IFERROR(VLOOKUP(I62,Customers!$B$2:$L$81,11,FALSE),"") -> EMP004 | O62: =SUMIF(OderItems!$A$2:$A$510,A62,OderItems!$L$2:$L$510) -> 1839000 | P62: =SUMIF(OderItems!$A$2:$A$510,A62,OderItems!$G$2:$G$510) -> 50000 | Q62: =SUMIF(OderItems!$A$2:$A$510,A62,OderItems!$K$2:$K$510) -> 0 | R62: =O62+P62-Q62 -> 1889000 | S62: VNĐ | T62: =AND(C62="delivered",I62<>"",R62>0) -> TRUE
A63: DH00062 | B63: CUS00001 | C63: canceled | D63: 45929.42 | H63: 45937.42 | I63: KH0001 | J63: Cửa hàng | K63: Ví điện tử | L63: Miền Trung | M63: Đà Nẵng | N63: =IFERROR(VLOOKUP(I63,Customers!$B$2:$L$81,11,FALSE),"") -> EMP001 | O63: =SUMIF(OderItems!$A$2:$A$510,A63,OderItems!$L$2:$L$510) -> 2300000 | P63: =SUMIF(OderItems!$A$2:$A$510,A63,OderItems!$G$2:$G$510) -> 29000 | Q63: =SUMIF(OderItems!$A$2:$A$510,A63,OderItems!$K$2:$K$510) -> 0 | R63: =O63+P63-Q63 -> 2329000 | S63: VNĐ | T63: =AND(C63="delivered",I63<>"",R63>0) -> FALSE
A64: DH00063 | B64: CUS00013 | C64: processing | D64: 45824.218 | E64: 45824.301 | H64: 45832.218 | I64: KH0013 | J64: Sàn thương mại điện tử | K64: Ví điện tử | L64: Miền Trung | M64: Đà Nẵng | N64: =IFERROR(VLOOKUP(I64,Customers!$B$2:$L$81,11,FALSE),"") -> EMP005 | O64: =SUMIF(OderItems!$A$2:$A$510,A64,OderItems!$L$2:$L$510) -> 2884000 | P64: =SUMIF(OderItems!$A$2:$A$510,A64,OderItems!$G$2:$G$510) -> 53000 | Q64: =SUMIF(OderItems!$A$2:$A$510,A64,OderItems!$K$2:$K$510) -> 0 | R64: =O64+P64-Q64 -> 2937000 | S64: VNĐ | T64: =AND(C64="delivered",I64<>"",R64>0) -> FALSE
A65: DH00064 | B65: CUS00047 | C65: returned | D65: 45688.997 | E65: 45689.08 | F65: 45690.997 | G65: 45694.997 | H65: 45696.997 | I65: KH0047 | J65: Ứng dụng | K65: Chuyển khoản | L65: Miền Bắc | M65: Hải Phòng | N65: =IFERROR(VLOOKUP(I65,Customers!$B$2:$L$81,11,FALSE),"") -> EMP007 | O65: =SUMIF(OderItems!$A$2:$A$510,A65,OderItems!$L$2:$L$510) -> 2352000 | P65: =SUMIF(OderItems!$A$2:$A$510,A65,OderItems!$G$2:$G$510) -> 29000 | Q65: =SUMIF(OderItems!$A$2:$A$510,A65,OderItems!$K$2:$K$510) -> 0 | R65: =O65+P65-Q65 -> 2381000 | S65: VNĐ | T65: =AND(C65="delivered",I65<>"",R65>0) -> FALSE
A66: DH00065 | B66: CUS00032 | C66: delivered | D66: 45519.935 | E66: 45520.018 | F66: 45521.935 | G66: 45525.935 | H66: 45527.935 | I66: KH0032 | J66: Website | K66: Thẻ ngân hàng | L66: Miền Nam | M66: Bà Rịa - Vũng Tàu | N66: =IFERROR(VLOOKUP(I66,Customers!$B$2:$L$81,11,FALSE),"") -> EMP008 | O66: =SUMIF(OderItems!$A$2:$A$510,A66,OderItems!$L$2:$L$510) -> 851000 | P66: =SUMIF(OderItems!$A$2:$A$510,A66,OderItems!$G$2:$G$510) -> 28000 | Q66: =SUMIF(OderItems!$A$2:$A$510,A66,OderItems!$K$2:$K$510) -> 0 | R66: =O66+P66-Q66 -> 879000 | S66: VNĐ | T66: =AND(C66="delivered",I66<>"",R66>0) -> TRUE
A67: DH00066 | B67: CUS00058 | C67: delivered | D67: 45905.016 | E67: 45905.099 | F67: 45907.016 | G67: 45911.016 | H67: 45913.016 | I67: KH0058 | J67: Cửa hàng | K67: COD | L67: Miền Trung | M67: Nghệ An | N67: =IFERROR(VLOOKUP(I67,Customers!$B$2:$L$81,11,FALSE),"") -> EMP002 | O67: =SUMIF(OderItems!$A$2:$A$510,A67,OderItems!$L$2:$L$510) -> 1368000 | P67: =SUMIF(OderItems!$A$2:$A$510,A67,OderItems!$G$2:$G$510) -> 34000 | Q67: =SUMIF(OderItems!$A$2:$A$510,A67,OderItems!$K$2:$K$510) -> 0 | R67: =O67+P67-Q67 -> 1402000 | S67: VNĐ | T67: =AND(C67="delivered",I67<>"",R67>0) -> TRUE
A68: DH00067 | B68: CUS00012 | C68: delivered | D68: 45981.436 | E68: 45981.519 | F68: 45983.436 | G68: 45987.436 | H68: 45989.436 | I68: KH0012 | J68: Sàn thương mại điện tử | K68: Ví điện tử | L68: Miền Bắc | M68: Quảng Ninh | N68: =IFERROR(VLOOKUP(I68,Customers!$B$2:$L$81,11,FALSE),"") -> EMP004 | O68: =SUMIF(OderItems!$A$2:$A$510,A68,OderItems!$L$2:$L$510) -> 2309000 | P68: =SUMIF(OderItems!$A$2:$A$510,A68,OderItems!$G$2:$G$510) -> 42000 | Q68: =SUMIF(OderItems!$A$2:$A$510,A68,OderItems!$K$2:$K$510) -> 0 | R68: =O68+P68-Q68 -> 2351000 | S68: VNĐ | T68: =AND(C68="delivered",I68<>"",R68>0) -> TRUE
A69: DH00068 | B69: CUS00024 | C69: delivered | D69: 45489.725 | E69: 45489.808 | F69: 45491.725 | G69: 45495.725 | H69: 45497.725 | I69: KH0024 | J69: Sàn thương mại điện tử | K69: Chuyển khoản | L69: Miền Bắc | M69: Nam Định | N69: =IFERROR(VLOOKUP(I69,Customers!$B$2:$L$81,11,FALSE),"") -> EMP008 | O69: =SUMIF(OderItems!$A$2:$A$510,A69,OderItems!$L$2:$L$510) -> 1215000 | P69: =SUMIF(OderItems!$A$2:$A$510,A69,OderItems!$G$2:$G$510) -> 28000 | Q69: =SUMIF(OderItems!$A$2:$A$510,A69,OderItems!$K$2:$K$510) -> 0 | R69: =O69+P69-Q69 -> 1243000 | S69: VNĐ | T69: =AND(C69="delivered",I69<>"",R69>0) -> TRUE
A70: DH00069 | B70: CUS00002 | C70: delivered | D70: 46165.922 | E70: 46166.005 | F70: 46167.922 | G70: 46171.922 | H70: 46173.922 | I70: KH0002 | J70: Sàn thương mại điện tử | K70: Ví điện tử | L70: Miền Bắc | M70: Hà Nội | N70: =IFERROR(VLOOKUP(I70,Customers!$B$2:$L$81,11,FALSE),"") -> EMP002 | O70: =SUMIF(OderItems!$A$2:$A$510,A70,OderItems!$L$2:$L$510) -> 2277000 | P70: =SUMIF(OderItems!$A$2:$A$510,A70,OderItems!$G$2:$G$510) -> 38000 | Q70: =SUMIF(OderItems!$A$2:$A$510,A70,OderItems!$K$2:$K$510) -> 0 | R70: =O70+P70-Q70 -> 2315000 | S70: VNĐ | T70: =AND(C70="delivered",I70<>"",R70>0) -> TRUE
A71: DH00070 | B71: CUS00006 | C71: delivered | D71: 46160.596 | E71: 46160.679 | F71: 46162.596 | G71: 46166.596 | H71: 46168.596 | I71: KH0006 | J71: Website | K71: Thẻ ngân hàng | L71: Miền Bắc | M71: Thái Nguyên | N71: =IFERROR(VLOOKUP(I71,Customers!$B$2:$L$81,11,FALSE),"") -> EMP006 | O71: =SUMIF(OderItems!$A$2:$A$510,A71,OderItems!$L$2:$L$510) -> 1263000 | P71: =SUMIF(OderItems!$A$2:$A$510,A71,OderItems!$G$2:$G$510) -> 22000 | Q71: =SUMIF(OderItems!$A$2:$A$510,A71,OderItems!$K$2:$K$510) -> 0 | R71: =O71+P71-Q71 -> 1285000 | S71: VNĐ | T71: =AND(C71="delivered",I71<>"",R71>0) -> TRUE
A72: DH00071 | B72: CUS00047 | C72: delivered | D72: 45330.518 | E72: 45330.601 | F72: 45332.518 | G72: 45336.518 | H72: 45338.518 | I72: KH0047 | J72: Website | K72: Thẻ ngân hàng | L72: Miền Bắc | M72: Hải Phòng | N72: =IFERROR(VLOOKUP(I72,Customers!$B$2:$L$81,11,FALSE),"") -> EMP007 | O72: =SUMIF(OderItems!$A$2:$A$510,A72,OderItems!$L$2:$L$510) -> 1976000 | P72: =SUMIF(OderItems!$A$2:$A$510,A72,OderItems!$G$2:$G$510) -> 25000 | Q72: =SUMIF(OderItems!$A$2:$A$510,A72,OderItems!$K$2:$K$510) -> 0 | R72: =O72+P72-Q72 -> 2001000 | S72: VNĐ | T72: =AND(C72="delivered",I72<>"",R72>0) -> TRUE
A73: DH00072 | B73: CUS00076 | C73: delivered | D73: 45403.726 | E73: 45403.809 | F73: 45405.726 | G73: 45409.726 | H73: 45411.726 | I73: KH0076 | J73: Sàn thương mại điện tử | K73: COD | L73: Miền Trung | M73: Khánh Hòa | N73: =IFERROR(VLOOKUP(I73,Customers!$B$2:$L$81,11,FALSE),"") -> EMP004 | O73: =SUMIF(OderItems!$A$2:$A$510,A73,OderItems!$L$2:$L$510) -> 555000 | P73: =SUMIF(OderItems!$A$2:$A$510,A73,OderItems!$G$2:$G$510) -> 7000 | Q73: =SUMIF(OderItems!$A$2:$A$510,A73,OderItems!$K$2:$K$510) -> 0 | R73: =O73+P73-Q73 -> 562000 | S73: VNĐ | T73: =AND(C73="delivered",I73<>"",R73>0) -> TRUE
A74: DH00073 | B74: CUS00055 | C74: delivered | D74: 45638.818 | E74: 45638.901 | F74: 45640.818 | G74: 45644.818 | H74: 45646.818 | I74: KH0055 | J74: Cửa hàng | K74: Ví điện tử | L74: Miền Nam | M74: Long An | N74: =IFERROR(VLOOKUP(I74,Customers!$B$2:$L$81,11,FALSE),"") -> EMP007 | O74: =SUMIF(OderItems!$A$2:$A$510,A74,OderItems!$L$2:$L$510) -> 966000 | P74: =SUMIF(OderItems!$A$2:$A$510,A74,OderItems!$G$2:$G$510) -> 29000 | Q74: =SUMIF(OderItems!$A$2:$A$510,A74,OderItems!$K$2:$K$510) -> 0 | R74: =O74+P74-Q74 -> 995000 | S74: VNĐ | T74: =AND(C74="delivered",I74<>"",R74>0) -> TRUE
A75: DH00074 | B75: CUS00044 | C75: processing | D75: 46127.723 | E75: 46127.807 | H75: 46135.723 | I75: KH0044 | J75: Website | K75: Chuyển khoản | L75: Miền Bắc | M75: Bắc Ninh | N75: =IFERROR(VLOOKUP(I75,Customers!$B$2:$L$81,11,FALSE),"") -> EMP004 | O75: =SUMIF(OderItems!$A$2:$A$510,A75,OderItems!$L$2:$L$510) -> 555000 | P75: =SUMIF(OderItems!$A$2:$A$510,A75,OderItems!$G$2:$G$510) -> 7000 | Q75: =SUMIF(OderItems!$A$2:$A$510,A75,OderItems!$K$2:$K$510) -> 0 | R75: =O75+P75-Q75 -> 562000 | S75: VNĐ | T75: =AND(C75="delivered",I75<>"",R75>0) -> FALSE
A76: DH00075 | B76: CUS00035 | C76: delivered | D76: 46043.032 | E76: 46043.116 | F76: 46045.032 | G76: 46049.032 | H76: 46051.032 | I76: KH0035 | J76: Sàn thương mại điện tử | K76: Chuyển khoản | L76: Miền Nam | M76: Bình Dương | N76: =IFERROR(VLOOKUP(I76,Customers!$B$2:$L$81,11,FALSE),"") -> EMP003 | O76: =SUMIF(OderItems!$A$2:$A$510,A76,OderItems!$L$2:$L$510) -> 171000 | P76: =SUMIF(OderItems!$A$2:$A$510,A76,OderItems!$G$2:$G$510) -> 9000 | Q76: =SUMIF(OderItems!$A$2:$A$510,A76,OderItems!$K$2:$K$510) -> 0 | R76: =O76+P76-Q76 -> 180000 | S76: VNĐ | T76: =AND(C76="delivered",I76<>"",R76>0) -> TRUE
A77: DH00076 | B77: CUS00012 | C77: delivered | D77: 45866.902 | E77: 45866.985 | F77: 45868.902 | G77: 45872.902 | H77: 45874.902 | I77: KH0012 | J77: Cửa hàng | K77: Chuyển khoản | L77: Miền Bắc | M77: Quảng Ninh | N77: =IFERROR(VLOOKUP(I77,Customers!$B$2:$L$81,11,FALSE),"") -> EMP004 | O77: =SUMIF(OderItems!$A$2:$A$510,A77,OderItems!$L$2:$L$510) -> 1894000 | P77: =SUMIF(OderItems!$A$2:$A$510,A77,OderItems!$G$2:$G$510) -> 34000 | Q77: =SUMIF(OderItems!$A$2:$A$510,A77,OderItems!$K$2:$K$510) -> 0 | R77: =O77+P77-Q77 -> 1928000 | S77: VNĐ | T77: =AND(C77="delivered",I77<>"",R77>0) -> TRUE
A78: DH00077 | B78: CUS00023 | C78: delivered | D78: 45863.475 | E78: 45863.559 | F78: 45865.475 | G78: 45869.475 | H78: 45871.475 | I78: KH0023 | J78: Ứng dụng | K78: COD | L78: Miền Nam | M78: Long An | N78: =IFERROR(VLOOKUP(I78,Customers!$B$2:$L$81,11,FALSE),"") -> EMP007 | O78: =SUMIF(OderItems!$A$2:$A$510,A78,OderItems!$L$2:$L$510) -> 580000 | P78: =SUMIF(OderItems!$A$2:$A$510,A78,OderItems!$G$2:$G$510) -> 9000 | Q78: =SUMIF(OderItems!$A$2:$A$510,A78,OderItems!$K$2:$K$510) -> 0 | R78: =O78+P78-Q78 -> 589000 | S78: VNĐ | T78: =AND(C78="delivered",I78<>"",R78>0) -> TRUE
A79: DH00078 | B79: CUS00023 | C79: delivered | D79: 45387.571 | E79: 45387.654 | F79: 45389.571 | G79: 45393.571 | H79: 45395.571 | I79: KH0023 | J79: Sàn thương mại điện tử | K79: Ví điện tử | L79: Miền Nam | M79: Long An | N79: =IFERROR(VLOOKUP(I79,Customers!$B$2:$L$81,11,FALSE),"") -> EMP007 | O79: =SUMIF(OderItems!$A$2:$A$510,A79,OderItems!$L$2:$L$510) -> 2578000 | P79: =SUMIF(OderItems!$A$2:$A$510,A79,OderItems!$G$2:$G$510) -> 40000 | Q79: =SUMIF(OderItems!$A$2:$A$510,A79,OderItems!$K$2:$K$510) -> 0 | R79: =O79+P79-Q79 -> 2618000 | S79: VNĐ | T79: =AND(C79="delivered",I79<>"",R79>0) -> TRUE
A80: DH00079 | B80: CUS00062 | C80: returned | D80: 45411.789 | E80: 45411.872 | F80: 45413.789 | G80: 45417.789 | H80: 45419.789 | I80: KH0062 | J80: Ứng dụng | K80: Chuyển khoản | L80: Miền Trung | M80: Bình Định | N80: =IFERROR(VLOOKUP(I80,Customers!$B$2:$L$81,11,FALSE),"") -> EMP006 | O80: =SUMIF(OderItems!$A$2:$A$510,A80,OderItems!$L$2:$L$510) -> 3194000 | P80: =SUMIF(OderItems!$A$2:$A$510,A80,OderItems!$G$2:$G$510) -> 47000 | Q80: =SUMIF(OderItems!$A$2:$A$510,A80,OderItems!$K$2:$K$510) -> 0 | R80: =O80+P80-Q80 -> 3241000 | S80: VNĐ | T80: =AND(C80="delivered",I80<>"",R80>0) -> FALSE
A81: DH00080 | B81: CUS00018 | C81: delivered | D81: 45534.977 | E81: 45535.06 | F81: 45536.977 | G81: 45540.977 | H81: 45542.977 | I81: KH0018 | J81: Cửa hàng | K81: Chuyển khoản | L81: Miền Nam | M81: Long An | N81: =IFERROR(VLOOKUP(I81,Customers!$B$2:$L$81,11,FALSE),"") -> EMP002 | O81: =SUMIF(OderItems!$A$2:$A$510,A81,OderItems!$L$2:$L$510) -> 918000 | P81: =SUMIF(OderItems!$A$2:$A$510,A81,OderItems!$G$2:$G$510) -> 20000 | Q81: =SUMIF(OderItems!$A$2:$A$510,A81,OderItems!$K$2:$K$510) -> 0 | R81: =O81+P81-Q81 -> 938000 | S81: VNĐ | T81: =AND(C81="delivered",I81<>"",R81>0) -> TRUE
A82: DH00081 | B82: CUS00052 | C82: delivered | D82: 45520.753 | E82: 45520.836 | F82: 45522.753 | G82: 45526.753 | H82: 45528.753 | I82: KH0052 | J82: Website | K82: COD | L82: Miền Nam | M82: Bà Rịa - Vũng Tàu | N82: =IFERROR(VLOOKUP(I82,Customers!$B$2:$L$81,11,FALSE),"") -> EMP004 | O82: =SUMIF(OderItems!$A$2:$A$510,A82,OderItems!$L$2:$L$510) -> 1928000 | P82: =SUMIF(OderItems!$A$2:$A$510,A82,OderItems!$G$2:$G$510) -> 29000 | Q82: =SUMIF(OderItems!$A$2:$A$510,A82,OderItems!$K$2:$K$510) -> 0 | R82: =O82+P82-Q82 -> 1957000 | S82: VNĐ | T82: =AND(C82="delivered",I82<>"",R82>0) -> TRUE
A83: DH00082 | B83: CUS00022 | C83: processing | D83: 45980.548 | E83: 45980.632 | H83: 45988.548 | I83: KH0022 | J83: Cửa hàng | K83: Thẻ ngân hàng | L83: Miền Nam | M83: Đồng Nai | N83: =IFERROR(VLOOKUP(I83,Customers!$B$2:$L$81,11,FALSE),"") -> EMP006 | O83: =SUMIF(OderItems!$A$2:$A$510,A83,OderItems!$L$2:$L$510) -> 242000 | P83: =SUMIF(OderItems!$A$2:$A$510,A83,OderItems!$G$2:$G$510) -> 7000 | Q83: =SUMIF(OderItems!$A$2:$A$510,A83,OderItems!$K$2:$K$510) -> 0 | R83: =O83+P83-Q83 -> 249000 | S83: VNĐ | T83: =AND(C83="delivered",I83<>"",R83>0) -> FALSE
A84: DH00083 | B84: CUS00041 | C84: delivered | D84: 46093.325 | E84: 46093.409 | F84: 46095.325 | G84: 46099.325 | H84: 46101.325 | I84: KH0041 | J84: Ứng dụng | K84: Chuyển khoản | L84: Miền Nam | M84: TP. Hồ Chí Minh | N84: =IFERROR(VLOOKUP(I84,Customers!$B$2:$L$81,11,FALSE),"") -> EMP001 | O84: =SUMIF(OderItems!$A$2:$A$510,A84,OderItems!$L$2:$L$510) -> 4930000 | P84: =SUMIF(OderItems!$A$2:$A$510,A84,OderItems!$G$2:$G$510) -> 76000 | Q84: =SUMIF(OderItems!$A$2:$A$510,A84,OderItems!$K$2:$K$510) -> 0 | R84: =O84+P84-Q84 -> 5006000 | S84: VNĐ | T84: =AND(C84="delivered",I84<>"",R84>0) -> TRUE
A85: DH00084 | B85: CUS00006 | C85: canceled | D85: 45458.249 | H85: 45466.249 | I85: KH0006 | J85: Sàn thương mại điện tử | K85: Chuyển khoản | L85: Miền Bắc | M85: Thái Nguyên | N85: =IFERROR(VLOOKUP(I85,Customers!$B$2:$L$81,11,FALSE),"") -> EMP006 | O85: =SUMIF(OderItems!$A$2:$A$510,A85,OderItems!$L$2:$L$510) -> 1764000 | P85: =SUMIF(OderItems!$A$2:$A$510,A85,OderItems!$G$2:$G$510) -> 34000 | Q85: =SUMIF(OderItems!$A$2:$A$510,A85,OderItems!$K$2:$K$510) -> 0 | R85: =O85+P85-Q85 -> 1798000 | S85: VNĐ | T85: =AND(C85="delivered",I85<>"",R85>0) -> FALSE
A86: DH00085 | B86: CUS00034 | C86: delivered | D86: 45832.806 | E86: 45832.89 | F86: 45834.806 | G86: 45838.806 | H86: 45840.806 | I86: KH0034 | J86: Website | K86: Thẻ ngân hàng | L86: Miền Bắc | M86: Hải Phòng | N86: =IFERROR(VLOOKUP(I86,Customers!$B$2:$L$81,11,FALSE),"") -> EMP002 | O86: =SUMIF(OderItems!$A$2:$A$510,A86,OderItems!$L$2:$L$510) -> 2166000 | P86: =SUMIF(OderItems!$A$2:$A$510,A86,OderItems!$G$2:$G$510) -> 44000 | Q86: =SUMIF(OderItems!$A$2:$A$510,A86,OderItems!$K$2:$K$510) -> 0 | R86: =O86+P86-Q86 -> 2210000 | S86: VNĐ | T86: =AND(C86="delivered",I86<>"",R86>0) -> TRUE
A87: DH00086 | B87: CUS00023 | C87: returned | D87: 45972.216 | E87: 45972.299 | F87: 45974.216 | G87: 45978.216 | H87: 45980.216 | I87: KH0023 | J87: Website | K87: Chuyển khoản | L87: Miền Nam | M87: Long An | N87: =IFERROR(VLOOKUP(I87,Customers!$B$2:$L$81,11,FALSE),"") -> EMP007 | O87: =SUMIF(OderItems!$A$2:$A$510,A87,OderItems!$L$2:$L$510) -> 780000 | P87: =SUMIF(OderItems!$A$2:$A$510,A87,OderItems!$G$2:$G$510) -> 20000 | Q87: =SUMIF(OderItems!$A$2:$A$510,A87,OderItems!$K$2:$K$510) -> 0 | R87: =O87+P87-Q87 -> 800000 | S87: VNĐ | T87: =AND(C87="delivered",I87<>"",R87>0) -> FALSE
A88: DH00087 | B88: CUS00017 | C88: processing | D88: 45797.407 | E88: 45797.491 | H88: 45805.407 | I88: KH0017 | J88: Ứng dụng | K88: COD | L88: Miền Nam | M88: Bà Rịa - Vũng Tàu | N88: =IFERROR(VLOOKUP(I88,Customers!$B$2:$L$81,11,FALSE),"") -> EMP001 | O88: =SUMIF(OderItems!$A$2:$A$510,A88,OderItems!$L$2:$L$510) -> 1578000 | P88: =SUMIF(OderItems!$A$2:$A$510,A88,OderItems!$G$2:$G$510) -> 34000 | Q88: =SUMIF(OderItems!$A$2:$A$510,A88,OderItems!$K$2:$K$510) -> 0 | R88: =O88+P88-Q88 -> 1612000 | S88: VNĐ | T88: =AND(C88="delivered",I88<>"",R88>0) -> FALSE
A89: DH00088 | B89: CUS00036 | C89: delivered | D89: 45979.334 | E89: 45979.418 | F89: 45981.334 | G89: 45985.334 | H89: 45987.334 | I89: KH0036 | J89: Cửa hàng | K89: Chuyển khoản | L89: Miền Trung | M89: Quảng Nam | N89: =IFERROR(VLOOKUP(I89,Customers!$B$2:$L$81,11,FALSE),"") -> EMP004 | O89: =SUMIF(OderItems!$A$2:$A$510,A89,OderItems!$L$2:$L$510) -> 1062000 | P89: =SUMIF(OderItems!$A$2:$A$510,A89,OderItems!$G$2:$G$510) -> 19000 | Q89: =SUMIF(OderItems!$A$2:$A$510,A89,OderItems!$K$2:$K$510) -> 0 | R89: =O89+P89-Q89 -> 1081000 | S89: VNĐ | T89: =AND(C89="delivered",I89<>"",R89>0) -> TRUE
A90: DH00089 | B90: CUS00019 | C90: delivered | D90: 45590.59 | E90: 45590.673 | F90: 45592.59 | G90: 45596.59 | H90: 45598.59 | I90: KH0019 | J90: Website | K90: COD | L90: Miền Trung | M90: Thừa Thiên Huế | N90: =IFERROR(VLOOKUP(I90,Customers!$B$2:$L$81,11,FALSE),"") -> EMP003 | O90: =SUMIF(OderItems!$A$2:$A$510,A90,OderItems!$L$2:$L$510) -> 2251000 | P90: =SUMIF(OderItems!$A$2:$A$510,A90,OderItems!$G$2:$G$510) -> 57000 | Q90: =SUMIF(OderItems!$A$2:$A$510,A90,OderItems!$K$2:$K$510) -> 0 | R90: =O90+P90-Q90 -> 2308000 | S90: VNĐ | T90: =AND(C90="delivered",I90<>"",R90>0) -> TRUE
A91: DH00090 | B91: CUS00042 | C91: delivered | D91: 45819.561 | E91: 45819.644 | F91: 45821.561 | G91: 45825.561 | H91: 45827.561 | I91: KH0042 | J91: Ứng dụng | K91: Ví điện tử | L91: Miền Nam | M91: TP. Hồ Chí Minh | N91: =IFERROR(VLOOKUP(I91,Customers!$B$2:$L$81,11,FALSE),"") -> EMP002 | O91: =SUMIF(OderItems!$A$2:$A$510,A91,OderItems!$L$2:$L$510) -> 2304000 | P91: =SUMIF(OderItems!$A$2:$A$510,A91,OderItems!$G$2:$G$510) -> 20000 | Q91: =SUMIF(OderItems!$A$2:$A$510,A91,OderItems!$K$2:$K$510) -> 0 | R91: =O91+P91-Q91 -> 2324000 | S91: VNĐ | T91: =AND(C91="delivered",I91<>"",R91>0) -> TRUE
A92: DH00091 | B92: CUS00013 | C92: canceled | D92: 45332.003 | H92: 45340.003 | I92: KH0013 | J92: Cửa hàng | K92: Ví điện tử | L92: Miền Trung | M92: Đà Nẵng | N92: =IFERROR(VLOOKUP(I92,Customers!$B$2:$L$81,11,FALSE),"") -> EMP005 | O92: =SUMIF(OderItems!$A$2:$A$510,A92,OderItems!$L$2:$L$510) -> 2573000 | P92: =SUMIF(OderItems!$A$2:$A$510,A92,OderItems!$G$2:$G$510) -> 46000 | Q92: =SUMIF(OderItems!$A$2:$A$510,A92,OderItems!$K$2:$K$510) -> 0 | R92: =O92+P92-Q92 -> 2619000 | S92: VNĐ | T92: =AND(C92="delivered",I92<>"",R92>0) -> FALSE
A93: DH00092 | B93: CUS00040 | C93: delivered | D93: 46152.142 | E93: 46152.225 | F93: 46154.142 | G93: 46158.142 | H93: 46160.142 | I93: KH0040 | J93: Ứng dụng | K93: Thẻ ngân hàng | L93: Miền Trung | M93: Đà Nẵng | N93: =IFERROR(VLOOKUP(I93,Customers!$B$2:$L$81,11,FALSE),"") -> EMP008 | O93: =SUMIF(OderItems!$A$2:$A$510,A93,OderItems!$L$2:$L$510) -> 390000 | P93: =SUMIF(OderItems!$A$2:$A$510,A93,OderItems!$G$2:$G$510) -> 10000 | Q93: =SUMIF(OderItems!$A$2:$A$510,A93,OderItems!$K$2:$K$510) -> 0 | R93: =O93+P93-Q93 -> 400000 | S93: VNĐ | T93: =AND(C93="delivered",I93<>"",R93>0) -> TRUE
A94: DH00093 | B94: CUS00031 | C94: processing | D94: 45363.389 | E94: 45363.472 | H94: 45371.389 | I94: KH0031 | J94: Website | K94: Thẻ ngân hàng | L94: Miền Nam | M94: Long An | N94: =IFERROR(VLOOKUP(I94,Customers!$B$2:$L$81,11,FALSE),"") -> EMP007 | O94: =SUMIF(OderItems!$A$2:$A$510,A94,OderItems!$L$2:$L$510) -> 1764000 | P94: =SUMIF(OderItems!$A$2:$A$510,A94,OderItems!$G$2:$G$510) -> 32000 | Q94: =SUMIF(OderItems!$A$2:$A$510,A94,OderItems!$K$2:$K$510) -> 0 | R94: =O94+P94-Q94 -> 1796000 | S94: VNĐ | T94: =AND(C94="delivered",I94<>"",R94>0) -> FALSE
A95: DH00094 | B95: CUS00037 | C95: delivered | D95: 46141.442 | E95: 46141.525 | F95: 46143.442 | G95: 46147.442 | H95: 46149.442 | I95: KH0037 | J95: Website | K95: Chuyển khoản | L95: Miền Trung | M95: Đà Nẵng | N95: =IFERROR(VLOOKUP(I95,Customers!$B$2:$L$81,11,FALSE),"") -> EMP005 | O95: =SUMIF(OderItems!$A$2:$A$510,A95,OderItems!$L$2:$L$510) -> 967000 | P95: =SUMIF(OderItems!$A$2:$A$510,A95,OderItems!$G$2:$G$510) -> 20000 | Q95: =SUMIF(OderItems!$A$2:$A$510,A95,OderItems!$K$2:$K$510) -> 0 | R95: =O95+P95-Q95 -> 987000 | S95: VNĐ | T95: =AND(C95="delivered",I95<>"",R95>0) -> TRUE
A96: DH00095 | B96: CUS00032 | C96: delivered | D96: 45570.573 | E96: 45570.657 | F96: 45572.573 | G96: 45576.573 | H96: 45578.573 | I96: KH0032 | J96: Website | K96: COD | L96: Miền Nam | M96: Bà Rịa - Vũng Tàu | N96: =IFERROR(VLOOKUP(I96,Customers!$B$2:$L$81,11,FALSE),"") -> EMP008 | O96: =SUMIF(OderItems!$A$2:$A$510,A96,OderItems!$L$2:$L$510) -> 120000 | P96: =SUMIF(OderItems!$A$2:$A$510,A96,OderItems!$G$2:$G$510) -> 4000 | Q96: =SUMIF(OderItems!$A$2:$A$510,A96,OderItems!$K$2:$K$510) -> 0 | R96: =O96+P96-Q96 -> 124000 | S96: VNĐ | T96: =AND(C96="delivered",I96<>"",R96>0) -> TRUE
A97: DH00096 | B97: CUS00010 | C97: delivered | D97: 45389.89 | E97: 45389.973 | F97: 45391.89 | G97: 45395.89 | H97: 45397.89 | I97: KH0010 | J97: Ứng dụng | K97: Chuyển khoản | L97: Miền Nam | M97: Bà Rịa - Vũng Tàu | N97: =IFERROR(VLOOKUP(I97,Customers!$B$2:$L$81,11,FALSE),"") -> EMP002 | O97: =SUMIF(OderItems!$A$2:$A$510,A97,OderItems!$L$2:$L$510) -> 350000 | P97: =SUMIF(OderItems!$A$2:$A$510,A97,OderItems!$G$2:$G$510) -> 14000 | Q97: =SUMIF(OderItems!$A$2:$A$510,A97,OderItems!$K$2:$K$510) -> 0 | R97: =O97+P97-Q97 -> 364000 | S97: VNĐ | T97: =AND(C97="delivered",I97<>"",R97>0) -> TRUE
A98: DH00097 | B98: CUS00014 | C98: delivered | D98: 45604.086 | E98: 45604.169 | F98: 45606.086 | G98: 45610.086 | H98: 45612.086 | I98: KH0014 | J98: Ứng dụng | K98: Thẻ ngân hàng | L98: Miền Trung | M98: Thừa Thiên Huế | N98: =IFERROR(VLOOKUP(I98,Customers!$B$2:$L$81,11,FALSE),"") -> EMP006 | O98: =SUMIF(OderItems!$A$2:$A$510,A98,OderItems!$L$2:$L$510) -> 400000 | P98: =SUMIF(OderItems!$A$2:$A$510,A98,OderItems!$G$2:$G$510) -> 5000 | Q98: =SUMIF(OderItems!$A$2:$A$510,A98,OderItems!$K$2:$K$510) -> 0 | R98: =O98+P98-Q98 -> 405000 | S98: VNĐ | T98: =AND(C98="delivered",I98<>"",R98>0) -> TRUE
A99: DH00098 | B99: CUS00056 | C99: delivered | D99: 45507.181 | E99: 45507.265 | F99: 45509.181 | G99: 45513.181 | H99: 45515.181 | I99: KH0056 | J99: Sàn thương mại điện tử | K99: COD | L99: Miền Nam | M99: TP. Hồ Chí Minh | N99: =IFERROR(VLOOKUP(I99,Customers!$B$2:$L$81,11,FALSE),"") -> EMP008 | O99: =SUMIF(OderItems!$A$2:$A$510,A99,OderItems!$L$2:$L$510) -> 1596000 | P99: =SUMIF(OderItems!$A$2:$A$510,A99,OderItems!$G$2:$G$510) -> 24000 | Q99: =SUMIF(OderItems!$A$2:$A$510,A99,OderItems!$K$2:$K$510) -> 0 | R99: =O99+P99-Q99 -> 1620000 | S99: VNĐ | T99: =AND(C99="delivered",I99<>"",R99>0) -> TRUE
A100: DH00099 | B100: CUS00057 | C100: delivered | D100: 45544.853 | E100: 45544.937 | F100: 45546.853 | G100: 45550.853 | H100: 45552.853 | I100: KH0057 | J100: Website | K100: Thẻ ngân hàng | L100: Miền Bắc | M100: Thái Nguyên | N100: =IFERROR(VLOOKUP(I100,Customers!$B$2:$L$81,11,FALSE),"") -> EMP001 | O100: =SUMIF(OderItems!$A$2:$A$510,A100,OderItems!$L$2:$L$510) -> 1139000 | P100: =SUMIF(OderItems!$A$2:$A$510,A100,OderItems!$G$2:$G$510) -> 20000 | Q100: =SUMIF(OderItems!$A$2:$A$510,A100,OderItems!$K$2:$K$510) -> 0 | R100: =O100+P100-Q100 -> 1159000 | S100: VNĐ | T100: =AND(C100="delivered",I100<>"",R100>0) -> TRUE
...

Sheet OderItems
A1: order_id | B1: order_item_id | C1: product_id | D1: seller_id | E1: shipping_limit_date | F1: price | G1: freight_value | H1: Quantity | I1: LineAmount | J1: OrderDetailID | K1: discount_value | L1: line_subtotal | M1: line_total
A2: DH00001 | B2: 1 | C2: SP019 | D2: NCC0019 | E2: 45906.813 | F2: 420000 | G2: 13000 | H2: 2 | I2: 840000 | J2: CT000001 | K2: =0 -> 0 | L2: =F2*H2 -> 840000 | M2: =L2+G2-K2 -> 853000
A3: DH00001 | B3: 2 | C3: SP003 | D3: NCC0003 | E3: 45906.813 | F3: 390000 | G3: 16000 | H3: 4 | I3: 1560000 | J3: CT000002 | K3: =0 -> 0 | L3: =F3*H3 -> 1560000 | M3: =L3+G3-K3 -> 1576000
A4: DH00001 | B4: 3 | C4: SP039 | D4: NCC0009 | E4: 45906.813 | F4: 142000 | G4: 7000 | H4: 2 | I4: 284000 | J4: CT000003 | K4: =0 -> 0 | L4: =F4*H4 -> 284000 | M4: =L4+G4-K4 -> 291000
A5: DH00001 | B5: 4 | C5: SP029 | D5: NCC0029 | E5: 45906.813 | F5: 350000 | G5: 21000 | H5: 2 | I5: 700000 | J5: CT000004 | K5: =0 -> 0 | L5: =F5*H5 -> 700000 | M5: =L5+G5-K5 -> 721000
A6: DH00002 | B6: 1 | C6: SP029 | D6: NCC0029 | E6: 46137.272 | F6: 350000 | G6: 11000 | H6: 3 | I6: 1050000 | J6: CT000005 | K6: =0 -> 0 | L6: =F6*H6 -> 1050000 | M6: =L6+G6-K6 -> 1061000
A7: DH00002 | B7: 2 | C7: SP008 | D7: NCC0008 | E7: 46137.272 | F7: 266000 | G7: 11000 | H7: 3 | I7: 798000 | J7: CT000006 | K7: =0 -> 0 | L7: =F7*H7 -> 798000 | M7: =L7+G7-K7 -> 809000
A8: DH00002 | B8: 3 | C8: SP023 | D8: NCC0023 | E8: 46137.272 | F8: 126000 | G8: 6000 | H8: 3 | I8: 378000 | J8: CT000007 | K8: =0 -> 0 | L8: =F8*H8 -> 378000 | M8: =L8+G8-K8 -> 384000
A9: DH00002 | B9: 4 | C9: SP030 | D9: NCC0030 | E9: 46137.272 | F9: 290000 | G9: 17000 | H9: 2 | I9: 580000 | J9: CT000008 | K9: =0 -> 0 | L9: =F9*H9 -> 580000 | M9: =L9+G9-K9 -> 597000
A10: DH00003 | B10: 1 | C10: SP021 | D10: NCC0021 | E10: 45806.919 | F10: 89000 | G10: 3000 | H10: 2 | I10: 178000 | J10: CT000009 | K10: =0 -> 0 | L10: =F10*H10 -> 178000 | M10: =L10+G10-K10 -> 181000
A11: DH00003 | B11: 2 | C11: SP002 | D11: NCC0002 | E11: 45806.919 | F11: 220000 | G11: 9000 | H11: 2 | I11: 440000 | J11: CT000010 | K11: =0 -> 0 | L11: =F11*H11 -> 440000 | M11: =L11+G11-K11 -> 449000
A12: DH00004 | B12: 1 | C12: SP031 | D12: NCC0001 | E12: 46123.139 | F12: 189000 | G12: 9000 | H12: 4 | I12: 756000 | J12: CT000011 | K12: =0 -> 0 | L12: =F12*H12 -> 756000 | M12: =L12+G12-K12 -> 765000
A13: DH00004 | B13: 2 | C13: SP025 | D13: NCC0025 | E13: 46123.139 | F13: 280000 | G13: 17000 | H13: 1 | I13: 280000 | J13: CT000012 | K13: =0 -> 0 | L13: =F13*H13 -> 280000 | M13: =L13+G13-K13 -> 297000
... A510: DH00200 | B510: 4 | C510: SP033 | D510: NCC0003 | E510: 45530.487 | F510: 125000 | G510: 4000 | H510: 4 | I510: 500000 | J510: CT000509 | K510: =0 -> 0 | L510: =F510*H510 -> 500000 | M510: =L510+G510-K510 -> 504000

Sheet Payments
A1: order_id | B1: payment_sequential | C1: payment_type | D1: payment_installments | E1: payment_value | F1: PaymentMethodVN | G1: Currency
A2: DH00001 | B2: 1 | C2: bank_transfer | D2: 1 | E2: 3441000 | F2: Chuyển khoản | G2: VNĐ
A3: DH00002 | B3: 1 | C3: cash_on_delivery | D3: 1 | E3: 2851000 | F3: COD | G3: VNĐ
A4: DH00003 | B4: 1 | C4: e_wallet | D4: 1 | E4: 630000 | F4: Ví điện tử | G4: VNĐ
A5: DH00004 | B5: 1 | C5: credit_card | D5: 4 | E5: 1185000 | F5: Thẻ ngân hàng | G5: VNĐ
A6: DH00005 | B6: 1 | C6: cash_on_delivery | D6: 1 | E6: 2037000 | F6: COD | G6: VNĐ
A7: DH00006 | B7: 1 | C7: e_wallet | D7: 1 | E7: 1027000 | F7: Ví điện tử | G7: VNĐ
A8: DH00007 | B8: 1 | C8: e_wallet | D8: 1 | E8: 747000 | F8: Ví điện tử | G8: VNĐ
A9: DH00008 | B9: 1 | C9: e_wallet | D9: 1 | E9: 1947000 | F9: Ví điện tử | G9: VNĐ
A10: DH00009 | B10: 1 | C10: e_wallet | D10: 1 | E10: 1234000 | F10: Ví điện tử | G10: VNĐ
A11: DH00010 | B11: 1 | C11: bank_transfer | D11: 1 | E11: 210000 | F11: Chuyển khoản | G11: VNĐ
A12: DH00011 | B12: 1 | C12: bank_transfer | D12: 1 | E12: 751000 | F12: Chuyển khoản | G12: VNĐ
A13: DH00012 | B13: 1 | C13: bank_transfer | D13: 1 | E13: 1868000 | F13: Chuyển khoản | G13: VNĐ
... A201: DH00200 | B201: 1 | C201: e_wallet | D201: 1 | E201: 1952000 | F201: Ví điện tử | G201: VNĐ

Sheet Reviews
A1: review_id | B1: order_id | C1: review_score | D1: review_comment_title | E1: review_comment_message | F1: review_creation_date | G1: review_answer_timestamp | H1: CustomerID | I1: Channel
A2: TT00001 | B2: DH00001 | C2: 4 | D2: Hài lòng | E2: Sản phẩm đúng mô tả, đóng gói cẩn thận. | F2: 45908.313 | G2: 45908.563 | H2: KH0057 | I2: Website/App
A3: TT00002 | B3: DH00002 | C3: 5 | D3: Hài lòng | E3: Hài lòng với sản phẩm và dịch vụ. | F3: 46143.772 | G3: 46144.022 | H3: KH0056 | I3: Website/App
A4: TT00003 | B4: DH00003 | C4: 3 | D4: Bình thường | E4: Giao hàng nhanh, chất lượng tốt. | F4: 45816.419 | G4: 45816.669 | H4: KH0026 | I4: Website/App
A5: TT00004 | B5: DH00004 | C5: 3 | D5: Bình thường | E5: Giao hàng nhanh, chất lượng tốt. | F5: 46124.639 | G5: 46124.889 | H5: KH0033 | I5: Website/App
A6: TT00005 | B6: DH00005 | C6: 5 | D6: Hài lòng | E6: Sản phẩm đúng mô tả, đóng gói cẩn thận. | F6: 46207.926 | G6: 46208.176 | H6: KH0078 | I6: Website/App
A7: TT00006 | B7: DH00006 | C7: 4 | D7: Hài lòng | E7: Sẽ tiếp tục ủng hộ cửa hàng. | F7: 45801.558 | G7: 45801.808 | H7: KH0053 | I7: Website/App
A8: TT00007 | B8: DH00008 | C8: 5 | D8: Hài lòng | E8: Hài lòng với sản phẩm và dịch vụ. | F8: 45527.834 | G8: 45528.084 | H8: KH0020 | I8: Website/App
A9: TT00008 | B9: DH00010 | C9: 5 | D9: Hài lòng | E9: Sản phẩm đẹp, giá hợp lý. | F9: 45358.111 | G9: 45358.361 | H9: KH0036 | I9: Website/App
A10: TT00009 | B10: DH00011 | C10: 3 | D10: Bình thường | E10: Sản phẩm đẹp, giá hợp lý. | F10: 45795.633 | G10: 45795.883 | H10: KH0022 | I10: Website/App
A11: TT00010 | B11: DH00014 | C11: 5 | D11: Hài lòng | E11: Sản phẩm đúng mô tả, đóng gói cẩn thận. | F11: 45758.179 | G11: 45758.429 | H11: KH0006 | I11: Website/App
A12: TT00011 | B12: DH00015 | C12: 3 | D12: Bình thường | E12: Sản phẩm đúng mô tả, đóng gói cẩn thận. | F12: 45797.099 | G12: 45797.349 | H12: KH0045 | I12: Website/App
A13: TT00012 | B13: DH00016 | C13: 5 | D13: Hài lòng | E13: Sản phẩm đúng mô tả, đóng gói cẩn thận. | F13: 45329.592 | G13: 45329.842 | H13: KH0022 | I13: Website/App
... A142: TT00141 | B142: DH00200 | C142: 3 | D142: Bình thường | E142: Sản phẩm đúng mô tả, đóng gói cẩn thận. | F142: 45538.987 | G142: 45539.237 | H142: KH0032 | I142: Website/App

Sheet Sellers
A1: seller_id | B1: seller_zip_code_prefix | C1: seller_city | D1: seller_state | E1: Region | F1: SellerName
A2: NCC0001 | B2: 10000 | C2: Hà Nội | D2: HN | E2: Miền Bắc | F2: Nhà bán hàng 01
A3: NCC0002 | B3: 18000 | C3: Hải Phòng | D3: HP | E3: Miền Bắc | F3: Nhà bán hàng 02
A4: NCC0003 | B4: 20000 | C4: Quảng Ninh | D4: QN | E4: Miền Bắc | F4: Nhà bán hàng 03
A5: NCC0004 | B5: 16000 | C5: Bắc Ninh | D5: BN | E5: Miền Bắc | F5: Nhà bán hàng 04
A6: NCC0005 | B6: 17000 | C6: Nam Định | D6: ND | E6: Miền Bắc | F6: Nhà bán hàng 05
A7: NCC0006 | B7: 25000 | C7: Thái Nguyên | D7: TN | E7: Miền Bắc | F7: Nhà bán hàng 06
A8: NCC0007 | B8: 55000 | C8: Đà Nẵng | D8: DN | E8: Miền Trung | F8: Nhà bán hàng 07
A9: NCC0008 | B9: 53000 | C9: Thừa Thiên Huế | D9: TTH | E9: Miền Trung | F9: Nhà bán hàng 08
A10: NCC0009 | B10: 56000 | C10: Quảng Nam | D10: QNA | E10: Miền Trung | F10: Nhà bán hàng 09
A11: NCC0010 | B11: 65000 | C11: Khánh Hòa | D11: KH | E11: Miền Trung | F11: Nhà bán hàng 10
A12: NCC0011 | B12: 43000 | C12: Nghệ An | D12: NA | E12: Miền Trung | F12: Nhà bán hàng 11
A13: NCC0012 | B13: 59000 | C13: Bình Định | D13: BD | E13: Miền Trung | F13: Nhà bán hàng 12
... A31: NCC0030 | B31: 59000 | C31: Bình Định | D31: BD | E31: Miền Trung | F31: Nhà bán hàng 30

Sheet Geolocation
A1: geolocation_zip_code_prefix | B1: geolocation_lat | C1: geolocation_lng | D1: geolocation_city | E1: geolocation_state | F1: Region
A2: 10000 | B2: 21.0285 | C2: 105.8542 | D2: Hà Nội | E2: HN | F2: Miền Bắc
A3: 18000 | B3: 20.8449 | C3: 106.6881 | D3: Hải Phòng | E3: HP | F3: Miền Bắc
A4: 20000 | B4: 20.95 | C4: 107.08 | D4: Quảng Ninh | E4: QN | F4: Miền Bắc
A5: 16000 | B5: 21.1861 | C5: 106.0763 | D5: Bắc Ninh | E5: BN | F5: Miền Bắc
A6: 17000 | B6: 20.4388 | C6: 106.1621 | D6: Nam Định | E6: ND | F6: Miền Bắc
A7: 25000 | B7: 21.5942 | C7: 105.8482 | D7: Thái Nguyên | E7: TN | F7: Miền Bắc
A8: 55000 | B8: 16.0544 | C8: 108.2022 | D8: Đà Nẵng | E8: DN | F8: Miền Trung
A9: 53000 | B9: 16.4637 | C9: 107.5909 | D9: Thừa Thiên Huế | E9: TTH | F9: Miền Trung
A10: 56000 | B10: 15.5394 | C10: 108.0191 | D10: Quảng Nam | E10: QNA | F10: Miền Trung
A11: 65000 | B11: 12.2388 | C11: 109.1967 | D11: Khánh Hòa | E11: KH | F11: Miền Trung
A12: 43000 | B12: 18.6796 | C12: 105.6813 | D12: Nghệ An | E12: NA | F12: Miền Trung
A13: 59000 | B13: 13.782 | C13: 109.219 | D13: Bình Định | E13: BD | F13: Miền Trung
... A19: 78000 | B19: 10.4114 | C19: 107.1362 | D19: Bà Rịa - Vũng Tàu | E19: BRVT | F19: Miền Nam

Sheet DataDictionary
A1: SheetName | B1: FieldName | C1: BusinessName | D1: Description | E1: DataType | F1: LengthFormat | G1: Required | H1: KeyType | I1: ReferenceField | J1: AllowedValues | K1: ValidationRule | L1: NullHandling | M1: TransformationRule | N1: ExampleValue | O1: SourceType
A2: Customers | B2: customer_id | C2: customer_id | D2: Đặc tả trường customer_id của bảng Customers | E2: Text | F2: Text | G2: Yes | H2: PK | K2: Không trùng và không rỗng | L2: Reject | M2: Giữ nguyên/chuẩn hóa ETL | N2: customer_id | O2: Olist structure
A3: Customers | B3: customer_unique_id | C3: customer_unique_id | D3: Đặc tả trường customer_unique_id của bảng Customers | E3: Text | F3: Text | G3: Yes | H3: FK | I3: Customers.customer_unique_id | K3: Phải tồn tại trong Customers.customer_unique_id | L3: Allow/derive theo quy tắc | M3: Giữ nguyên/chuẩn hóa ETL | N3: customer_unique_id | O3: Olist structure
A4: Customers | B4: customer_zip_code_prefix | C4: customer_zip_code_prefix | D4: Đặc tả trường customer_zip_code_prefix của bảng Customers | E4: Text | F4: Text | G4: Conditional | H4: Attribute | K4: Theo kiểu dữ liệu | L4: Allow/derive theo quy tắc | M4: Giữ nguyên/chuẩn hóa ETL | N4: customer_zip_code_prefix | O4: Olist structure
A5: Customers | B5: customer_city | C5: customer_city | D5: Đặc tả trường customer_city của bảng Customers | E5: Text | F5: Text | G5: Conditional | H5: Attribute | K5: Theo kiểu dữ liệu | L5: Allow/derive theo quy tắc | M5: Giữ nguyên/chuẩn hóa ETL | N5: customer_city | O5: Olist structure
A6: Customers | B6: customer_state | C6: customer_state | D6: Đặc tả trường customer_state của bảng Customers | E6: Text | F6: Text | G6: Conditional | H6: Attribute | K6: Theo kiểu dữ liệu | L6: Allow/derive theo quy tắc | M6: Giữ nguyên/chuẩn hóa ETL | N6: customer_state | O6: Olist structure
A7: Customers | B7: CustomerName | C7: CustomerName | D7: Đặc tả trường CustomerName của bảng Customers | E7: Text | F7: Text | G7: Conditional | H7: Attribute | K7: Theo kiểu dữ liệu | L7: Allow/derive theo quy tắc | M7: Giữ nguyên/chuẩn hóa ETL | N7: CustomerName | O7: Olist structure
A8: Customers | B8: Region | C8: Region | D8: Đặc tả trường Region của bảng Customers | E8: Text | F8: Text | G8: Conditional | H8: Attribute | K8: Theo kiểu dữ liệu | L8: Allow/derive theo quy tắc | M8: Giữ nguyên/chuẩn hóa ETL | N8: Region | O8: Olist structure
A9: Customers | B9: ProvinceCity | C9: ProvinceCity | D9: Đặc tả trường ProvinceCity của bảng Customers | E9: Text | F9: Text | G9: Conditional | H9: Attribute | K9: Theo kiểu dữ liệu | L9: Allow/derive theo quy tắc | M9: Giữ nguyên/chuẩn hóa ETL | N9: ProvinceCity | O9: Olist structure
A10: Customers | B10: Email | C10: Email | D10: Đặc tả trường Email của bảng Customers | E10: Text | F10: Text | G10: Conditional | H10: Attribute | K10: Theo kiểu dữ liệu | L10: Allow/derive theo quy tắc | M10: Giữ nguyên/chuẩn hóa ETL | N10: Email | O10: Olist structure
A11: Customers | B11: Phone | C11: Phone | D11: Đặc tả trường Phone của bảng Customers | E11: Text | F11: Text | G11: Conditional | H11: Attribute | K11: Theo kiểu dữ liệu | L11: Allow/derive theo quy tắc | M11: Giữ nguyên/chuẩn hóa ETL | N11: Phone | O11: Olist structure
A12: Customers | B12: RegisteredDate | C12: RegisteredDate | D12: Đặc tả trường RegisteredDate của bảng Customers | E12: Datetime | F12: yyyy-mm-dd hh:mm:ss | G12: Conditional | H12: Attribute | K12: Theo kiểu dữ liệu | L12: Allow/derive theo quy tắc | M12: Giữ nguyên/chuẩn hóa ETL | N12: RegisteredDate | O12: Olist structure
A13: Customers | B13: owner_id | C13: Nhân viên phụ trách | D13: Đặc tả trường owner_id của bảng Customers | E13: Text | F13: Text | G13: Yes | H13: FK | I13: Employees.employee_id | K13: Phải tồn tại trong Employees.employee_id | L13: Allow/derive theo quy tắc | M13: Tính toán hoặc sinh theo SRS | N13: owner_id | O13: SRS/VN-added
A14: Customers | B14: CustomerStatus | C14: CustomerStatus | D14: Đặc tả trường CustomerStatus của bảng Customers | E14: Text | F14: Text | G14: Conditional | H14: Attribute | K14: Theo kiểu dữ liệu | L14: Allow/derive theo quy tắc | M14: Tính toán hoặc sinh theo SRS | N14: CustomerStatus | O14: SRS/VN-added
A15: Customers | B15: CustomerSegment | C15: Phân khúc khách hàng | D15: Đặc tả trường CustomerSegment của bảng Customers | E15: Text | F15: Text | G15: Conditional | H15: Attribute | K15: Theo kiểu dữ liệu | L15: Allow/derive theo quy tắc | M15: Tính toán hoặc sinh theo SRS | N15: CustomerSegment | O15: SRS/VN-added
A16: Products | B16: product_id | C16: product_id | D16: Đặc tả trường product_id của bảng Products | E16: Text | F16: Text | G16: Yes | H16: PK | I16: Products.product_id | K16: Không trùng và không rỗng | L16: Reject | M16: Giữ nguyên/chuẩn hóa ETL | N16: product_id | O16: Olist structure
A17: Products | B17: product_category_name | C17: product_category_name | D17: Đặc tả trường product_category_name của bảng Products | E17: Text | F17: Text | G17: Conditional | H17: Attribute | K17: Theo kiểu dữ liệu | L17: Allow/derive theo quy tắc | M17: Giữ nguyên/chuẩn hóa ETL | N17: product_category_name | O17: Olist structure
A18: Products | B18: product_name_lenght | C18: product_name_lenght | D18: Đặc tả trường product_name_lenght của bảng Products | E18: Text | F18: Text | G18: Conditional | H18: Attribute | K18: Theo kiểu dữ liệu | L18: Allow/derive theo quy tắc | M18: Giữ nguyên/chuẩn hóa ETL | N18: product_name_lenght | O18: Olist structure
A19: Products | B19: product_description_lenght | C19: product_description_lenght | D19: Đặc tả trường product_description_lenght của bảng Products | E19: Text | F19: Text | G19: Conditional | H19: Attribute | K19: Theo kiểu dữ liệu | L19: Allow/derive theo quy tắc | M19: Giữ nguyên/chuẩn hóa ETL | N19: product_description_lenght | O19: Olist structure
A20: Products | B20: product_photos_qty | C20: product_photos_qty | D20: Đặc tả trường product_photos_qty của bảng Products | E20: Text | F20: Text | G20: Conditional | H20: Attribute | K20: Theo kiểu dữ liệu | L20: Allow/derive theo quy tắc | M20: Giữ nguyên/chuẩn hóa ETL | N20: product_photos_qty | O20: Olist structure
A21: Products | B21: product_weight_g | C21: product_weight_g | D21: Đặc tả trường product_weight_g của bảng Products | E21: Number | F21: Number | G21: Conditional | H21: Attribute | K21: Theo kiểu dữ liệu | L21: Allow/derive theo quy tắc | M21: Giữ nguyên/chuẩn hóa ETL | N21: product_weight_g | O21: Olist structure
A22: Products | B22: product_length_cm | C22: product_length_cm | D22: Đặc tả trường product_length_cm của bảng Products | E22: Number | F22: Number | G22: Conditional | H22: Attribute | K22: Theo kiểu dữ liệu | L22: Allow/derive theo quy tắc | M22: Giữ nguyên/chuẩn hóa ETL | N22: product_length_cm | O22: Olist structure
A23: Products | B23: product_height_cm | C23: product_height_cm | D23: Đặc tả trường product_height_cm của bảng Products | E23: Number | F23: Number | G23: Conditional | H23: Attribute | K23: Theo kiểu dữ liệu | L23: Allow/derive theo quy tắc | M23: Giữ nguyên/chuẩn hóa ETL | N23: product_height_cm | O23: Olist structure
A24: Products | B24: product_width_cm | C24: product_width_cm | D24: Đặc tả trường product_width_cm của bảng Products | E24: Number | F24: Number | G24: Conditional | H24: Attribute | K24: Theo kiểu dữ liệu | L24: Allow/derive theo quy tắc | M24: Giữ nguyên/chuẩn hóa ETL | N24: product_width_cm | O24: Olist structure
A25: Products | B25: Description | C25: Description | D25: Đặc tả trường Description của bảng Products | E25: Text | F25: Text | G25: Conditional | H25: Attribute | K25: Theo kiểu dữ liệu | L25: Allow/derive theo quy tắc | M25: Giữ nguyên/chuẩn hóa ETL | N25: Description | O25: Olist structure
A26: Products | B26: ProductCategory | C26: ProductCategory | D26: Đặc tả trường ProductCategory của bảng Products | E26: Text | F26: Text | G26: Conditional | H26: Attribute | K26: Theo kiểu dữ liệu | L26: Allow/derive theo quy tắc | M26: Giữ nguyên/chuẩn hóa ETL | N26: ProductCategory | O26: Olist structure
A27: Products | B27: ListPrice | C27: Giá niêm yết | D27: Giá bán tham chiếu trung bình của sản phẩm, tính từ chi tiết đơn hàng | E27: Number | F27: #,##0 "₫" | G27: Yes | H27: Attribute | J27: Giá trị >= 0 | K27: Phải là số không âm | L27: Không để trống; 0 nếu chưa có giao dịch | M27: AVG OderItems.price theo product_id | N27: 420000 | O27: Derived/VN-added
A28: Products | B28: Currency | C28: Đơn vị tiền tệ | D28: Đơn vị tiền tệ áp dụng cho giá niêm yết sản phẩm | E28: Text | F28: 3 | G28: Yes | H28: Attribute | J28: VNĐ | K28: Giá trị phải bằng "VNĐ" | L28: Mặc định VNĐ | M28: Gán cố định "VNĐ" | N28: VNĐ | O28: VN-added
A29: Products | B29: ProductStatus | C29: Trạng thái sản phẩm | D29: Trạng thái đang kinh doanh hoặc ngừng kinh doanh của sản phẩm | E29: Text | F29: 20 | G29: Yes | H29: Attribute | J29: Active; Inactive | K29: Chỉ nhận Active hoặc Inactive | L29: Mặc định Active | M29: Gán "Active" cho dữ liệu demo | N29: Active | O29: VN-added
A30: Orders | B30: order_id | C30: order_id | D30: Đặc tả trường order_id của bảng Orders | E30: Text | F30: Text | G30: Yes | H30: PK/FK | I30: Orders.order_id | K30: Không trùng và không rỗng | L30: Reject | M30: Giữ nguyên/chuẩn hóa ETL | N30: order_id | O30: Olist structure
A31: Orders | B31: customer_id | C31: customer_id | D31: Đặc tả trường customer_id của bảng Orders | E31: Text | F31: Text | G31: Yes | H31: PK | K31: Không trùng và không rỗng | L31: Reject | M31: Giữ nguyên/chuẩn hóa ETL | N31: customer_id | O31: Olist structure
A32: Orders | B32: order_status | C32: order_status | D32: Đặc tả trường order_status của bảng Orders | E32: Text | F32: Text | G32: Conditional | H32: Attribute | J32: delivered,canceled,returned,processing | K32: Theo kiểu dữ liệu | L32: Allow/derive theo quy tắc | M32: Giữ nguyên/chuẩn hóa ETL | N32: order_status | O32: Olist structure
A33: Orders | B33: order_purchase_timestamp | C33: order_purchase_timestamp | D33: Đặc tả trường order_purchase_timestamp của bảng Orders | E33: Datetime | F33: yyyy-mm-dd hh:mm:ss | G33: Conditional | H33: Attribute | K33: Theo kiểu dữ liệu | L33: Allow/derive theo quy tắc | M33: Giữ nguyên/chuẩn hóa ETL | N33: order_purchase_timestamp | O33: Olist structure
A34: Orders | B34: order_approved_at | C34: order_approved_at | D34: Đặc tả trường order_approved_at của bảng Orders | E34: Datetime | F34: yyyy-mm-dd hh:mm:ss | G34: Conditional | H34: Attribute | K34: Theo kiểu dữ liệu | L34: Allow/derive theo quy tắc | M34: Giữ nguyên/chuẩn hóa ETL | N34: order_approved_at | O34: Olist structure
A35: Orders | B35: order_delivered_carrier_date | C35: order_delivered_carrier_date | D35: Đặc tả trường order_delivered_carrier_date của bảng Orders | E35: Datetime | F35: yyyy-mm-dd hh:mm:ss | G35: Conditional | H35: Attribute | K35: Theo kiểu dữ liệu | L35: Allow/derive theo quy tắc | M35: Giữ nguyên/chuẩn hóa ETL | N35: order_delivered_carrier_date | O35: Olist structure
A36: Orders | B36: order_delivered_customer_date | C36: order_delivered_customer_date | D36: Đặc tả trường order_delivered_customer_date của bảng Orders | E36: Datetime | F36: yyyy-mm-dd hh:mm:ss | G36: Conditional | H36: Attribute | K36: Theo kiểu dữ liệu | L36: Allow/derive theo quy tắc | M36: Giữ nguyên/chuẩn hóa ETL | N36: order_delivered_customer_date | O36: Olist structure
A37: Orders | B37: order_estimated_delivery_date | C37: order_estimated_delivery_date | D37: Đặc tả trường order_estimated_delivery_date của bảng Orders | E37: Datetime | F37: yyyy-mm-dd hh:mm:ss | G37: Conditional | H37: Attribute | K37: Theo kiểu dữ liệu | L37: Allow/derive theo quy tắc | M37: Giữ nguyên/chuẩn hóa ETL | N37: order_estimated_delivery_date | O37: Olist structure
A38: Orders | B38: CustomerID | C38: CustomerID | D38: Đặc tả trường CustomerID của bảng Orders | E38: Text | F38: Text | G38: Conditional | H38: FK | I38: Customers.customer_unique_id | K38: Phải tồn tại trong Customers.customer_unique_id | L38: Allow/derive theo quy tắc | M38: Giữ nguyên/chuẩn hóa ETL | N38: CustomerID | O38: Olist structure
A39: Orders | B39: SalesChannel | C39: SalesChannel | D39: Đặc tả trường SalesChannel của bảng Orders | E39: Text | F39: Text | G39: Conditional | H39: Attribute | K39: Theo kiểu dữ liệu | L39: Allow/derive theo quy tắc | M39: Giữ nguyên/chuẩn hóa ETL | N39: SalesChannel | O39: Olist structure
A40: Orders | B40: PaymentMethod | C40: PaymentMethod | D40: Đặc tả trường PaymentMethod của bảng Orders | E40: Text | F40: Text | G40: Conditional | H40: Attribute | K40: Theo kiểu dữ liệu | L40: Allow/derive theo quy tắc | M40: Giữ nguyên/chuẩn hóa ETL | N40: PaymentMethod | O40: Olist structure
A41: Orders | B41: Region | C41: Region | D41: Đặc tả trường Region của bảng Orders | E41: Text | F41: Text | G41: Conditional | H41: Attribute | K41: Theo kiểu dữ liệu | L41: Allow/derive theo quy tắc | M41: Giữ nguyên/chuẩn hóa ETL | N41: Region | O41: Olist structure
A42: Orders | B42: ProvinceCity | C42: ProvinceCity | D42: Đặc tả trường ProvinceCity của bảng Orders | E42: Text | F42: Text | G42: Conditional | H42: Attribute | K42: Theo kiểu dữ liệu | L42: Allow/derive theo quy tắc | M42: Giữ nguyên/chuẩn hóa ETL | N42: ProvinceCity | O42: Olist structure
A43: Orders | B43: owner_id | C43: Nhân viên phụ trách | D43: Đặc tả trường owner_id của bảng Orders | E43: Text | F43: Text | G43: Yes | H43: FK | I43: Employees.employee_id | K43: Phải tồn tại trong Employees.employee_id | L43: Allow/derive theo quy tắc | M43: Tính toán hoặc sinh theo SRS | N43: owner_id | O43: SRS/VN-added
A44: Orders | B44: OrderSubtotal | C44: Tổng tiền hàng | D44: Đặc tả trường OrderSubtotal của bảng Orders | E44: Number | F44: Number | G44: Conditional | H44: Attribute | K44: Theo kiểu dữ liệu | L44: Allow/derive theo quy tắc | M44: Tính toán hoặc sinh theo SRS | N44: OrderSubtotal | O44: SRS/VN-added
A45: Orders | B45: FreightTotal | C45: Tổng phí vận chuyển | D45: Đặc tả trường FreightTotal của bảng Orders | E45: Number | F45: Number | G45: Conditional | H45: Attribute | K45: Theo kiểu dữ liệu | L45: Allow/derive theo quy tắc | M45: Tính toán hoặc sinh theo SRS | N45: FreightTotal | O45: SRS/VN-added
A46: Orders | B46: DiscountTotal | C46: Tổng giảm giá | D46: Đặc tả trường DiscountTotal của bảng Orders | E46: Number | F46: Number | G46: Conditional | H46: Attribute | K46: Theo kiểu dữ liệu | L46: Allow/derive theo quy tắc | M46: Tính toán hoặc sinh theo SRS | N46: DiscountTotal | O46: SRS/VN-added
A47: Orders | B47: OrderTotal | C47: Tổng thanh toán | D47: Đặc tả trường OrderTotal của bảng Orders | E47: Number | F47: Number | G47: Conditional | H47: Attribute | K47: Theo kiểu dữ liệu | L47: Allow/derive theo quy tắc | M47: Tính toán hoặc sinh theo SRS | N47: OrderTotal | O47: SRS/VN-added
A48: Orders | B48: Currency | C48: Currency | D48: Đặc tả trường Currency của bảng Orders | E48: Text | F48: Text | G48: Conditional | H48: Attribute | K48: Theo kiểu dữ liệu | L48: Allow/derive theo quy tắc | M48: Giữ nguyên/chuẩn hóa ETL | N48: Currency | O48: Olist structure
A49: Orders | B49: IsValidForRFM | C49: Được tính RFM | D49: Đặc tả trường IsValidForRFM của bảng Orders | E49: Text | F49: Text | G49: Conditional | H49: Attribute | J49: TRUE,FALSE | K49: Theo kiểu dữ liệu | L49: Allow/derive theo quy tắc | M49: Tính toán hoặc sinh theo SRS | N49: IsValidForRFM | O49: SRS/VN-added
A50: OderItems | B50: order_id | C50: order_id | D50: Đặc tả trường order_id của bảng OderItems | E50: Text | F50: Text | G50: Yes | H50: PK/FK | I50: Orders.order_id | K50: Không trùng và không rỗng | L50: Reject | M50: Giữ nguyên/chuẩn hóa ETL | N50: order_id | O50: Olist structure
A51: OderItems | B51: order_item_id | C51: order_item_id | D51: Đặc tả trường order_item_id của bảng OderItems | E51: Text | F51: Text | G51: Yes | H51: Attribute | K51: Theo kiểu dữ liệu | L51: Allow/derive theo quy tắc | M51: Giữ nguyên/chuẩn hóa ETL | N51: order_item_id | O51: Olist structure
A52: OderItems | B52: product_id | C52: product_id | D52: Đặc tả trường product_id của bảng OderItems | E52: Text | F52: Text | G52: Yes | H52: PK | I52: Products.product_id | K52: Không trùng và không rỗng | L52: Reject | M52: Giữ nguyên/chuẩn hóa ETL | N52: product_id | O52: Olist structure
A53: OderItems | B53: seller_id | C53: seller_id | D53: Đặc tả trường seller_id của bảng OderItems | E53: Text | F53: Text | G53: Yes | H53: PK | I53: Sellers.seller_id | K53: Không trùng và không rỗng | L53: Reject | M53: Giữ nguyên/chuẩn hóa ETL | N53: seller_id | O53: Olist structure
A54: OderItems | B54: shipping_limit_date | C54: shipping_limit_date | D54: Đặc tả trường shipping_limit_date của bảng OderItems | E54: Datetime | F54: yyyy-mm-dd hh:mm:ss | G54: Conditional | H54: Attribute | K54: Theo kiểu dữ liệu | L54: Allow/derive theo quy tắc | M54: Giữ nguyên/chuẩn hóa ETL | N54: shipping_limit_date | O54: Olist structure
A55: OderItems | B55: price | C55: price | D55: Đặc tả trường price của bảng OderItems | E55: Number | F55: Number | G55: Conditional | H55: Attribute | K55: Theo kiểu dữ liệu | L55: Allow/derive theo quy tắc | M55: Giữ nguyên/chuẩn hóa ETL | N55: price | O55: Olist structure
A56: OderItems | B56: freight_value | C56: freight_value | D56: Đặc tả trường freight_value của bảng OderItems | E56: Number | F56: Number | G56: Conditional | H56: Attribute | K56: Theo kiểu dữ liệu | L56: Allow/derive theo quy tắc | M56: Giữ nguyên/chuẩn hóa ETL | N56: freight_value | O56: Olist structure
A57: OderItems | B57: Quantity | C57: Quantity | D57: Đặc tả trường Quantity của bảng OderItems | E57: Number | F57: Number | G57: Conditional | H57: Attribute | K57: Theo kiểu dữ liệu | L57: Allow/derive theo quy tắc | M57: Giữ nguyên/chuẩn hóa ETL | N57: Quantity | O57: Olist structure
A58: OderItems | B58: LineAmount | C58: LineAmount | D58: Đặc tả trường LineAmount của bảng OderItems | E58: Number | F58: Number | G58: Conditional | H58: Attribute | K58: Theo kiểu dữ liệu | L58: Allow/derive theo quy tắc | M58: Giữ nguyên/chuẩn hóa ETL | N58: LineAmount | O58: Olist structure
A59: OderItems | B59: OrderDetailID | C59: OrderDetailID | D59: Đặc tả trường OrderDetailID của bảng OderItems | E59: Text | F59: Text | G59: Conditional | H59: PK | K59: Không trùng và không rỗng | L59: Reject | M59: Giữ nguyên/chuẩn hóa ETL | N59: OrderDetailID | O59: Olist structure
A60: OderItems | B60: discount_value | C60: discount_value | D60: Đặc tả trường discount_value của bảng OderItems | E60: Number | F60: Number | G60: Conditional | H60: Attribute | K60: Theo kiểu dữ liệu | L60: Allow/derive theo quy tắc | M60: Tính toán hoặc sinh theo SRS | N60: discount_value | O60: SRS/VN-added
A61: OderItems | B61: line_subtotal | C61: line_subtotal | D61: Đặc tả trường line_subtotal của bảng OderItems | E61: Number | F61: Number | G61: Conditional | H61: Attribute | K61: Theo kiểu dữ liệu | L61: Allow/derive theo quy tắc | M61: Tính toán hoặc sinh theo SRS | N61: line_subtotal | O61: SRS/VN-added
A62: OderItems | B62: line_total | C62: line_total | D62: Đặc tả trường line_total của bảng OderItems | E62: Number | F62: Number | G62: Conditional | H62: Attribute | K62: Theo kiểu dữ liệu | L62: Allow/derive theo quy tắc | M62: Tính toán hoặc sinh theo SRS | N62: line_total | O62: SRS/VN-added
A63: Payments | B63: order_id | C63: order_id | D63: Đặc tả trường order_id của bảng Payments | E63: Text | F63: Text | G63: Yes | H63: PK/FK | I63: Orders.order_id | K63: Không trùng và không rỗng | L63: Reject | M63: Giữ nguyên/chuẩn hóa ETL | N63: order_id | O63: Olist structure
A64: Payments | B64: payment_sequential | C64: payment_sequential | D64: Đặc tả trường payment_sequential của bảng Payments | E64: Text | F64: Text | G64: Conditional | H64: Attribute | K64: Theo kiểu dữ liệu | L64: Allow/derive theo quy tắc | M64: Giữ nguyên/chuẩn hóa ETL | N64: payment_sequential | O64: Olist structure
A65: Payments | B65: payment_type | C65: payment_type | D65: Đặc tả trường payment_type của bảng Payments | E65: Text | F65: Text | G65: Conditional | H65: Attribute | K65: Theo kiểu dữ liệu | L65: Allow/derive theo quy tắc | M65: Giữ nguyên/chuẩn hóa ETL | N65: payment_type | O65: Olist structure
A66: Payments | B66: payment_installments | C66: payment_installments | D66: Đặc tả trường payment_installments của bảng Payments | E66: Number | F66: Number | G66: Conditional | H66: Attribute | K66: Theo kiểu dữ liệu | L66: Allow/derive theo quy tắc | M66: Giữ nguyên/chuẩn hóa ETL | N66: payment_installments | O66: Olist structure
A67: Payments | B67: payment_value | C67: payment_value | D67: Đặc tả trường payment_value của bảng Payments | E67: Number | F67: Number | G67: Conditional | H67: Attribute | K67: Theo kiểu dữ liệu | L67: Allow/derive theo quy tắc | M67: Giữ nguyên/chuẩn hóa ETL | N67: payment_value | O67: Olist structure
A68: Payments | B68: PaymentMethodVN | C68: PaymentMethodVN | D68: Đặc tả trường PaymentMethodVN của bảng Payments | E68: Text | F68: Text | G68: Conditional | H68: Attribute | K68: Theo kiểu dữ liệu | L68: Allow/derive theo quy tắc | M68: Giữ nguyên/chuẩn hóa ETL | N68: PaymentMethodVN | O68: Olist structure
A69: Payments | B69: Currency | C69: Currency | D69: Đặc tả trường Currency của bảng Payments | E69: Text | F69: Text | G69: Conditional | H69: Attribute | K69: Theo kiểu dữ liệu | L69: Allow/derive theo quy tắc | M69: Giữ nguyên/chuẩn hóa ETL | N69: Currency | O69: Olist structure
A70: Reviews | B70: review_id | C70: review_id | D70: Đặc tả trường review_id của bảng Reviews | E70: Text | F70: Text | G70: Yes | H70: PK | K70: Không trùng và không rỗng | L70: Reject | M70: Giữ nguyên/chuẩn hóa ETL | N70: review_id | O70: Olist structure
A71: Reviews | B71: order_id | C71: order_id | D71: Đặc tả trường order_id của bảng Reviews | E71: Text | F71: Text | G71: Yes | H71: PK/FK | I71: Orders.order_id | K71: Không trùng và không rỗng | L71: Reject | M71: Giữ nguyên/chuẩn hóa ETL | N71: order_id | O71: Olist structure
A72: Reviews | B72: review_score | C72: review_score | D72: Đặc tả trường review_score của bảng Reviews | E72: Number | F72: Number | G72: Conditional | H72: Attribute | K72: Theo kiểu dữ liệu | L72: Allow/derive theo quy tắc | M72: Giữ nguyên/chuẩn hóa ETL | N72: review_score | O72: Olist structure
A73: Reviews | B73: review_comment_title | C73: review_comment_title | D73: Đặc tả trường review_comment_title của bảng Reviews | E73: Text | F73: Text | G73: Conditional | H73: Attribute | K73: Theo kiểu dữ liệu | L73: Allow/derive theo quy tắc | M73: Giữ nguyên/chuẩn hóa ETL | N73: review_comment_title | O73: Olist structure
A74: Reviews | B74: review_comment_message | C74: review_comment_message | D74: Đặc tả trường review_comment_message của bảng Reviews | E74: Text | F74: Text | G74: Conditional | H74: Attribute | K74: Theo kiểu dữ liệu | L74: Allow/derive theo quy tắc | M74: Giữ nguyên/chuẩn hóa ETL | N74: review_comment_message | O74: Olist structure
A75: Reviews | B75: review_creation_date | C75: review_creation_date | D75: Đặc tả trường review_creation_date của bảng Reviews | E75: Datetime | F75: yyyy-mm-dd hh:mm:ss | G75: Conditional | H75: Attribute | K75: Theo kiểu dữ liệu | L75: Allow/derive theo quy tắc | M75: Giữ nguyên/chuẩn hóa ETL | N75: review_creation_date | O75: Olist structure
A76: Reviews | B76: review_answer_timestamp | C76: review_answer_timestamp | D76: Đặc tả trường review_answer_timestamp của bảng Reviews | E76: Datetime | F76: yyyy-mm-dd hh:mm:ss | G76: Conditional | H76: Attribute | K76: Theo kiểu dữ liệu | L76: Allow/derive theo quy tắc | M76: Giữ nguyên/chuẩn hóa ETL | N76: review_answer_timestamp | O76: Olist structure
A77: Reviews | B77: CustomerID | C77: CustomerID | D77: Đặc tả trường CustomerID của bảng Reviews | E77: Text | F77: Text | G77: Conditional | H77: FK | I77: Customers.customer_unique_id | K77: Phải tồn tại trong Customers.customer_unique_id | L77: Allow/derive theo quy tắc | M77: Giữ nguyên/chuẩn hóa ETL | N77: CustomerID | O77: Olist structure
A78: Reviews | B78: Channel | C78: Channel | D78: Đặc tả trường Channel của bảng Reviews | E78: Text | F78: Text | G78: Conditional | H78: Attribute | K78: Theo kiểu dữ liệu | L78: Allow/derive theo quy tắc | M78: Giữ nguyên/chuẩn hóa ETL | N78: Channel | O78: Olist structure
A79: Sellers | B79: seller_id | C79: seller_id | D79: Đặc tả trường seller_id của bảng Sellers | E79: Text | F79: Text | G79: Yes | H79: PK | I79: Sellers.seller_id | K79: Không trùng và không rỗng | L79: Reject | M79: Giữ nguyên/chuẩn hóa ETL | N79: seller_id | O79: Olist structure
A80: Sellers | B80: seller_zip_code_prefix | C80: seller_zip_code_prefix | D80: Đặc tả trường seller_zip_code_prefix của bảng Sellers | E80: Text | F80: Text | G80: Conditional | H80: Attribute | K80: Theo kiểu dữ liệu | L80: Allow/derive theo quy tắc | M80: Giữ nguyên/chuẩn hóa ETL | N80: seller_zip_code_prefix | O80: Olist structure
A81: Sellers | B81: seller_city | C81: seller_city | D81: Đặc tả trường seller_city của bảng Sellers | E81: Text | F81: Text | G81: Conditional | H81: Attribute | K81: Theo kiểu dữ liệu | L81: Allow/derive theo quy tắc | M81: Giữ nguyên/chuẩn hóa ETL | N81: seller_city | O81: Olist structure
A82: Sellers | B82: seller_state | C82: seller_state | D82: Đặc tả trường seller_state của bảng Sellers | E82: Text | F82: Text | G82: Conditional | H82: Attribute | K82: Theo kiểu dữ liệu | L82: Allow/derive theo quy tắc | M82: Giữ nguyên/chuẩn hóa ETL | N82: seller_state | O82: Olist structure
A83: Sellers | B83: Region | C83: Region | D83: Đặc tả trường Region của bảng Sellers | E83: Text | F83: Text | G83: Conditional | H83: Attribute | K83: Theo kiểu dữ liệu | L83: Allow/derive theo quy tắc | M83: Giữ nguyên/chuẩn hóa ETL | N83: Region | O83: Olist structure
A84: Sellers | B84: SellerName | C84: SellerName | D84: Đặc tả trường SellerName của bảng Sellers | E84: Text | F84: Text | G84: Conditional | H84: Attribute | K84: Theo kiểu dữ liệu | L84: Allow/derive theo quy tắc | M84: Giữ nguyên/chuẩn hóa ETL | N84: SellerName | O84: Olist structure
A85: Geolocation | B85: geolocation_zip_code_prefix | C85: geolocation_zip_code_prefix | D85: Đặc tả trường geolocation_zip_code_prefix của bảng Geolocation | E85: Text | F85: Text | G85: Conditional | H85: Attribute | K85: Theo kiểu dữ liệu | L85: Allow/derive theo quy tắc | M85: Giữ nguyên/chuẩn hóa ETL | N85: geolocation_zip_code_prefix | O85: Olist structure
A86: Geolocation | B86: geolocation_lat | C86: geolocation_lat | D86: Đặc tả trường geolocation_lat của bảng Geolocation | E86: Text | F86: Text | G86: Conditional | H86: Attribute | K86: Theo kiểu dữ liệu | L86: Allow/derive theo quy tắc | M86: Giữ nguyên/chuẩn hóa ETL | N86: geolocation_lat | O86: Olist structure
A87: Geolocation | B87: geolocation_lng | C87: geolocation_lng | D87: Đặc tả trường geolocation_lng của bảng Geolocation | E87: Text | F87: Text | G87: Conditional | H87: Attribute | K87: Theo kiểu dữ liệu | L87: Allow/derive theo quy tắc | M87: Giữ nguyên/chuẩn hóa ETL | N87: geolocation_lng | O87: Olist structure
A88: Geolocation | B88: geolocation_city | C88: geolocation_city | D88: Đặc tả trường geolocation_city của bảng Geolocation | E88: Text | F88: Text | G88: Conditional | H88: Attribute | K88: Theo kiểu dữ liệu | L88: Allow/derive theo quy tắc | M88: Giữ nguyên/chuẩn hóa ETL | N88: geolocation_city | O88: Olist structure
A89: Geolocation | B89: geolocation_state | C89: geolocation_state | D89: Đặc tả trường geolocation_state của bảng Geolocation | E89: Text | F89: Text | G89: Conditional | H89: Attribute | K89: Theo kiểu dữ liệu | L89: Allow/derive theo quy tắc | M89: Giữ nguyên/chuẩn hóa ETL | N89: geolocation_state | O89: Olist structure
A90: Geolocation | B90: Region | C90: Region | D90: Đặc tả trường Region của bảng Geolocation | E90: Text | F90: Text | G90: Conditional | H90: Attribute | K90: Theo kiểu dữ liệu | L90: Allow/derive theo quy tắc | M90: Giữ nguyên/chuẩn hóa ETL | N90: Region | O90: Olist structure
A91: Employees | B91: employee_id | C91: employee_id | D91: Đặc tả trường employee_id của bảng Employees | E91: Text | F91: Text | G91: Yes | H91: PK | K91: Không trùng và không rỗng | L91: Reject | M91: Tính toán hoặc sinh theo SRS | N91: employee_id | O91: SRS/VN-added
... A96: Employees | B96: region_scope | C96: region_scope | D96: Đặc tả trường region_scope của bảng Employees | E96: Text | F96: Text | G96: Conditional | H96: Attribute | K96: Theo kiểu dữ liệu | L96: Allow/derive theo quy tắc | M96: Tính toán hoặc sinh theo SRS | N96: region_scope | O96: SRS/VN-added
A97: Employees | B97: status | C97: status | D97: Đặc tả trường status của bảng Employees | E97: Text | F97: Text | G97: Conditional | H97: Attribute | J97: Active,Inactive,Completed,Not trained | K97: Theo kiểu dữ liệu | L97: Allow/derive theo quy tắc | M97: Tính toán hoặc sinh theo SRS | N97: status | O97: SRS/VN-added
A98: Employees | B98: start_date | C98: start_date | D98: Đặc tả trường start_date của bảng Employees | E98: Datetime | F98: yyyy-mm-dd hh:mm:ss | G98: Conditional | H98: Attribute | K98: Theo kiểu dữ liệu | L98: Allow/derive theo quy tắc | M98: Tính toán hoặc sinh theo SRS | N98: start_date | O98: SRS/VN-added
A99: Interactions | B99: interaction_id | C99: interaction_id | D99: Đặc tả trường interaction_id của bảng Interactions | E99: Text | F99: Text | G99: Yes | H99: PK | K99: Không trùng và không rỗng | L99: Reject | M99: Tính toán hoặc sinh theo SRS | N99: interaction_id | O99: SRS/VN-added
A100: Interactions | B100: customer_unique_id | C100: customer_unique_id | D100: Đặc tả trường customer_unique_id của bảng Interactions | E100: Text | F100: Text | G100: Yes | H100: FK | I100: Customers.customer_unique_id | K100: Phải tồn tại trong Customers.customer_unique_id | L100: Allow/derive theo quy tắc | M100: Tính toán hoặc sinh theo SRS | N100: customer_unique_id | O100: SRS/VN-added
A101: Interactions | B101: product_id | C101: product_id | D101: Đặc tả trường product_id của bảng Interactions | E101: Text | F101: Text | G101: Yes | H101: PK | I101: Products.product_id | K101: Không trùng và không rỗng | L101: Reject | M101: Tính toán hoặc sinh theo SRS | N101: product_id | O101: SRS/VN-added
A102: Interactions | B102: interaction_type | C102: Loại tương tác | D102: Đặc tả trường interaction_type của bảng Interactions | E102: Text | F102: Text | G102: Conditional | H102: Attribute | J102: product_view,search,add_to_cart,wishlist,checkout_started,email_open,email_click,chat | K102: Theo kiểu dữ liệu | L102: Allow/derive theo quy tắc | M102: Tính toán hoặc sinh theo SRS | N102: interaction_type | O102: SRS/VN-added
A103: Interactions | B103: interaction_timestamp | C103: interaction_timestamp | D103: Đặc tả trường interaction_timestamp của bảng Interactions | E103: Datetime | F103: yyyy-mm-dd hh:mm:ss | G103: Conditional | H103: Attribute | K103: Theo kiểu dữ liệu | L103: Allow/derive theo quy tắc | M103: Tính toán hoặc sinh theo SRS | N103: interaction_timestamp | O103: SRS/VN-added
A104: Interactions | B104: channel | C104: channel | D104: Đặc tả trường channel của bảng Interactions | E104: Text | F104: Text | G104: Conditional | H104: Attribute | K104: Theo kiểu dữ liệu | L104: Allow/derive theo quy tắc | M104: Tính toán hoặc sinh theo SRS | N104: channel | O104: SRS/VN-added
...

Sheet Employees
A1: employee_id | B1: employee_name | C1: department | D1: email | E1: phone | F1: region_scope | G1: status | H1: start_date
A2: EMP001 | B2: Nguyễn Minh Anh | C2: Kinh doanh | D2: minhanh@demo.vn | E2: 0901 000 001 | F2: Miền Bắc | G2: Active | H2: 45292
A3: EMP002 | B3: Trần Quốc Bảo | C3: Kinh doanh | D3: quocbao@demo.vn | E3: 0901 000 002 | F3: Miền Bắc | G3: Active | H3: 45323
A4: EMP003 | B4: Lê Thu Hà | C4: Chăm sóc khách hàng | D4: thuha@demo.vn | E4: 0901 000 003 | F4: Miền Trung | G4: Active | H4: 45352
A5: EMP004 | B5: Phạm Gia Huy | C5: Kinh doanh | D5: giahuy@demo.vn | E5: 0901 000 004 | F5: Miền Trung | G5: Active | H5: 45383
A6: EMP005 | B6: Võ Ngọc Lan | C6: Chăm sóc khách hàng | D6: ngoclan@demo.vn | E6: 0901 000 005 | F6: Miền Nam | G6: Active | H6: 45413
A7: EMP006 | B7: Bùi Thanh Nam | C7: Kinh doanh | D7: thanhnam@demo.vn | E7: 0901 000 006 | F7: Miền Nam | G7: Active | H7: 45444
A8: EMP007 | B8: Đặng Minh Phúc | C8: Marketing | D8: minhphuc@demo.vn | E8: 0901 000 007 | F8: Toàn quốc | G8: Active | H8: 45474
A9: EMP008 | B9: Hoàng Thu Trang | C9: Marketing | D9: thutrang@demo.vn | E9: 0901 000 008 | F9: Toàn quốc | G9: Active | H9: 45505

Sheet Interactions
A1: interaction_id | B1: customer_unique_id | C1: product_id | D1: interaction_type | E1: interaction_timestamp | F1: channel | G1: session_id | H1: campaign_id | I1: interaction_value | J1: interaction_result
A2: INT00001 | B2: KH0001 | C2: SP012 | D2: search | E2: 46056.655 | F2: Ứng dụng | G2: SES000101 | H2: CAM002 | I2: 1 | J2: results_viewed
A3: INT00002 | B3: KH0001 | C3: SP034 | D3: checkout_started | E3: 45959.32 | F3: Email | G3: SES000102 | I3: 4 | J3: started
A4: INT00003 | B4: KH0001 | C4: SP008 | D4: chat | E4: 45940.345 | F4: Chat | G4: SES000103 | I4: 3 | J4: contacted
A5: INT00004 | B5: KH0001 | C5: SP005 | D5: add_to_cart | E5: 45501.566 | F5: Website | G5: SES000104 | H5: CAM001 | I5: 3 | J5: added
A6: INT00005 | B6: KH0001 | C6: SP021 | D6: email_open | E6: 45848.54 | F6: Ứng dụng | G6: SES000105 | I6: 1 | J6: opened
A7: INT00006 | B7: KH0001 | C7: SP026 | D7: product_view | E7: 46219.744 | F7: Email | G7: SES000106 | I7: 1 | J7: viewed
A8: INT00007 | B8: KH0002 | C8: SP035 | D8: add_to_cart | E8: 46189.58 | F8: Email | G8: SES000201 | H8: CAM003 | I8: 3 | J8: added
A9: INT00008 | B9: KH0002 | C9: SP004 | D9: email_open | E9: 45551.078 | F9: Chat | G9: SES000202 | I9: 1 | J9: opened
A10: INT00009 | B10: KH0002 | C10: SP028 | D10: product_view | E10: 45601.511 | F10: Website | G10: SES000203 | I10: 1 | J10: viewed
A11: INT00010 | B11: KH0002 | C11: SP040 | D11: wishlist | E11: 46128.362 | F11: Ứng dụng | G11: SES000204 | H11: CAM002 | I11: 2 | J11: saved
A12: INT00011 | B12: KH0002 | C12: SP001 | D12: email_click | E12: 45690.682 | F12: Email | G12: SES000205 | I12: 2 | J12: clicked
A13: INT00012 | B13: KH0002 | C13: SP035 | D13: search | E13: 45820.522 | F13: Chat | G13: SES000206 | I13: 1 | J13: results_viewed
A14: INT00013 | B14: KH0003 | C14: SP026 | D14: wishlist | E14: 45825.018 | F14: Chat | G14: SES000301 | H14: CAM004 | I14: 2 | J14: saved
A15: INT00014 | B15: KH0003 | C15: SP025 | D15: email_click | E15: 45453.639 | F15: Website | G15: SES000302 | I15: 2 | J15: clicked
A16: INT00015 | B16: KH0003 | C16: SP010 | D16: search | E16: 45397.388 | F16: Ứng dụng | G16: SES000303 | I16: 1 | J16: results_viewed
A17: INT00016 | B17: KH0003 | C17: SP023 | D17: checkout_started | E17: 45321.027 | F17: Email | G17: SES000304 | H17: CAM003 | I17: 4 | J17: started
A18: INT00017 | B18: KH0003 | C18: SP016 | D18: chat | E18: 46216.791 | F18: Chat | G18: SES000305 | I18: 3 | J18: contacted
A19: INT00018 | B19: KH0003 | C19: SP006 | D19: add_to_cart | E19: 45678.094 | F19: Website | G19: SES000306 | I19: 3 | J19: added
A20: INT00019 | B20: KH0004 | C20: SP024 | D20: checkout_started | E20: 45478.519 | F20: Website | G20: SES000401 | H20: CAM001 | I20: 4 | J20: started
A21: INT00020 | B21: KH0004 | C21: SP025 | D21: chat | E21: 45408.982 | F21: Ứng dụng | G21: SES000402 | I21: 3 | J21: contacted
A22: INT00021 | B22: KH0004 | C22: SP016 | D22: add_to_cart | E22: 45466.344 | F22: Email | G22: SES000403 | I22: 3 | J22: added
A23: INT00022 | B23: KH0004 | C23: SP018 | D23: email_open | E23: 45477.885 | F23: Chat | G23: SES000404 | H23: CAM004 | I23: 1 | J23: opened
A24: INT00023 | B24: KH0004 | C24: SP027 | D24: product_view | E24: 45961.945 | F24: Website | G24: SES000405 | I24: 1 | J24: viewed
A25: INT00024 | B25: KH0004 | C25: SP040 | D25: wishlist | E25: 45695.635 | F25: Ứng dụng | G25: SES000406 | I25: 2 | J25: saved
A26: INT00025 | B26: KH0005 | C26: SP009 | D26: email_open | E26: 45535.556 | F26: Ứng dụng | G26: SES000501 | H26: CAM002 | I26: 1 | J26: opened
A27: INT00026 | B27: KH0005 | C27: SP040 | D27: product_view | E27: 46146.118 | F27: Email | G27: SES000502 | I27: 1 | J27: viewed
A28: INT00027 | B28: KH0005 | C28: SP014 | D28: wishlist | E28: 45500.956 | F28: Chat | G28: SES000503 | I28: 2 | J28: saved
A29: INT00028 | B29: KH0005 | C29: SP034 | D29: email_click | E29: 46001.442 | F29: Website | G29: SES000504 | H29: CAM001 | I29: 2 | J29: clicked
A30: INT00029 | B30: KH0005 | C30: SP001 | D30: search | E30: 45923.803 | F30: Ứng dụng | G30: SES000505 | I30: 1 | J30: results_viewed
A31: INT00030 | B31: KH0005 | C31: SP028 | D31: checkout_started | E31: 45464.012 | F31: Email | G31: SES000506 | I31: 4 | J31: started
A32: INT00031 | B32: KH0006 | C32: SP016 | D32: email_click | E32: 45765.665 | F32: Email | G32: SES000601 | H32: CAM003 | I32: 2 | J32: clicked
A33: INT00032 | B33: KH0006 | C33: SP035 | D33: search | E33: 45942.986 | F33: Chat | G33: SES000602 | I33: 1 | J33: results_viewed
A34: INT00033 | B34: KH0006 | C34: SP014 | D34: checkout_started | E34: 46216.396 | F34: Website | G34: SES000603 | I34: 4 | J34: started
A35: INT00034 | B35: KH0006 | C35: SP019 | D35: chat | E35: 46145.375 | F35: Ứng dụng | G35: SES000604 | H35: CAM002 | I35: 3 | J35: contacted
A36: INT00035 | B36: KH0006 | C36: SP037 | D36: add_to_cart | E36: 45921.28 | F36: Email | G36: SES000605 | I36: 3 | J36: added
A37: INT00036 | B37: KH0006 | C37: SP006 | D37: email_open | E37: 46093.484 | F37: Chat | G37: SES000606 | I37: 1 | J37: opened
A38: INT00037 | B38: KH0007 | C38: SP035 | D38: chat | E38: 45687.291 | F38: Chat | G38: SES000701 | H38: CAM004 | I38: 3 | J38: contacted
A39: INT00038 | B39: KH0007 | C39: SP029 | D39: add_to_cart | E39: 45714.045 | F39: Website | G39: SES000702 | I39: 3 | J39: added
A40: INT00039 | B40: KH0007 | C40: SP011 | D40: email_open | E40: 45358.368 | F40: Ứng dụng | G40: SES000703 | I40: 1 | J40: opened
A41: INT00040 | B41: KH0007 | C41: SP033 | D41: product_view | E41: 45622.202 | F41: Email | G41: SES000704 | H41: CAM003 | I41: 1 | J41: viewed
A42: INT00041 | B42: KH0007 | C42: SP027 | D42: wishlist | E42: 45695.307 | F42: Chat | G42: SES000705 | I42: 2 | J42: saved
A43: INT00042 | B43: KH0007 | C43: SP035 | D43: email_click | E43: 45591.224 | F43: Website | G43: SES000706 | I43: 2 | J43: clicked
A44: INT00043 | B44: KH0008 | C44: SP033 | D44: product_view | E44: 46131.477 | F44: Website | G44: SES000801 | H44: CAM001 | I44: 1 | J44: viewed
A45: INT00044 | B45: KH0008 | C45: SP018 | D45: wishlist | E45: 45403.315 | F45: Ứng dụng | G45: SES000802 | I45: 2 | J45: saved
A46: INT00045 | B46: KH0008 | C46: SP023 | D46: email_click | E46: 45952.353 | F46: Email | G46: SES000803 | I46: 2 | J46: clicked
A47: INT00046 | B47: KH0008 | C47: SP018 | D47: search | E47: 45754.873 | F47: Chat | G47: SES000804 | H47: CAM004 | I47: 1 | J47: results_viewed
A48: INT00047 | B48: KH0008 | C48: SP039 | D48: checkout_started | E48: 45844.699 | F48: Website | G48: SES000805 | I48: 4 | J48: started
A49: INT00048 | B49: KH0008 | C49: SP033 | D49: chat | E49: 45485.006 | F49: Ứng dụng | G49: SES000806 | I49: 3 | J49: contacted
A50: INT00049 | B50: KH0009 | C50: SP030 | D50: search | E50: 45543.373 | F50: Ứng dụng | G50: SES000901 | H50: CAM002 | I50: 1 | J50: results_viewed
A51: INT00050 | B51: KH0009 | C51: SP027 | D51: checkout_started | E51: 45568.595 | F51: Email | G51: SES000902 | I51: 4 | J51: started
A52: INT00051 | B52: KH0009 | C52: SP002 | D52: chat | E52: 45439.065 | F52: Chat | G52: SES000903 | I52: 3 | J52: contacted
A53: INT00052 | B53: KH0009 | C53: SP004 | D53: add_to_cart | E53: 45457.864 | F53: Website | G53: SES000904 | H53: CAM001 | I53: 3 | J53: added
A54: INT00053 | B54: KH0009 | C54: SP003 | D54: email_open | E54: 45811.018 | F54: Ứng dụng | G54: SES000905 | I54: 1 | J54: opened
A55: INT00054 | B55: KH0009 | C55: SP036 | D55: product_view | E55: 45506.674 | F55: Email | G55: SES000906 | I55: 1 | J55: viewed
A56: INT00055 | B56: KH0010 | C56: SP031 | D56: add_to_cart | E56: 45426.86 | F56: Email | G56: SES001001 | H56: CAM003 | I56: 3 | J56: added
A57: INT00056 | B57: KH0010 | C57: SP002 | D57: email_open | E57: 45406.856 | F57: Chat | G57: SES001002 | I57: 1 | J57: opened
A58: INT00057 | B58: KH0010 | C58: SP009 | D58: product_view | E58: 45986.264 | F58: Website | G58: SES001003 | I58: 1 | J58: viewed
A59: INT00058 | B59: KH0010 | C59: SP012 | D59: wishlist | E59: 45700.194 | F59: Ứng dụng | G59: SES001004 | H59: CAM002 | I59: 2 | J59: saved
A60: INT00059 | B60: KH0010 | C60: SP003 | D60: email_click | E60: 46169.226 | F60: Email | G60: SES001005 | I60: 2 | J60: clicked
A61: INT00060 | B61: KH0010 | C61: SP024 | D61: search | E61: 45342.447 | F61: Chat | G61: SES001006 | I61: 1 | J61: results_viewed
A62: INT00061 | B62: KH0011 | C62: SP004 | D62: wishlist | E62: 45882.459 | F62: Chat | G62: SES001101 | H62: CAM004 | I62: 2 | J62: saved
A63: INT00062 | B63: KH0011 | C63: SP023 | D63: email_click | E63: 45829.406 | F63: Website | G63: SES001102 | I63: 2 | J63: clicked
A64: INT00063 | B64: KH0011 | C64: SP037 | D64: search | E64: 45778.66 | F64: Ứng dụng | G64: SES001103 | I64: 1 | J64: results_viewed
A65: INT00064 | B65: KH0011 | C65: SP033 | D65: checkout_started | E65: 45866.638 | F65: Email | G65: SES001104 | H65: CAM003 | I65: 4 | J65: started
A66: INT00065 | B66: KH0011 | C66: SP033 | D66: chat | E66: 46075.549 | F66: Chat | G66: SES001105 | I66: 3 | J66: contacted
A67: INT00066 | B67: KH0011 | C67: SP027 | D67: add_to_cart | E67: 45525.774 | F67: Website | G67: SES001106 | I67: 3 | J67: added
A68: INT00067 | B68: KH0012 | C68: SP023 | D68: checkout_started | E68: 46099.263 | F68: Website | G68: SES001201 | H68: CAM001 | I68: 4 | J68: started
A69: INT00068 | B69: KH0012 | C69: SP017 | D69: chat | E69: 45659.991 | F69: Ứng dụng | G69: SES001202 | I69: 3 | J69: contacted
A70: INT00069 | B70: KH0012 | C70: SP011 | D70: add_to_cart | E70: 45477.452 | F70: Email | G70: SES001203 | I70: 3 | J70: added
A71: INT00070 | B71: KH0012 | C71: SP026 | D71: email_open | E71: 45621.359 | F71: Chat | G71: SES001204 | H71: CAM004 | I71: 1 | J71: opened
A72: INT00071 | B72: KH0012 | C72: SP018 | D72: product_view | E72: 45918.865 | F72: Website | G72: SES001205 | I72: 1 | J72: viewed
A73: INT00072 | B73: KH0012 | C73: SP038 | D73: wishlist | E73: 45534.923 | F73: Ứng dụng | G73: SES001206 | I73: 2 | J73: saved
A74: INT00073 | B74: KH0013 | C74: SP004 | D74: email_open | E74: 45769.818 | F74: Ứng dụng | G74: SES001301 | H74: CAM002 | I74: 1 | J74: opened
A75: INT00074 | B75: KH0013 | C75: SP020 | D75: product_view | E75: 46168.472 | F75: Email | G75: SES001302 | I75: 1 | J75: viewed
A76: INT00075 | B76: KH0013 | C76: SP018 | D76: wishlist | E76: 45391.358 | F76: Chat | G76: SES001303 | I76: 2 | J76: saved
A77: INT00076 | B77: KH0013 | C77: SP016 | D77: email_click | E77: 45786.82 | F77: Website | G77: SES001304 | H77: CAM001 | I77: 2 | J77: clicked
A78: INT00077 | B78: KH0013 | C78: SP028 | D78: search | E78: 45416.664 | F78: Ứng dụng | G78: SES001305 | I78: 1 | J78: results_viewed
A79: INT00078 | B79: KH0013 | C79: SP039 | D79: checkout_started | E79: 45729.77 | F79: Email | G79: SES001306 | I79: 4 | J79: started
A80: INT00079 | B80: KH0014 | C80: SP029 | D80: email_click | E80: 45904.875 | F80: Email | G80: SES001401 | H80: CAM003 | I80: 2 | J80: clicked
A81: INT00080 | B81: KH0014 | C81: SP013 | D81: search | E81: 46126.78 | F81: Chat | G81: SES001402 | I81: 1 | J81: results_viewed
A82: INT00081 | B82: KH0014 | C82: SP018 | D82: checkout_started | E82: 46213.616 | F82: Website | G82: SES001403 | I82: 4 | J82: started
A83: INT00082 | B83: KH0014 | C83: SP018 | D83: chat | E83: 45788.204 | F83: Ứng dụng | G83: SES001404 | H83: CAM002 | I83: 3 | J83: contacted
A84: INT00083 | B84: KH0014 | C84: SP029 | D84: add_to_cart | E84: 45665.652 | F84: Email | G84: SES001405 | I84: 3 | J84: added
A85: INT00084 | B85: KH0014 | C85: SP002 | D85: email_open | E85: 45624.005 | F85: Chat | G85: SES001406 | I85: 1 | J85: opened
A86: INT00085 | B86: KH0015 | C86: SP008 | D86: chat | E86: 45309.739 | F86: Chat | G86: SES001501 | H86: CAM004 | I86: 3 | J86: contacted
A87: INT00086 | B87: KH0015 | C87: SP034 | D87: add_to_cart | E87: 45705.505 | F87: Website | G87: SES001502 | I87: 3 | J87: added
A88: INT00087 | B88: KH0015 | C88: SP015 | D88: email_open | E88: 45472.7 | F88: Ứng dụng | G88: SES001503 | I88: 1 | J88: opened
A89: INT00088 | B89: KH0015 | C89: SP037 | D89: product_view | E89: 45914.166 | F89: Email | G89: SES001504 | H89: CAM003 | I89: 1 | J89: viewed
A90: INT00089 | B90: KH0015 | C90: SP037 | D90: wishlist | E90: 45431.195 | F90: Chat | G90: SES001505 | I90: 2 | J90: saved
A91: INT00090 | B91: KH0015 | C91: SP008 | D91: email_click | E91: 45551.122 | F91: Website | G91: SES001506 | I91: 2 | J91: clicked
A92: INT00091 | B92: KH0016 | C92: SP028 | D92: product_view | E92: 45874.631 | F92: Website | G92: SES001601 | H92: CAM001 | I92: 1 | J92: viewed
A93: INT00092 | B93: KH0016 | C93: SP027 | D93: wishlist | E93: 45301.275 | F93: Ứng dụng | G93: SES001602 | I93: 2 | J93: saved
A94: INT00093 | B94: KH0016 | C94: SP001 | D94: email_click | E94: 45558.206 | F94: Email | G94: SES001603 | I94: 2 | J94: clicked
A95: INT00094 | B95: KH0016 | C95: SP028 | D95: search | E95: 45506.791 | F95: Chat | G95: SES001604 | H95: CAM004 | I95: 1 | J95: results_viewed
A96: INT00095 | B96: KH0016 | C96: SP001 | D96: checkout_started | E96: 45992.26 | F96: Website | G96: SES001605 | I96: 4 | J96: started
A97: INT00096 | B97: KH0016 | C97: SP005 | D97: chat | E97: 46096.86 | F97: Ứng dụng | G97: SES001606 | I97: 3 | J97: contacted
A98: INT00097 | B98: KH0017 | C98: SP019 | D98: search | E98: 46164.069 | F98: Ứng dụng | G98: SES001701 | H98: CAM002 | I98: 1 | J98: results_viewed
A99: INT00098 | B99: KH0017 | C99: SP002 | D99: checkout_started | E99: 45661.14 | F99: Email | G99: SES001702 | I99: 4 | J99: started
A100: INT00099 | B100: KH0017 | C100: SP037 | D100: chat | E100: 46148.831 | F100: Chat | G100: SES001703 | I100: 3 | J100: contacted
...

Sheet Campaigns
A1: campaign_id | B1: campaign_name | C1: campaign_type | D1: start_date | E1: end_date | F1: channel | G1: target_segment | H1: status | I1: budget_vnd
A2: CAM001 | B2: Khuyến mãi Tết | C2: Promotion | D2: 45292 | E2: 45352 | F2: Email/App | G2: Khách hàng hiện hữu | H2: Completed | I2: 80000000
A3: CAM002 | B3: Hè năng động | C3: Seasonal | D3: 45444 | E3: 45535 | F3: Website/App | G3: Khách hàng trẻ | H3: Completed | I3: 60000000
A4: CAM003 | B4: Ngày hội thành viên | C4: Loyalty | D4: 45747 | E4: 45838 | F4: Email/App | G4: Khách mua lặp lại | H4: Completed | I4: 70000000
A5: CAM004 | B5: Ưu đãi cuối năm | C5: Promotion | D5: 45991 | E5: 46081 | F5: Đa kênh | G5: Khách tiềm năng | H5: Active | I5: 100000000

Sheet CustomerAnalytics
A1: AnalysisDate | B1: CustomerID | C1: OwnerID | D1: RecencyDays | E1: Frequency | F1: Monetary | G1: AOV | H1: AvgPurchaseCycleDays | I1: AvgReviewScore | J1: InteractionScore | K1: RScore | L1: FScore | M1: MScore | N1: PotentialScore | O1: Segment | P1: ModelStatus
A2: 46247 | B2: KH0001 | C2: =IFERROR(VLOOKUP(B2,Customers!$B$2:$L$81,11,FALSE),"") -> EMP001 | D2: =IFERROR(__xludf.DUMMYFUNCTION("IFERROR(A2-MAX(FILTER(Orders!$D$2:$D$201,Orders!$I$2:$I$201=B2,Orders!$T$2:$T$201=TRUE)),"""")"),68.35771990740614) -> 68.35772 | E2: =COUNTIFS(Orders!$I$2:$I$201,B2,Orders!$T$2:$T$201,TRUE) -> 2 | F2: =SUMIFS(Orders!$R$2:$R$201,Orders!$I$2:$I$201,B2,Orders!$T$2:$T$201,TRUE) -> 2661000 | G2: =IFERROR(F2/E2,0) -> 1330500 | H2: =IFERROR(__xludf.DUMMYFUNCTION("IF(E2<2,"""",IFERROR((MAX(FILTER(Orders!$D$2:$D$201,Orders!$I$2:$I$201=B2,Orders!$T$2:$T$201=TRUE))-MIN(FILTER(Orders!$D$2:$D$201,Orders!$I$2:$I$201=B2,Orders!$T$2:$T$201=TRUE)))/(E2-1),""""))"),561.5618518518531) -> 561.56185 | I2: =IFERROR(AVERAGEIF(Reviews!$H$2:$H$142,B3,Reviews!$C$2:$C$142),"") -> 3.75 | J2: =SUMIF(Interactions!$B$2:$B$481,B2,Interactions!$I$2:$I$481) -> 13 | K2: =IF(D2="","",MAX(1,MIN(5,6-ROUNDUP(PERCENTRANK($D$2:$D$81,D2)*4+1,0)))) -> 4 | L2: =MAX(1,MIN(5,ROUNDUP(PERCENTRANK($E$2:$E$81,E2)*4+1,0))) -> 4 | M2: =MAX(1,MIN(5,ROUNDUP(PERCENTRANK($F$2:$F$81,F2)*4+1,0))) -> 4 | N2: =IF(K2="","",ROUND((K2*35+L2*30+M2*20+(1+4*(J2-MIN($J$2:$J$81))/MAX(1,MAX($J$2:$J$81)-MIN($J$2:$J$81)))*15)/5,1)) -> 78.2 | O2: =IF(N2="","Chưa đủ dữ liệu",IF(N2>=80,"Tiềm năng cao",IF(N2>=60,"Tiềm năng","Thông thường"))) -> Tiềm năng | P2: Rule-based prototype
A3: 46247 | B3: KH0002 | C3: =IFERROR(VLOOKUP(B3,Customers!$B$2:$L$81,11,FALSE),"") -> EMP002 | D3: =IFERROR(__xludf.DUMMYFUNCTION("IFERROR(A3-MAX(FILTER(Orders!$D$2:$D$201,Orders!$I$2:$I$201=B3,Orders!$T$2:$T$201=TRUE)),"""")"),50.9545370370397) -> 50.954537 | E3: =COUNTIFS(Orders!$I$2:$I$201,B3,Orders!$T$2:$T$201,TRUE) -> 3 | F3: =SUMIFS(Orders!$R$2:$R$201,Orders!$I$2:$I$201,B3,Orders!$T$2:$T$201,TRUE) -> 4841000 | G3: =IFERROR(F3/E3,0) -> 1613666.7 | H3: =IFERROR(__xludf.DUMMYFUNCTION("IF(E3<2,"""",IFERROR((MAX(FILTER(Orders!$D$2:$D$201,Orders!$I$2:$I$201=B3,Orders!$T$2:$T$201=TRUE))-MIN(FILTER(Orders!$D$2:$D$201,Orders!$I$2:$I$201=B3,Orders!$T$2:$T$201=TRUE)))/(E3-1),""""))"),433.2268402777772) -> 433.22684 | J3: =SUMIF(Interactions!$B$2:$B$481,B3,Interactions!$I$2:$I$481) -> 10 | K3: =IF(D3="","",MAX(1,MIN(5,6-ROUNDUP(PERCENTRANK($D$2:$D$81,D3)*4+1,0)))) -> 4 | L3: =MAX(1,MIN(5,ROUNDUP(PERCENTRANK($E$2:$E$81,E3)*4+1,0))) -> 4 | M3: =MAX(1,MIN(5,ROUNDUP(PERCENTRANK($F$2:$F$81,F3)*4+1,0))) -> 5 | N3: =IF(K3="","",ROUND((K3*35+L3*30+M3*20+(1+4*(J3-MIN($J$2:$J$81))/MAX(1,MAX($J$2:$J$81)-MIN($J$2:$J$81)))*15)/5,1)) -> 75 | O3: =IF(N3="","Chưa đủ dữ liệu",IF(N3>=80,"Tiềm năng cao",IF(N3>=60,"Tiềm năng","Thông thường"))) -> Tiềm năng | P3: Rule-based prototype
A4: 46247 | B4: KH0003 | C4: =IFERROR(VLOOKUP(B4,Customers!$B$2:$L$81,11,FALSE),"") -> EMP003 | D4: =IFERROR(__xludf.DUMMYFUNCTION("IFERROR(A4-MAX(FILTER(Orders!$D$2:$D$201,Orders!$I$2:$I$201=B4,Orders!$T$2:$T$201=TRUE)),"""")"),91.89237268518627) -> 91.892373 | E4: =COUNTIFS(Orders!$I$2:$I$201,B4,Orders!$T$2:$T$201,TRUE) -> 2 | F4: =SUMIFS(Orders!$R$2:$R$201,Orders!$I$2:$I$201,B4,Orders!$T$2:$T$201,TRUE) -> 5863000 | G4: =IFERROR(F4/E4,0) -> 2931500 | H4: =IFERROR(__xludf.DUMMYFUNCTION("IF(E4<2,"""",IFERROR((MAX(FILTER(Orders!$D$2:$D$201,Orders!$I$2:$I$201=B4,Orders!$T$2:$T$201=TRUE))-MIN(FILTER(Orders!$D$2:$D$201,Orders!$I$2:$I$201=B4,Orders!$T$2:$T$201=TRUE)))/(E4-1),""""))"),631.4191203703667) -> 631.41912 | I4: =IFERROR(AVERAGEIF(Reviews!$H$2:$H$142,B4,Reviews!$C$2:$C$142),"") -> 2.6666667 | J4: =SUMIF(Interactions!$B$2:$B$481,B4,Interactions!$I$2:$I$481) -> 15 | K4: =IF(D4="","",MAX(1,MIN(5,6-ROUNDUP(PERCENTRANK($D$2:$D$81,D4)*4+1,0)))) -> 3 | L4: =MAX(1,MIN(5,ROUNDUP(PERCENTRANK($E$2:$E$81,E4)*4+1,0))) -> 4 | M4: =MAX(1,MIN(5,ROUNDUP(PERCENTRANK($F$2:$F$81,F4)*4+1,0))) -> 5 | N4: =IF(K4="","",ROUND((K4*35+L4*30+M4*20+(1+4*(J4-MIN($J$2:$J$81))/MAX(1,MAX($J$2:$J$81)-MIN($J$2:$J$81)))*15)/5,1)) -> 80 | O4: =IF(N4="","Chưa đủ dữ liệu",IF(N4>=80,"Tiềm năng cao",IF(N4>=60,"Tiềm năng","Thông thường"))) -> Tiềm năng cao | P4: Rule-based prototype
A5: 46247 | B5: KH0004 | C5: =IFERROR(VLOOKUP(B5,Customers!$B$2:$L$81,11,FALSE),"") -> EMP004 | D5: =IFERROR(__xludf.DUMMYFUNCTION("IFERROR(A5-MAX(FILTER(Orders!$D$2:$D$201,Orders!$I$2:$I$201=B5,Orders!$T$2:$T$201=TRUE)),"""")"),815.6887384259244) -> 815.68874 | E5: =COUNTIFS(Orders!$I$2:$I$201,B5,Orders!$T$2:$T$201,TRUE) -> 1 | F5: =SUMIFS(Orders!$R$2:$R$201,Orders!$I$2:$I$201,B5,Orders!$T$2:$T$201,TRUE) -> 2522000 | G5: =IFERROR(F5/E5,0) -> 2522000 | H5: =IFERROR(__xludf.DUMMYFUNCTION("IF(E5<2,"""",IFERROR((MAX(FILTER(Orders!$D$2:$D$201,Orders!$I$2:$I$201=B5,Orders!$T$2:$T$201=TRUE))-MIN(FILTER(Orders!$D$2:$D$201,Orders!$I$2:$I$201=B5,Orders!$T$2:$T$201=TRUE)))/(E5-1),""""))"),"") | I5: =IFERROR(AVERAGEIF(Reviews!$H$2:$H$142,B5,Reviews!$C$2:$C$142),"") -> 4 | J5: =SUMIF(Interactions!$B$2:$B$481,B5,Interactions!$I$2:$I$481) -> 14 | K5: =IF(D5="","",MAX(1,MIN(5,6-ROUNDUP(PERCENTRANK($D$2:$D$81,D5)*4+1,0)))) -> 1 | L5: =MAX(1,MIN(5,ROUNDUP(PERCENTRANK($E$2:$E$81,E5)*4+1,0))) -> 3 | M5: =MAX(1,MIN(5,ROUNDUP(PERCENTRANK($F$2:$F$81,F5)*4+1,0))) -> 4 | N5: =IF(K5="","",ROUND((K5*35+L5*30+M5*20+(1+4*(J5-MIN($J$2:$J$81))/MAX(1,MAX($J$2:$J$81)-MIN($J$2:$J$81)))*15)/5,1)) -> 53.6 | O5: =IF(N5="","Chưa đủ dữ liệu",IF(N5>=80,"Tiềm năng cao",IF(N5>=60,"Tiềm năng","Thông thường"))) -> Thông thường | P5: Rule-based prototype
A6: 46247 | B6: KH0005 | C6: =IFERROR(VLOOKUP(B6,Customers!$B$2:$L$81,11,FALSE),"") -> EMP005 | D6: =IFERROR(__xludf.DUMMYFUNCTION("IFERROR(A6-MAX(FILTER(Orders!$D$2:$D$201,Orders!$I$2:$I$201=B6,Orders!$T$2:$T$201=TRUE)),"""")"),361.53322916666366) -> 361.53323 | E6: =COUNTIFS(Orders!$I$2:$I$201,B6,Orders!$T$2:$T$201,TRUE) -> 1 | F6: =SUMIFS(Orders!$R$2:$R$201,Orders!$I$2:$I$201,B6,Orders!$T$2:$T$201,TRUE) -> 1192000 | G6: =IFERROR(F6/E6,0) -> 1192000 | H6: =IFERROR(__xludf.DUMMYFUNCTION("IF(E6<2,"""",IFERROR((MAX(FILTER(Orders!$D$2:$D$201,Orders!$I$2:$I$201=B6,Orders!$T$2:$T$201=TRUE))-MIN(FILTER(Orders!$D$2:$D$201,Orders!$I$2:$I$201=B6,Orders!$T$2:$T$201=TRUE)))/(E6-1),""""))"),"") | I6: =IFERROR(AVERAGEIF(Reviews!$H$2:$H$142,B6,Reviews!$C$2:$C$142),"") -> 4 | J6: =SUMIF(Interactions!$B$2:$B$481,B6,Interactions!$I$2:$I$481) -> 11 | K6: =IF(D6="","",MAX(1,MIN(5,6-ROUNDUP(PERCENTRANK($D$2:$D$81,D6)*4+1,0)))) -> 2 | L6: =MAX(1,MIN(5,ROUNDUP(PERCENTRANK($E$2:$E$81,E6)*4+1,0))) -> 3 | M6: =MAX(1,MIN(5,ROUNDUP(PERCENTRANK($F$2:$F$81,F6)*4+1,0))) -> 3 | N6: =IF(K6="","",ROUND((K6*35+L6*30+M6*20+(1+4*(J6-MIN($J$2:$J$81))/MAX(1,MAX($J$2:$J$81)-MIN($J$2:$J$81)))*15)/5,1)) -> 49.4 | O6: =IF(N6="","Chưa đủ dữ liệu",IF(N6>=80,"Tiềm năng cao",IF(N6>=60,"Tiềm năng","Thông thường"))) -> Thông thường | P6: Rule-based prototype
A7: 46247 | B7: KH0006 | C7: =IFERROR(VLOOKUP(B7,Customers!$B$2:$L$81,11,FALSE),"") -> EMP006 | D7: =IFERROR(__xludf.DUMMYFUNCTION("IFERROR(A7-MAX(FILTER(Orders!$D$2:$D$201,Orders!$I$2:$I$201=B7,Orders!$T$2:$T$201=TRUE)),"""")"),86.40400462962862) -> 86.404005 | E7: =COUNTIFS(Orders!$I$2:$I$201,B7,Orders!$T$2:$T$201,TRUE) -> 2 | F7: =SUMIFS(Orders!$R$2:$R$201,Orders!$I$2:$I$201,B7,Orders!$T$2:$T$201,TRUE) -> 1563000 | G7: =IFERROR(F7/E7,0) -> 781500 | H7: =IFERROR(__xludf.DUMMYFUNCTION("IF(E7<2,"""",IFERROR((MAX(FILTER(Orders!$D$2:$D$201,Orders!$I$2:$I$201=B7,Orders!$T$2:$T$201=TRUE))-MIN(FILTER(Orders!$D$2:$D$201,Orders!$I$2:$I$201=B7,Orders!$T$2:$T$201=TRUE)))/(E7-1),""""))"),410.41738425925723) -> 410.41738 | I7: =IFERROR(AVERAGEIF(Reviews!$H$2:$H$142,B7,Reviews!$C$2:$C$142),"") -> 2.6666667 | J7: =SUMIF(Interactions!$B$2:$B$481,B7,Interactions!$I$2:$I$481) -> 14 | K7: =IF(D7="","",MAX(1,MIN(5,6-ROUNDUP(PERCENTRANK($D$2:$D$81,D7)*4+1,0)))) -> 4 | L7: =MAX(1,MIN(5,ROUNDUP(PERCENTRANK($E$2:$E$81,E7)*4+1,0))) -> 4 | M7: =MAX(1,MIN(5,ROUNDUP(PERCENTRANK($F$2:$F$81,F7)*4+1,0))) -> 3 | N7: =IF(K7="","",ROUND((K7*35+L7*30+M7*20+(1+4*(J7-MIN($J$2:$J$81))/MAX(1,MAX($J$2:$J$81)-MIN($J$2:$J$81)))*15)/5,1)) -> 76.6 | O7: =IF(N7="","Chưa đủ dữ liệu",IF(N7>=80,"Tiềm năng cao",IF(N7>=60,"Tiềm năng","Thông thường"))) -> Tiềm năng | P7: Rule-based prototype
A8: 46247 | B8: KH0007 | C8: =IFERROR(VLOOKUP(B8,Customers!$B$2:$L$81,11,FALSE),"") -> EMP007 | D8: =IFERROR(__xludf.DUMMYFUNCTION("IFERROR(A8-MAX(FILTER(Orders!$D$2:$D$201,Orders!$I$2:$I$201=B8,Orders!$T$2:$T$201=TRUE)),"""")"),125.82817129629984) -> 125.82817 | E8: =COUNTIFS(Orders!$I$2:$I$201,B8,Orders!$T$2:$T$201,TRUE) -> 1 | F8: =SUMIFS(Orders!$R$2:$R$201,Orders!$I$2:$I$201,B8,Orders!$T$2:$T$201,TRUE) -> 1443000 | G8: =IFERROR(F8/E8,0) -> 1443000 | H8: =IFERROR(__xludf.DUMMYFUNCTION("IF(E8<2,"""",IFERROR((MAX(FILTER(Orders!$D$2:$D$201,Orders!$I$2:$I$201=B8,Orders!$T$2:$T$201=TRUE))-MIN(FILTER(Orders!$D$2:$D$201,Orders!$I$2:$I$201=B8,Orders!$T$2:$T$201=TRUE)))/(E8-1),""""))"),"") | I8: =IFERROR(AVERAGEIF(Reviews!$H$2:$H$142,B8,Reviews!$C$2:$C$142),"") -> 5 | J8: =SUMIF(Interactions!$B$2:$B$481,B8,Interactions!$I$2:$I$481) -> 12 | K8: =IF(D8="","",MAX(1,MIN(5,6-ROUNDUP(PERCENTRANK($D$2:$D$81,D8)*4+1,0)))) -> 3 | L8: =MAX(1,MIN(5,ROUNDUP(PERCENTRANK($E$2:$E$81,E8)*4+1,0))) -> 3 | M8: =MAX(1,MIN(5,ROUNDUP(PERCENTRANK($F$2:$F$81,F8)*4+1,0))) -> 3 | N8: =IF(K8="","",ROUND((K8*35+L8*30+M8*20+(1+4*(J8-MIN($J$2:$J$81))/MAX(1,MAX($J$2:$J$81)-MIN($J$2:$J$81)))*15)/5,1)) -> 58.8 | O8: =IF(N8="","Chưa đủ dữ liệu",IF(N8>=80,"Tiềm năng cao",IF(N8>=60,"Tiềm năng","Thông thường"))) -> Thông thường | P8: Rule-based prototype
A9: 46247 | B9: KH0008 | C9: =IFERROR(VLOOKUP(B9,Customers!$B$2:$L$81,11,FALSE),"") -> EMP008 | D9: =IFERROR(__xludf.DUMMYFUNCTION("IFERROR(A9-MAX(FILTER(Orders!$D$2:$D$201,Orders!$I$2:$I$201=B9,Orders!$T$2:$T$201=TRUE)),"""")"),347.6227893518517) -> 347.62279 | E9: =COUNTIFS(Orders!$I$2:$I$201,B9,Orders!$T$2:$T$201,TRUE) -> 4 | F9: =SUMIFS(Orders!$R$2:$R$201,Orders!$I$2:$I$201,B9,Orders!$T$2:$T$201,TRUE) -> 6855000 | G9: =IFERROR(F9/E9,0) -> 1713750 | H9: =IFERROR(__xludf.DUMMYFUNCTION("IF(E9<2,"""",IFERROR((MAX(FILTER(Orders!$D$2:$D$201,Orders!$I$2:$I$201=B9,Orders!$T$2:$T$201=TRUE))-MIN(FILTER(Orders!$D$2:$D$201,Orders!$I$2:$I$201=B9,Orders!$T$2:$T$201=TRUE)))/(E9-1),""""))"),143.83449459876525) -> 143.83449 | I9: =IFERROR(AVERAGEIF(Reviews!$H$2:$H$142,B9,Reviews!$C$2:$C$142),"") -> 3.75 | J9: =SUMIF(Interactions!$B$2:$B$481,B9,Interactions!$I$2:$I$481) -> 13 | K9: =IF(D9="","",MAX(1,MIN(5,6-ROUNDUP(PERCENTRANK($D$2:$D$81,D9)*4+1,0)))) -> 2 | L9: =MAX(1,MIN(5,ROUNDUP(PERCENTRANK($E$2:$E$81,E9)*4+1,0))) -> 5 | M9: =MAX(1,MIN(5,ROUNDUP(PERCENTRANK($F$2:$F$81,F9)*4+1,0))) -> 5 | N9: =IF(K9="","",ROUND((K9*35+L9*30+M9*20+(1+4*(J9-MIN($J$2:$J$81))/MAX(1,MAX($J$2:$J$81)-MIN($J$2:$J$81)))*15)/5,1)) -> 74.2 | O9: =IF(N9="","Chưa đủ dữ liệu",IF(N9>=80,"Tiềm năng cao",IF(N9>=60,"Tiềm năng","Thông thường"))) -> Tiềm năng | P9: Rule-based prototype
A10: 46247 | B10: KH0009 | C10: =IFERROR(VLOOKUP(B10,Customers!$B$2:$L$81,11,FALSE),"") -> EMP001 | D10: =IFERROR(__xludf.DUMMYFUNCTION("IFERROR(A10-MAX(FILTER(Orders!$D$2:$D$201,Orders!$I$2:$I$201=B10,Orders!$T$2:$T$201=TRUE)),"""")"),245.41439814814657) -> 245.4144 | E10: =COUNTIFS(Orders!$I$2:$I$201,B10,Orders!$T$2:$T$201,TRUE) -> 1 | F10: =SUMIFS(Orders!$R$2:$R$201,Orders!$I$2:$I$201,B10,Orders!$T$2:$T$201,TRUE) -> 3360000 | G10: =IFERROR(F10/E10,0) -> 3360000 | H10: =IFERROR(__xludf.DUMMYFUNCTION("IF(E10<2,"""",IFERROR((MAX(FILTER(Orders!$D$2:$D$201,Orders!$I$2:$I$201=B10,Orders!$T$2:$T$201=TRUE))-MIN(FILTER(Orders!$D$2:$D$201,Orders!$I$2:$I$201=B10,Orders!$T$2:$T$201=TRUE)))/(E10-1),""""))"),"") | I10: =IFERROR(AVERAGEIF(Reviews!$H$2:$H$142,B10,Reviews!$C$2:$C$142),"") -> 3 | J10: =SUMIF(Interactions!$B$2:$B$481,B10,Interactions!$I$2:$I$481) -> 13 | K10: =IF(D10="","",MAX(1,MIN(5,6-ROUNDUP(PERCENTRANK($D$2:$D$81,D10)*4+1,0)))) -> 3 | L10: =MAX(1,MIN(5,ROUNDUP(PERCENTRANK($E$2:$E$81,E10)*4+1,0))) -> 3 | M10: =MAX(1,MIN(5,ROUNDUP(PERCENTRANK($F$2:$F$81,F10)*4+1,0))) -> 4 | N10: =IF(K10="","",ROUND((K10*35+L10*30+M10*20+(1+4*(J10-MIN($J$2:$J$81))/MAX(1,MAX($J$2:$J$81)-MIN($J$2:$J$81)))*15)/5,1)) -> 65.2 | O10: =IF(N10="","Chưa đủ dữ liệu",IF(N10>=80,"Tiềm năng cao",IF(N10>=60,"Tiềm năng","Thông thường"))) -> Tiềm năng | P10: Rule-based prototype
A11: 46247 | B11: KH0010 | C11: =IFERROR(VLOOKUP(B11,Customers!$B$2:$L$81,11,FALSE),"") -> EMP002 | D11: =IFERROR(__xludf.DUMMYFUNCTION("IFERROR(A11-MAX(FILTER(Orders!$D$2:$D$201,Orders!$I$2:$I$201=B11,Orders!$T$2:$T$201=TRUE)),"""")"),523.729895833334) -> 523.7299 | E11: =COUNTIFS(Orders!$I$2:$I$201,B11,Orders!$T$2:$T$201,TRUE) -> 2 | F11: =SUMIFS(Orders!$R$2:$R$201,Orders!$I$2:$I$201,B11,Orders!$T$2:$T$201,TRUE) -> 1741000 | G11: =IFERROR(F11/E11,0) -> 870500 | H11: =IFERROR(__xludf.DUMMYFUNCTION("IF(E11<2,"""",IFERROR((MAX(FILTER(Orders!$D$2:$D$201,Orders!$I$2:$I$201=B11,Orders!$T$2:$T$201=TRUE))-MIN(FILTER(Orders!$D$2:$D$201,Orders!$I$2:$I$201=B11,Orders!$T$2:$T$201=TRUE)))/(E11-1),""""))"),333.3799884259279) -> 333.37999 | I11: =IFERROR(AVERAGEIF(Reviews!$H$2:$H$142,B11,Reviews!$C$2:$C$142),"") -> 4.5 | J11: =SUMIF(Interactions!$B$2:$B$481,B11,Interactions!$I$2:$I$481) -> 10 | K11: =IF(D11="","",MAX(1,MIN(5,6-ROUNDUP(PERCENTRANK($D$2:$D$81,D11)*4+1,0)))) -> 1 | L11: =MAX(1,MIN(5,ROUNDUP(PERCENTRANK($E$2:$E$81,E11)*4+1,0))) -> 4 | M11: =MAX(1,MIN(5,ROUNDUP(PERCENTRANK($F$2:$F$81,F11)*4+1,0))) -> 3 | N11: =IF(K11="","",ROUND((K11*35+L11*30+M11*20+(1+4*(J11-MIN($J$2:$J$81))/MAX(1,MAX($J$2:$J$81)-MIN($J$2:$J$81)))*15)/5,1)) -> 46 | O11: =IF(N11="","Chưa đủ dữ liệu",IF(N11>=80,"Tiềm năng cao",IF(N11>=60,"Tiềm năng","Thông thường"))) -> Thông thường | P11: Rule-based prototype
A12: 46247 | B12: KH0011 | C12: =IFERROR(VLOOKUP(B12,Customers!$B$2:$L$81,11,FALSE),"") -> EMP003 | D12: =IFERROR(__xludf.DUMMYFUNCTION("IFERROR(A12-MAX(FILTER(Orders!$D$2:$D$201,Orders!$I$2:$I$201=B12,Orders!$T$2:$T$201=TRUE)),"""")"),"") | E12: =COUNTIFS(Orders!$I$2:$I$201,B12,Orders!$T$2:$T$201,TRUE) -> 0 | F12: =SUMIFS(Orders!$R$2:$R$201,Orders!$I$2:$I$201,B12,Orders!$T$2:$T$201,TRUE) -> 0 | G12: =IFERROR(F12/E12,0) -> 0 | H12: =IFERROR(__xludf.DUMMYFUNCTION("IF(E12<2,"""",IFERROR((MAX(FILTER(Orders!$D$2:$D$201,Orders!$I$2:$I$201=B12,Orders!$T$2:$T$201=TRUE))-MIN(FILTER(Orders!$D$2:$D$201,Orders!$I$2:$I$201=B12,Orders!$T$2:$T$201=TRUE)))/(E12-1),""""))"),"") | I12: =IFERROR(AVERAGEIF(Reviews!$H$2:$H$142,B12,Reviews!$C$2:$C$142),"") | J12: =SUMIF(Interactions!$B$2:$B$481,B12,Interactions!$I$2:$I$481) -> 15 | K12: =IF(D12="","",MAX(1,MIN(5,6-ROUNDUP(PERCENTRANK($D$2:$D$81,D12)*4+1,0)))) | L12: =MAX(1,MIN(5,ROUNDUP(PERCENTRANK($E$2:$E$81,E12)*4+1,0))) -> 1 | M12: =MAX(1,MIN(5,ROUNDUP(PERCENTRANK($F$2:$F$81,F12)*4+1,0))) -> 1 | N12: =IF(K12="","",ROUND((K12*35+L12*30+M12*20+(1+4*(J12-MIN($J$2:$J$81))/MAX(1,MAX($J$2:$J$81)-MIN($J$2:$J$81)))*15)/5,1)) | O12: =IF(N12="","Chưa đủ dữ liệu",IF(N12>=80,"Tiềm năng cao",IF(N12>=60,"Tiềm năng","Thông thường"))) -> Chưa đủ dữ liệu | P12: Rule-based prototype
A13: 46247 | B13: KH0012 | C13: =IFERROR(VLOOKUP(B13,Customers!$B$2:$L$81,11,FALSE),"") -> EMP004 | D13: =IFERROR(__xludf.DUMMYFUNCTION("IFERROR(A13-MAX(FILTER(Orders!$D$2:$D$201,Orders!$I$2:$I$201=B13,Orders!$T$2:$T$201=TRUE)),"""")"),265.56388888888614) -> 265.56389 | E13: =COUNTIFS(Orders!$I$2:$I$201,B13,Orders!$T$2:$T$201,TRUE) -> 2 | F13: =SUMIFS(Orders!$R$2:$R$201,Orders!$I$2:$I$201,B13,Orders!$T$2:$T$201,TRUE) -> 4279000 | G13: =IFERROR(F13/E13,0) -> 2139500 | H13: =IFERROR(__xludf.DUMMYFUNCTION("IF(E13<2,"""",IFERROR((MAX(FILTER(Orders!$D$2:$D$201,Orders!$I$2:$I$201=B13,Orders!$T$2:$T$201=TRUE))-MIN(FILTER(Orders!$D$2:$D$201,Orders!$I$2:$I$201=B13,Orders!$T$2:$T$201=TRUE)))/(E13-1),""""))"),114.53442129629548) -> 114.53442 | I13: =IFERROR(AVERAGEIF(Reviews!$H$2:$H$142,B13,Reviews!$C$2:$C$142),"") -> 4 | J13: =SUMIF(Interactions!$B$2:$B$481,B13,Interactions!$I$2:$I$481) -> 14 | K13: =IF(D13="","",MAX(1,MIN(5,6-ROUNDUP(PERCENTRANK($D$2:$D$81,D13)*4+1,0)))) -> 2 | L13: =MAX(1,MIN(5,ROUNDUP(PERCENTRANK($E$2:$E$81,E13)*4+1,0))) -> 4 | M13: =MAX(1,MIN(5,ROUNDUP(PERCENTRANK($F$2:$F$81,F13)*4+1,0))) -> 4 | N13: =IF(K13="","",ROUND((K13*35+L13*30+M13*20+(1+4*(J13-MIN($J$2:$J$81))/MAX(1,MAX($J$2:$J$81)-MIN($J$2:$J$81)))*15)/5,1)) -> 66.6 | O13: =IF(N13="","Chưa đủ dữ liệu",IF(N13>=80,"Tiềm năng cao",IF(N13>=60,"Tiềm năng","Thông thường"))) -> Tiềm năng | P13: Rule-based prototype
A14: 46247 | B14: KH0013 | C14: =IFERROR(VLOOKUP(B14,Customers!$B$2:$L$81,11,FALSE),"") -> EMP005 | D14: =IFERROR(__xludf.DUMMYFUNCTION("IFERROR(A14-MAX(FILTER(Orders!$D$2:$D$201,Orders!$I$2:$I$201=B14,Orders!$T$2:$T$201=TRUE)),"""")"),98.88432870370161) -> 98.884329 | E14: =COUNTIFS(Orders!$I$2:$I$201,B14,Orders!$T$2:$T$201,TRUE) -> 4 | F14: =SUMIFS(Orders!$R$2:$R$201,Orders!$I$2:$I$201,B14,Orders!$T$2:$T$201,TRUE) -> 8444000 | G14: =IFERROR(F14/E14,0) -> 2111000 | H14: =IFERROR(__xludf.DUMMYFUNCTION("IF(E14<2,"""",IFERROR((MAX(FILTER(Orders!$D$2:$D$201,Orders!$I$2:$I$201=B14,Orders!$T$2:$T$201=TRUE))-MIN(FILTER(Orders!$D$2:$D$201,Orders!$I$2:$I$201=B14,Orders!$T$2:$T$201=TRUE)))/(E14-1),""""))"),228.60295524691415) -> 228.60296 | I14: =IFERROR(AVERAGEIF(Reviews!$H$2:$H$142,B14,Reviews!$C$2:$C$142),"") -> 4.3333333 | J14: =SUMIF(Interactions!$B$2:$B$481,B14,Interactions!$I$2:$I$481) -> 11 | K14: =IF(D14="","",MAX(1,MIN(5,6-ROUNDUP(PERCENTRANK($D$2:$D$81,D14)*4+1,0)))) -> 3 | L14: =MAX(1,MIN(5,ROUNDUP(PERCENTRANK($E$2:$E$81,E14)*4+1,0))) -> 5 | M14: =MAX(1,MIN(5,ROUNDUP(PERCENTRANK($F$2:$F$81,F14)*4+1,0))) -> 5 | N14: =IF(K14="","",ROUND((K14*35+L14*30+M14*20+(1+4*(J14-MIN($J$2:$J$81))/MAX(1,MAX($J$2:$J$81)-MIN($J$2:$J$81)))*15)/5,1)) -> 76.4 | O14: =IF(N14="","Chưa đủ dữ liệu",IF(N14>=80,"Tiềm năng cao",IF(N14>=60,"Tiềm năng","Thông thường"))) -> Tiềm năng | P14: Rule-based prototype
A15: 46247 | B15: KH0014 | C15: =IFERROR(VLOOKUP(B15,Customers!$B$2:$L$81,11,FALSE),"") -> EMP006 | D15: =IFERROR(__xludf.DUMMYFUNCTION("IFERROR(A15-MAX(FILTER(Orders!$D$2:$D$201,Orders!$I$2:$I$201=B15,Orders!$T$2:$T$201=TRUE)),"""")"),185.62101851851912) -> 185.62102 | E15: =COUNTIFS(Orders!$I$2:$I$201,B15,Orders!$T$2:$T$201,TRUE) -> 4 | F15: =SUMIFS(Orders!$R$2:$R$201,Orders!$I$2:$I$201,B15,Orders!$T$2:$T$201,TRUE) -> 6325000 | G15: =IFERROR(F15/E15,0) -> 1581250 | H15: =IFERROR(__xludf.DUMMYFUNCTION("IF(E15<2,"""",IFERROR((MAX(FILTER(Orders!$D$2:$D$201,Orders!$I$2:$I$201=B15,Orders!$T$2:$T$201=TRUE))-MIN(FILTER(Orders!$D$2:$D$201,Orders!$I$2:$I$201=B15,Orders!$T$2:$T$201=TRUE)))/(E15-1),""""))"),237.93795910493887) -> 237.93796 | I15: =IFERROR(AVERAGEIF(Reviews!$H$2:$H$142,B15,Reviews!$C$2:$C$142),"") -> 3.6666667 | J15: =SUMIF(Interactions!$B$2:$B$481,B15,Interactions!$I$2:$I$481) -> 14 | K15: =IF(D15="","",MAX(1,MIN(5,6-ROUNDUP(PERCENTRANK($D$2:$D$81,D15)*4+1,0)))) -> 3 | L15: =MAX(1,MIN(5,ROUNDUP(PERCENTRANK($E$2:$E$81,E15)*4+1,0))) -> 5 | M15: =MAX(1,MIN(5,ROUNDUP(PERCENTRANK($F$2:$F$81,F15)*4+1,0))) -> 5 | N15: =IF(K15="","",ROUND((K15*35+L15*30+M15*20+(1+4*(J15-MIN($J$2:$J$81))/MAX(1,MAX($J$2:$J$81)-MIN($J$2:$J$81)))*15)/5,1)) -> 83.6 | O15: =IF(N15="","Chưa đủ dữ liệu",IF(N15>=80,"Tiềm năng cao",IF(N15>=60,"Tiềm năng","Thông thường"))) -> Tiềm năng cao | P15: Rule-based prototype
A16: 46247 | B16: KH0015 | C16: =IFERROR(VLOOKUP(B16,Customers!$B$2:$L$81,11,FALSE),"") -> EMP007 | D16: =IFERROR(__xludf.DUMMYFUNCTION("IFERROR(A16-MAX(FILTER(Orders!$D$2:$D$201,Orders!$I$2:$I$201=B16,Orders!$T$2:$T$201=TRUE)),"""")"),740.6040972222254) -> 740.6041 | E16: =COUNTIFS(Orders!$I$2:$I$201,B16,Orders!$T$2:$T$201,TRUE) -> 2 | F16: =SUMIFS(Orders!$R$2:$R$201,Orders!$I$2:$I$201,B16,Orders!$T$2:$T$201,TRUE) -> 2569000 | G16: =IFERROR(F16/E16,0) -> 1284500 | H16: =IFERROR(__xludf.DUMMYFUNCTION("IF(E16<2,"""",IFERROR((MAX(FILTER(Orders!$D$2:$D$201,Orders!$I$2:$I$201=B16,Orders!$T$2:$T$201=TRUE))-MIN(FILTER(Orders!$D$2:$D$201,Orders!$I$2:$I$201=B16,Orders!$T$2:$T$201=TRUE)))/(E16-1),""""))"),164.10009259259095) -> 164.10009 | I16: =IFERROR(AVERAGEIF(Reviews!$H$2:$H$142,B16,Reviews!$C$2:$C$142),"") -> 4 | J16: =SUMIF(Interactions!$B$2:$B$481,B16,Interactions!$I$2:$I$481) -> 12 | K16: =IF(D16="","",MAX(1,MIN(5,6-ROUNDUP(PERCENTRANK($D$2:$D$81,D16)*4+1,0)))) -> 1 | L16: =MAX(1,MIN(5,ROUNDUP(PERCENTRANK($E$2:$E$81,E16)*4+1,0))) -> 4 | M16: =MAX(1,MIN(5,ROUNDUP(PERCENTRANK($F$2:$F$81,F16)*4+1,0))) -> 4 | N16: =IF(K16="","",ROUND((K16*35+L16*30+M16*20+(1+4*(J16-MIN($J$2:$J$81))/MAX(1,MAX($J$2:$J$81)-MIN($J$2:$J$81)))*15)/5,1)) -> 54.8 | O16: =IF(N16="","Chưa đủ dữ liệu",IF(N16>=80,"Tiềm năng cao",IF(N16>=60,"Tiềm năng","Thông thường"))) -> Thông thường | P16: Rule-based prototype
A17: 46247 | B17: KH0016 | C17: =IFERROR(VLOOKUP(B17,Customers!$B$2:$L$81,11,FALSE),"") -> EMP008 | D17: =IFERROR(__xludf.DUMMYFUNCTION("IFERROR(A17-MAX(FILTER(Orders!$D$2:$D$201,Orders!$I$2:$I$201=B17,Orders!$T$2:$T$201=TRUE)),"""")"),74.73663194444089) -> 74.736632 | E17: =COUNTIFS(Orders!$I$2:$I$201,B17,Orders!$T$2:$T$201,TRUE) -> 4 | F17: =SUMIFS(Orders!$R$2:$R$201,Orders!$I$2:$I$201,B17,Orders!$T$2:$T$201,TRUE) -> 7869000 | G17: =IFERROR(F17/E17,0) -> 1967250 | H17: =IFERROR(__xludf.DUMMYFUNCTION("IF(E17<2,"""",IFERROR((MAX(FILTER(Orders!$D$2:$D$201,Orders!$I$2:$I$201=B17,Orders!$T$2:$T$201=TRUE))-MIN(FILTER(Orders!$D$2:$D$201,Orders!$I$2:$I$201=B17,Orders!$T$2:$T$201=TRUE)))/(E17-1),""""))"),290.496763117284) -> 290.49676 | I17: =IFERROR(AVERAGEIF(Reviews!$H$2:$H$142,B17,Reviews!$C$2:$C$142),"") -> 4.2 | J17: =SUMIF(Interactions!$B$2:$B$481,B17,Interactions!$I$2:$I$481) -> 13 | K17: =IF(D17="","",MAX(1,MIN(5,6-ROUNDUP(PERCENTRANK($D$2:$D$81,D17)*4+1,0)))) -> 4 | L17: =MAX(1,MIN(5,ROUNDUP(PERCENTRANK($E$2:$E$81,E17)*4+1,0))) -> 5 | M17: =MAX(1,MIN(5,ROUNDUP(PERCENTRANK($F$2:$F$81,F17)*4+1,0))) -> 5 | N17: =IF(K17="","",ROUND((K17*35+L17*30+M17*20+(1+4*(J17-MIN($J$2:$J$81))/MAX(1,MAX($J$2:$J$81)-MIN($J$2:$J$81)))*15)/5,1)) -> 88.2 | O17: =IF(N17="","Chưa đủ dữ liệu",IF(N17>=80,"Tiềm năng cao",IF(N17>=60,"Tiềm năng","Thông thường"))) -> Tiềm năng cao | P17: Rule-based prototype
A18: 46247 | B18: KH0017 | C18: =IFERROR(VLOOKUP(B18,Customers!$B$2:$L$81,11,FALSE),"") -> EMP001 | D18: =IFERROR(__xludf.DUMMYFUNCTION("IFERROR(A18-MAX(FILTER(Orders!$D$2:$D$201,Orders!$I$2:$I$201=B18,Orders!$T$2:$T$201=TRUE)),"""")"),462.4115393518514) -> 462.41154 | E18: =COUNTIFS(Orders!$I$2:$I$201,B18,Orders!$T$2:$T$201,TRUE) -> 2 | F18: =SUMIFS(Orders!$R$2:$R$201,Orders!$I$2:$I$201,B18,Orders!$T$2:$T$201,TRUE) -> 3544000 | G18: =IFERROR(F18/E18,0) -> 1772000 | H18: =IFERROR(__xludf.DUMMYFUNCTION("IF(E18<2,"""",IFERROR((MAX(FILTER(Orders!$D$2:$D$201,Orders!$I$2:$I$201=B18,Orders!$T$2:$T$201=TRUE))-MIN(FILTER(Orders!$D$2:$D$201,Orders!$I$2:$I$201=B18,Orders!$T$2:$T$201=TRUE)))/(E18-1),""""))"),376.0384259259299) -> 376.03843 | I18: =IFERROR(AVERAGEIF(Reviews!$H$2:$H$142,B18,Reviews!$C$2:$C$142),"") -> 3.5 | J18: =SUMIF(Interactions!$B$2:$B$481,B18,Interactions!$I$2:$I$481) -> 13 | K18: =IF(D18="","",MAX(1,MIN(5,6-ROUNDUP(PERCENTRANK($D$2:$D$81,D18)*4+1,0)))) -> 1 | L18: =MAX(1,MIN(5,ROUNDUP(PERCENTRANK($E$2:$E$81,E18)*4+1,0))) -> 4 | M18: =MAX(1,MIN(5,ROUNDUP(PERCENTRANK($F$2:$F$81,F18)*4+1,0))) -> 4 | N18: =IF(K18="","",ROUND((K18*35+L18*30+M18*20+(1+4*(J18-MIN($J$2:$J$81))/MAX(1,MAX($J$2:$J$81)-MIN($J$2:$J$81)))*15)/5,1)) -> 57.2 | O18: =IF(N18="","Chưa đủ dữ liệu",IF(N18>=80,"Tiềm năng cao",IF(N18>=60,"Tiềm năng","Thông thường"))) -> Thông thường | P18: Rule-based prototype
A19: 46247 | B19: KH0018 | C19: =IFERROR(VLOOKUP(B19,Customers!$B$2:$L$81,11,FALSE),"") -> EMP002 | D19: =IFERROR(__xludf.DUMMYFUNCTION("IFERROR(A19-MAX(FILTER(Orders!$D$2:$D$201,Orders!$I$2:$I$201=B19,Orders!$T$2:$T$201=TRUE)),"""")"),309.24509259259503) -> 309.24509 | E19: =COUNTIFS(Orders!$I$2:$I$201,B19,Orders!$T$2:$T$201,TRUE) -> 2 | F19: =SUMIFS(Orders!$R$2:$R$201,Orders!$I$2:$I$201,B19,Orders!$T$2:$T$201,TRUE) -> 3366000 | G19: =IFERROR(F19/E19,0) -> 1683000 | H19: =IFERROR(__xludf.DUMMYFUNCTION("IF(E19<2,"""",IFERROR((MAX(FILTER(Orders!$D$2:$D$201,Orders!$I$2:$I$201=B19,Orders!$T$2:$T$201=TRUE))-MIN(FILTER(Orders!$D$2:$D$201,Orders!$I$2:$I$201=B19,Orders!$T$2:$T$201=TRUE)))/(E19-1),""""))"),402.778090277774) -> 402.77809 | I19: =IFERROR(AVERAGEIF(Reviews!$H$2:$H$142,B19,Reviews!$C$2:$C$142),"") -> 5 | J19: =SUMIF(Interactions!$B$2:$B$481,B19,Interactions!$I$2:$I$481) -> 10 | K19: =IF(D19="","",MAX(1,MIN(5,6-ROUNDUP(PERCENTRANK($D$2:$D$81,D19)*4+1,0)))) -> 2 | L19: =MAX(1,MIN(5,ROUNDUP(PERCENTRANK($E$2:$E$81,E19)*4+1,0))) -> 4 | M19: =MAX(1,MIN(5,ROUNDUP(PERCENTRANK($F$2:$F$81,F19)*4+1,0))) -> 4 | N19: =IF(K19="","",ROUND((K19*35+L19*30+M19*20+(1+4*(J19-MIN($J$2:$J$81))/MAX(1,MAX($J$2:$J$81)-MIN($J$2:$J$81)))*15)/5,1)) -> 57 | O19: =IF(N19="","Chưa đủ dữ liệu",IF(N19>=80,"Tiềm năng cao",IF(N19>=60,"Tiềm năng","Thông thường"))) -> Thông thường | P19: Rule-based prototype
A20: 46247 | B20: KH0019 | C20: =IFERROR(VLOOKUP(B20,Customers!$B$2:$L$81,11,FALSE),"") -> EMP003 | D20: =IFERROR(__xludf.DUMMYFUNCTION("IFERROR(A20-MAX(FILTER(Orders!$D$2:$D$201,Orders!$I$2:$I$201=B20,Orders!$T$2:$T$201=TRUE)),"""")"),656.4100347222193) -> 656.41003 | E20: =COUNTIFS(Orders!$I$2:$I$201,B20,Orders!$T$2:$T$201,TRUE) -> 1 | F20: =SUMIFS(Orders!$R$2:$R$201,Orders!$I$2:$I$201,B20,Orders!$T$2:$T$201,TRUE) -> 2308000 | G20: =IFERROR(F20/E20,0) -> 2308000 | H20: =IFERROR(__xludf.DUMMYFUNCTION("IF(E20<2,"""",IFERROR((MAX(FILTER(Orders!$D$2:$D$201,Orders!$I$2:$I$201=B20,Orders!$T$2:$T$201=TRUE))-MIN(FILTER(Orders!$D$2:$D$201,Orders!$I$2:$I$201=B20,Orders!$T$2:$T$201=TRUE)))/(E20-1),""""))"),"") | I20: =IFERROR(AVERAGEIF(Reviews!$H$2:$H$142,B20,Reviews!$C$2:$C$142),"") -> 3 | J20: =SUMIF(Interactions!$B$2:$B$481,B20,Interactions!$I$2:$I$481) -> 15 | K20: =IF(D20="","",MAX(1,MIN(5,6-ROUNDUP(PERCENTRANK($D$2:$D$81,D20)*4+1,0)))) -> 1 | L20: =MAX(1,MIN(5,ROUNDUP(PERCENTRANK($E$2:$E$81,E20)*4+1,0))) -> 3 | M20: =MAX(1,MIN(5,ROUNDUP(PERCENTRANK($F$2:$F$81,F20)*4+1,0))) -> 3 | N20: =IF(K20="","",ROUND((K20*35+L20*30+M20*20+(1+4*(J20-MIN($J$2:$J$81))/MAX(1,MAX($J$2:$J$81)-MIN($J$2:$J$81)))*15)/5,1)) -> 52 | O20: =IF(N20="","Chưa đủ dữ liệu",IF(N20>=80,"Tiềm năng cao",IF(N20>=60,"Tiềm năng","Thông thường"))) -> Thông thường | P20: Rule-based prototype
A21: 46247 | B21: KH0020 | C21: =IFERROR(VLOOKUP(B21,Customers!$B$2:$L$81,11,FALSE),"") -> EMP004 | D21: =IFERROR(__xludf.DUMMYFUNCTION("IFERROR(A21-MAX(FILTER(Orders!$D$2:$D$201,Orders!$I$2:$I$201=B21,Orders!$T$2:$T$201=TRUE)),"""")"),33.32013888889196) -> 33.320139 | E21: =COUNTIFS(Orders!$I$2:$I$201,B21,Orders!$T$2:$T$201,TRUE) -> 2 | F21: =SUMIFS(Orders!$R$2:$R$201,Orders!$I$2:$I$201,B21,Orders!$T$2:$T$201,TRUE) -> 3724000 | G21: =IFERROR(F21/E21,0) -> 1862000 | H21: =IFERROR(__xludf.DUMMYFUNCTION("IF(E21<2,"""",IFERROR((MAX(FILTER(Orders!$D$2:$D$201,Orders!$I$2:$I$201=B21,Orders!$T$2:$T$201=TRUE))-MIN(FILTER(Orders!$D$2:$D$201,Orders!$I$2:$I$201=B21,Orders!$T$2:$T$201=TRUE)))/(E21-1),""""))"),690.8458912037022) -> 690.84589 | I21: =IFERROR(AVERAGEIF(Reviews!$H$2:$H$142,B21,Reviews!$C$2:$C$142),"") -> 4.5 | J21: =SUMIF(Interactions!$B$2:$B$481,B21,Interactions!$I$2:$I$481) -> 14 | K21: =IF(D21="","",MAX(1,MIN(5,6-ROUNDUP(PERCENTRANK($D$2:$D$81,D21)*4+1,0)))) -> 4 | L21: =MAX(1,MIN(5,ROUNDUP(PERCENTRANK($E$2:$E$81,E21)*4+1,0))) -> 4 | M21: =MAX(1,MIN(5,ROUNDUP(PERCENTRANK($F$2:$F$81,F21)*4+1,0))) -> 4 | N21: =IF(K21="","",ROUND((K21*35+L21*30+M21*20+(1+4*(J21-MIN($J$2:$J$81))/MAX(1,MAX($J$2:$J$81)-MIN($J$2:$J$81)))*15)/5,1)) -> 80.6 | O21: =IF(N21="","Chưa đủ dữ liệu",IF(N21>=80,"Tiềm năng cao",IF(N21>=60,"Tiềm năng","Thông thường"))) -> Tiềm năng cao | P21: Rule-based prototype
A22: 46247 | B22: KH0021 | C22: =IFERROR(VLOOKUP(B22,Customers!$B$2:$L$81,11,FALSE),"") -> EMP005 | D22: =IFERROR(__xludf.DUMMYFUNCTION("IFERROR(A22-MAX(FILTER(Orders!$D$2:$D$201,Orders!$I$2:$I$201=B22,Orders!$T$2:$T$201=TRUE)),"""")"),400.8153125000026) -> 400.81531 | E22: =COUNTIFS(Orders!$I$2:$I$201,B22,Orders!$T$2:$T$201,TRUE) -> 1 | F22: =SUMIFS(Orders!$R$2:$R$201,Orders!$I$2:$I$201,B22,Orders!$T$2:$T$201,TRUE) -> 3200000 | G22: =IFERROR(F22/E22,0) -> 3200000 | H22: =IFERROR(__xludf.DUMMYFUNCTION("IF(E22<2,"""",IFERROR((MAX(FILTER(Orders!$D$2:$D$201,Orders!$I$2:$I$201=B22,Orders!$T$2:$T$201=TRUE))-MIN(FILTER(Orders!$D$2:$D$201,Orders!$I$2:$I$201=B22,Orders!$T$2:$T$201=TRUE)))/(E22-1),""""))"),"") | I22: =IFERROR(AVERAGEIF(Reviews!$H$2:$H$142,B22,Reviews!$C$2:$C$142),"") | J22: =SUMIF(Interactions!$B$2:$B$481,B22,Interactions!$I$2:$I$481) -> 11 | K22: =IF(D22="","",MAX(1,MIN(5,6-ROUNDUP(PERCENTRANK($D$2:$D$81,D22)*4+1,0)))) -> 1 | L22: =MAX(1,MIN(5,ROUNDUP(PERCENTRANK($E$2:$E$81,E22)*4+1,0))) -> 3 | M22: =MAX(1,MIN(5,ROUNDUP(PERCENTRANK($F$2:$F$81,F22)*4+1,0))) -> 4 | N22: =IF(K22="","",ROUND((K22*35+L22*30+M22*20+(1+4*(J22-MIN($J$2:$J$81))/MAX(1,MAX($J$2:$J$81)-MIN($J$2:$J$81)))*15)/5,1)) -> 46.4 | O22: =IF(N22="","Chưa đủ dữ liệu",IF(N22>=80,"Tiềm năng cao",IF(N22>=60,"Tiềm năng","Thông thường"))) -> Thông thường | P22: Rule-based prototype
A23: 46247 | B23: KH0022 | C23: =IFERROR(VLOOKUP(B23,Customers!$B$2:$L$81,11,FALSE),"") -> EMP006 | D23: =IFERROR(__xludf.DUMMYFUNCTION("IFERROR(A23-MAX(FILTER(Orders!$D$2:$D$201,Orders!$I$2:$I$201=B23,Orders!$T$2:$T$201=TRUE)),"""")"),386.75449074074277) -> 386.75449 | E23: =COUNTIFS(Orders!$I$2:$I$201,B23,Orders!$T$2:$T$201,TRUE) -> 4 | F23: =SUMIFS(Orders!$R$2:$R$201,Orders!$I$2:$I$201,B23,Orders!$T$2:$T$201,TRUE) -> 3879000 | G23: =IFERROR(F23/E23,0) -> 969750 | H23: =IFERROR(__xludf.DUMMYFUNCTION("IF(E23<2,"""",IFERROR((MAX(FILTER(Orders!$D$2:$D$201,Orders!$I$2:$I$201=B23,Orders!$T$2:$T$201=TRUE))-MIN(FILTER(Orders!$D$2:$D$201,Orders!$I$2:$I$201=B23,Orders!$T$2:$T$201=TRUE)))/(E23-1),""""))"),181.55102623456818) -> 181.55103 | I23: =IFERROR(AVERAGEIF(Reviews!$H$2:$H$142,B23,Reviews!$C$2:$C$142),"") -> 4.25 | J23: =SUMIF(Interactions!$B$2:$B$481,B23,Interactions!$I$2:$I$481) -> 14 | K23: =IF(D23="","",MAX(1,MIN(5,6-ROUNDUP(PERCENTRANK($D$2:$D$81,D23)*4+1,0)))) -> 2 | L23: =MAX(1,MIN(5,ROUNDUP(PERCENTRANK($E$2:$E$81,E23)*4+1,0))) -> 5 | M23: =MAX(1,MIN(5,ROUNDUP(PERCENTRANK($F$2:$F$81,F23)*4+1,0))) -> 4 | N23: =IF(K23="","",ROUND((K23*35+L23*30+M23*20+(1+4*(J23-MIN($J$2:$J$81))/MAX(1,MAX($J$2:$J$81)-MIN($J$2:$J$81)))*15)/5,1)) -> 72.6 | O23: =IF(N23="","Chưa đủ dữ liệu",IF(N23>=80,"Tiềm năng cao",IF(N23>=60,"Tiềm năng","Thông thường"))) -> Tiềm năng | P23: Rule-based prototype
A24: 46247 | B24: KH0023 | C24: =IFERROR(VLOOKUP(B24,Customers!$B$2:$L$81,11,FALSE),"") -> EMP007 | D24: =IFERROR(__xludf.DUMMYFUNCTION("IFERROR(A24-MAX(FILTER(Orders!$D$2:$D$201,Orders!$I$2:$I$201=B24,Orders!$T$2:$T$201=TRUE)),"""")"),105.95427083333198) -> 105.95427 | E24: =COUNTIFS(Orders!$I$2:$I$201,B24,Orders!$T$2:$T$201,TRUE) -> 4 | F24: =SUMIFS(Orders!$R$2:$R$201,Orders!$I$2:$I$201,B24,Orders!$T$2:$T$201,TRUE) -> 8324000 | G24: =IFERROR(F24/E24,0) -> 2081000 | H24: =IFERROR(__xludf.DUMMYFUNCTION("IF(E24<2,"""",IFERROR((MAX(FILTER(Orders!$D$2:$D$201,Orders!$I$2:$I$201=B24,Orders!$T$2:$T$201=TRUE))-MIN(FILTER(Orders!$D$2:$D$201,Orders!$I$2:$I$201=B24,Orders!$T$2:$T$201=TRUE)))/(E24-1),""""))"),251.15832175926093) -> 251.15832 | I24: =IFERROR(AVERAGEIF(Reviews!$H$2:$H$142,B24,Reviews!$C$2:$C$142),"") -> 3.25 | J24: =SUMIF(Interactions!$B$2:$B$481,B24,Interactions!$I$2:$I$481) -> 12 | K24: =IF(D24="","",MAX(1,MIN(5,6-ROUNDUP(PERCENTRANK($D$2:$D$81,D24)*4+1,0)))) -> 3 | L24: =MAX(1,MIN(5,ROUNDUP(PERCENTRANK($E$2:$E$81,E24)*4+1,0))) -> 5 | M24: =MAX(1,MIN(5,ROUNDUP(PERCENTRANK($F$2:$F$81,F24)*4+1,0))) -> 5 | N24: =IF(K24="","",ROUND((K24*35+L24*30+M24*20+(1+4*(J24-MIN($J$2:$J$81))/MAX(1,MAX($J$2:$J$81)-MIN($J$2:$J$81)))*15)/5,1)) -> 78.8 | O24: =IF(N24="","Chưa đủ dữ liệu",IF(N24>=80,"Tiềm năng cao",IF(N24>=60,"Tiềm năng","Thông thường"))) -> Tiềm năng | P24: Rule-based prototype
A25: 46247 | B25: KH0024 | C25: =IFERROR(VLOOKUP(B25,Customers!$B$2:$L$81,11,FALSE),"") -> EMP008 | D25: =IFERROR(__xludf.DUMMYFUNCTION("IFERROR(A25-MAX(FILTER(Orders!$D$2:$D$201,Orders!$I$2:$I$201=B25,Orders!$T$2:$T$201=TRUE)),"""")"),757.2750000000015) -> 757.275 | E25: =COUNTIFS(Orders!$I$2:$I$201,B25,Orders!$T$2:$T$201,TRUE) -> 1 | F25: =SUMIFS(Orders!$R$2:$R$201,Orders!$I$2:$I$201,B25,Orders!$T$2:$T$201,TRUE) -> 1243000 | G25: =IFERROR(F25/E25,0) -> 1243000 | H25: =IFERROR(__xludf.DUMMYFUNCTION("IF(E25<2,"""",IFERROR((MAX(FILTER(Orders!$D$2:$D$201,Orders!$I$2:$I$201=B25,Orders!$T$2:$T$201=TRUE))-MIN(FILTER(Orders!$D$2:$D$201,Orders!$I$2:$I$201=B25,Orders!$T$2:$T$201=TRUE)))/(E25-1),""""))"),"") | I25: =IFERROR(AVERAGEIF(Reviews!$H$2:$H$142,B25,Reviews!$C$2:$C$142),"") -> 2 | J25: =SUMIF(Interactions!$B$2:$B$481,B25,Interactions!$I$2:$I$481) -> 13 | K25: =IF(D25="","",MAX(1,MIN(5,6-ROUNDUP(PERCENTRANK($D$2:$D$81,D25)*4+1,0)))) -> 1 | L25: =MAX(1,MIN(5,ROUNDUP(PERCENTRANK($E$2:$E$81,E25)*4+1,0))) -> 3 | M25: =MAX(1,MIN(5,ROUNDUP(PERCENTRANK($F$2:$F$81,F25)*4+1,0))) -> 3 | N25: =IF(K25="","",ROUND((K25*35+L25*30+M25*20+(1+4*(J25-MIN($J$2:$J$81))/MAX(1,MAX($J$2:$J$81)-MIN($J$2:$J$81)))*15)/5,1)) -> 47.2 | O25: =IF(N25="","Chưa đủ dữ liệu",IF(N25>=80,"Tiềm năng cao",IF(N25>=60,"Tiềm năng","Thông thường"))) -> Thông thường | P25: Rule-based prototype
A26: 46247 | B26: KH0025 | C26: =IFERROR(VLOOKUP(B26,Customers!$B$2:$L$81,11,FALSE),"") -> EMP001 | D26: =IFERROR(__xludf.DUMMYFUNCTION("IFERROR(A26-MAX(FILTER(Orders!$D$2:$D$201,Orders!$I$2:$I$201=B26,Orders!$T$2:$T$201=TRUE)),"""")"),"") | E26: =COUNTIFS(Orders!$I$2:$I$201,B26,Orders!$T$2:$T$201,TRUE) -> 0 | F26: =SUMIFS(Orders!$R$2:$R$201,Orders!$I$2:$I$201,B26,Orders!$T$2:$T$201,TRUE) -> 0 | G26: =IFERROR(F26/E26,0) -> 0 | H26: =IFERROR(__xludf.DUMMYFUNCTION("IF(E26<2,"""",IFERROR((MAX(FILTER(Orders!$D$2:$D$201,Orders!$I$2:$I$201=B26,Orders!$T$2:$T$201=TRUE))-MIN(FILTER(Orders!$D$2:$D$201,Orders!$I$2:$I$201=B26,Orders!$T$2:$T$201=TRUE)))/(E26-1),""""))"),"") | I26: =IFERROR(AVERAGEIF(Reviews!$H$2:$H$142,B26,Reviews!$C$2:$C$142),"") -> 2 | J26: =SUMIF(Interactions!$B$2:$B$481,B26,Interactions!$I$2:$I$481) -> 13 | K26: =IF(D26="","",MAX(1,MIN(5,6-ROUNDUP(PERCENTRANK($D$2:$D$81,D26)*4+1,0)))) | L26: =MAX(1,MIN(5,ROUNDUP(PERCENTRANK($E$2:$E$81,E26)*4+1,0))) -> 1 | M26: =MAX(1,MIN(5,ROUNDUP(PERCENTRANK($F$2:$F$81,F26)*4+1,0))) -> 1 | N26: =IF(K26="","",ROUND((K26*35+L26*30+M26*20+(1+4*(J26-MIN($J$2:$J$81))/MAX(1,MAX($J$2:$J$81)-MIN($J$2:$J$81)))*15)/5,1)) | O26: =IF(N26="","Chưa đủ dữ liệu",IF(N26>=80,"Tiềm năng cao",IF(N26>=60,"Tiềm năng","Thông thường"))) -> Chưa đủ dữ liệu | P26: Rule-based prototype
A27: 46247 | B27: KH0026 | C27: =IFERROR(VLOOKUP(B27,Customers!$B$2:$L$81,11,FALSE),"") -> EMP002 | D27: =IFERROR(__xludf.DUMMYFUNCTION("IFERROR(A27-MAX(FILTER(Orders!$D$2:$D$201,Orders!$I$2:$I$201=B27,Orders!$T$2:$T$201=TRUE)),"""")"),90.21013888889138) -> 90.210139 | E27: =COUNTIFS(Orders!$I$2:$I$201,B27,Orders!$T$2:$T$201,TRUE) -> 3 | F27: =SUMIFS(Orders!$R$2:$R$201,Orders!$I$2:$I$201,B27,Orders!$T$2:$T$201,TRUE) -> 4811000 | G27: =IFERROR(F27/E27,0) -> 1603666.7 | H27: =IFERROR(__xludf.DUMMYFUNCTION("IF(E27<2,"""",IFERROR((MAX(FILTER(Orders!$D$2:$D$201,Orders!$I$2:$I$201=B27,Orders!$T$2:$T$201=TRUE))-MIN(FILTER(Orders!$D$2:$D$201,Orders!$I$2:$I$201=B27,Orders!$T$2:$T$201=TRUE)))/(E27-1),""""))"),175.68523726851708) -> 175.68524 | I27: =IFERROR(AVERAGEIF(Reviews!$H$2:$H$142,B27,Reviews!$C$2:$C$142),"") -> 2.75 | J27: =SUMIF(Interactions!$B$2:$B$481,B27,Interactions!$I$2:$I$481) -> 10 | K27: =IF(D27="","",MAX(1,MIN(5,6-ROUNDUP(PERCENTRANK($D$2:$D$81,D27)*4+1,0)))) -> 4 | L27: =MAX(1,MIN(5,ROUNDUP(PERCENTRANK($E$2:$E$81,E27)*4+1,0))) -> 4 | M27: =MAX(1,MIN(5,ROUNDUP(PERCENTRANK($F$2:$F$81,F27)*4+1,0))) -> 5 | N27: =IF(K27="","",ROUND((K27*35+L27*30+M27*20+(1+4*(J27-MIN($J$2:$J$81))/MAX(1,MAX($J$2:$J$81)-MIN($J$2:$J$81)))*15)/5,1)) -> 75 | O27: =IF(N27="","Chưa đủ dữ liệu",IF(N27>=80,"Tiềm năng cao",IF(N27>=60,"Tiềm năng","Thông thường"))) -> Tiềm năng | P27: Rule-based prototype
A28: 46247 | B28: KH0027 | C28: =IFERROR(VLOOKUP(B28,Customers!$B$2:$L$81,11,FALSE),"") -> EMP003 | D28: =IFERROR(__xludf.DUMMYFUNCTION("IFERROR(A28-MAX(FILTER(Orders!$D$2:$D$201,Orders!$I$2:$I$201=B28,Orders!$T$2:$T$201=TRUE)),"""")"),280.70033564815094) -> 280.70034 | E28: =COUNTIFS(Orders!$I$2:$I$201,B28,Orders!$T$2:$T$201,TRUE) -> 5 | F28: =SUMIFS(Orders!$R$2:$R$201,Orders!$I$2:$I$201,B28,Orders!$T$2:$T$201,TRUE) -> 8521000 | G28: =IFERROR(F28/E28,0) -> 1704200 | H28: =IFERROR(__xludf.DUMMYFUNCTION("IF(E28<2,"""",IFERROR((MAX(FILTER(Orders!$D$2:$D$201,Orders!$I$2:$I$201=B28,Orders!$T$2:$T$201=TRUE))-MIN(FILTER(Orders!$D$2:$D$201,Orders!$I$2:$I$201=B28,Orders!$T$2:$T$201=TRUE)))/(E28-1),""""))"),138.34770543981358) -> 138.34771 | I28: =IFERROR(AVERAGEIF(Reviews!$H$2:$H$142,B28,Reviews!$C$2:$C$142),"") -> 3.6 | J28: =SUMIF(Interactions!$B$2:$B$481,B28,Interactions!$I$2:$I$481) -> 15 | K28: =IF(D28="","",MAX(1,MIN(5,6-ROUNDUP(PERCENTRANK($D$2:$D$81,D28)*4+1,0)))) -> 2 | L28: =MAX(1,MIN(5,ROUNDUP(PERCENTRANK($E$2:$E$81,E28)*4+1,0))) -> 5 | M28: =MAX(1,MIN(5,ROUNDUP(PERCENTRANK($F$2:$F$81,F28)*4+1,0))) -> 5 | N28: =IF(K28="","",ROUND((K28*35+L28*30+M28*20+(1+4*(J28-MIN($J$2:$J$81))/MAX(1,MAX($J$2:$J$81)-MIN($J$2:$J$81)))*15)/5,1)) -> 79 | O28: =IF(N28="","Chưa đủ dữ liệu",IF(N28>=80,"Tiềm năng cao",IF(N28>=60,"Tiềm năng","Thông thường"))) -> Tiềm năng | P28: Rule-based prototype
A29: 46247 | B29: KH0028 | C29: =IFERROR(VLOOKUP(B29,Customers!$B$2:$L$81,11,FALSE),"") -> EMP004 | D29: =IFERROR(__xludf.DUMMYFUNCTION("IFERROR(A29-MAX(FILTER(Orders!$D$2:$D$201,Orders!$I$2:$I$201=B29,Orders!$T$2:$T$201=TRUE)),"""")"),"") | E29: =COUNTIFS(Orders!$I$2:$I$201,B29,Orders!$T$2:$T$201,TRUE) -> 0 | F29: =SUMIFS(Orders!$R$2:$R$201,Orders!$I$2:$I$201,B29,Orders!$T$2:$T$201,TRUE) -> 0 | G29: =IFERROR(F29/E29,0) -> 0 | H29: =IFERROR(__xludf.DUMMYFUNCTION("IF(E29<2,"""",IFERROR((MAX(FILTER(Orders!$D$2:$D$201,Orders!$I$2:$I$201=B29,Orders!$T$2:$T$201=TRUE))-MIN(FILTER(Orders!$D$2:$D$201,Orders!$I$2:$I$201=B29,Orders!$T$2:$T$201=TRUE)))/(E29-1),""""))"),"") | I29: =IFERROR(AVERAGEIF(Reviews!$H$2:$H$142,B29,Reviews!$C$2:$C$142),"") | J29: =SUMIF(Interactions!$B$2:$B$481,B29,Interactions!$I$2:$I$481) -> 14 | K29: =IF(D29="","",MAX(1,MIN(5,6-ROUNDUP(PERCENTRANK($D$2:$D$81,D29)*4+1,0)))) | L29: =MAX(1,MIN(5,ROUNDUP(PERCENTRANK($E$2:$E$81,E29)*4+1,0))) -> 1 | M29: =MAX(1,MIN(5,ROUNDUP(PERCENTRANK($F$2:$F$81,F29)*4+1,0))) -> 1 | N29: =IF(K29="","",ROUND((K29*35+L29*30+M29*20+(1+4*(J29-MIN($J$2:$J$81))/MAX(1,MAX($J$2:$J$81)-MIN($J$2:$J$81)))*15)/5,1)) | O29: =IF(N29="","Chưa đủ dữ liệu",IF(N29>=80,"Tiềm năng cao",IF(N29>=60,"Tiềm năng","Thông thường"))) -> Chưa đủ dữ liệu | P29: Rule-based prototype
A30: 46247 | B30: KH0029 | C30: =IFERROR(VLOOKUP(B30,Customers!$B$2:$L$81,11,FALSE),"") -> EMP005 | D30: =IFERROR(__xludf.DUMMYFUNCTION("IFERROR(A30-MAX(FILTER(Orders!$D$2:$D$201,Orders!$I$2:$I$201=B30,Orders!$T$2:$T$201=TRUE)),"""")"),341.62327546296) -> 341.62328 | E30: =COUNTIFS(Orders!$I$2:$I$201,B30,Orders!$T$2:$T$201,TRUE) -> 2 | F30: =SUMIFS(Orders!$R$2:$R$201,Orders!$I$2:$I$201,B30,Orders!$T$2:$T$201,TRUE) -> 1741000 | G30: =IFERROR(F30/E30,0) -> 870500 | H30: =IFERROR(__xludf.DUMMYFUNCTION("IF(E30<2,"""",IFERROR((MAX(FILTER(Orders!$D$2:$D$201,Orders!$I$2:$I$201=B30,Orders!$T$2:$T$201=TRUE))-MIN(FILTER(Orders!$D$2:$D$201,Orders!$I$2:$I$201=B30,Orders!$T$2:$T$201=TRUE)))/(E30-1),""""))"),546.2475462962975) -> 546.24755 | I30: =IFERROR(AVERAGEIF(Reviews!$H$2:$H$142,B30,Reviews!$C$2:$C$142),"") -> 4 | J30: =SUMIF(Interactions!$B$2:$B$481,B30,Interactions!$I$2:$I$481) -> 11 | K30: =IF(D30="","",MAX(1,MIN(5,6-ROUNDUP(PERCENTRANK($D$2:$D$81,D30)*4+1,0)))) -> 2 | L30: =MAX(1,MIN(5,ROUNDUP(PERCENTRANK($E$2:$E$81,E30)*4+1,0))) -> 4 | M30: =MAX(1,MIN(5,ROUNDUP(PERCENTRANK($F$2:$F$81,F30)*4+1,0))) -> 3 | N30: =IF(K30="","",ROUND((K30*35+L30*30+M30*20+(1+4*(J30-MIN($J$2:$J$81))/MAX(1,MAX($J$2:$J$81)-MIN($J$2:$J$81)))*15)/5,1)) -> 55.4 | O30: =IF(N30="","Chưa đủ dữ liệu",IF(N30>=80,"Tiềm năng cao",IF(N30>=60,"Tiềm năng","Thông thường"))) -> Thông thường | P30: Rule-based prototype
A31: 46247 | B31: KH0030 | C31: =IFERROR(VLOOKUP(B31,Customers!$B$2:$L$81,11,FALSE),"") -> EMP006 | D31: =IFERROR(__xludf.DUMMYFUNCTION("IFERROR(A31-MAX(FILTER(Orders!$D$2:$D$201,Orders!$I$2:$I$201=B31,Orders!$T$2:$T$201=TRUE)),"""")"),28.081307870372257) -> 28.081308 | E31: =COUNTIFS(Orders!$I$2:$I$201,B31,Orders!$T$2:$T$201,TRUE) -> 3 | F31: =SUMIFS(Orders!$R$2:$R$201,Orders!$I$2:$I$201,B31,Orders!$T$2:$T$201,TRUE) -> 7492000 | G31: =IFERROR(F31/E31,0) -> 2497333.3 | H31: =IFERROR(__xludf.DUMMYFUNCTION("IF(E31<2,"""",IFERROR((MAX(FILTER(Orders!$D$2:$D$201,Orders!$I$2:$I$201=B31,Orders!$T$2:$T$201=TRUE))-MIN(FILTER(Orders!$D$2:$D$201,Orders!$I$2:$I$201=B31,Orders!$T$2:$T$201=TRUE)))/(E31-1),""""))"),396.22424189814774) -> 396.22424 | I31: =IFERROR(AVERAGEIF(Reviews!$H$2:$H$142,B31,Reviews!$C$2:$C$142),"") -> 3 | J31: =SUMIF(Interactions!$B$2:$B$481,B31,Interactions!$I$2:$I$481) -> 14 | K31: =IF(D31="","",MAX(1,MIN(5,6-ROUNDUP(PERCENTRANK($D$2:$D$81,D31)*4+1,0)))) -> 4 | L31: =MAX(1,MIN(5,ROUNDUP(PERCENTRANK($E$2:$E$81,E31)*4+1,0))) -> 4 | M31: =MAX(1,MIN(5,ROUNDUP(PERCENTRANK($F$2:$F$81,F31)*4+1,0))) -> 5 | N31: =IF(K31="","",ROUND((K31*35+L31*30+M31*20+(1+4*(J31-MIN($J$2:$J$81))/MAX(1,MAX($J$2:$J$81)-MIN($J$2:$J$81)))*15)/5,1)) -> 84.6 | O31: =IF(N31="","Chưa đủ dữ liệu",IF(N31>=80,"Tiềm năng cao",IF(N31>=60,"Tiềm năng","Thông thường"))) -> Tiềm năng cao | P31: Rule-based prototype
A32: 46247 | B32: KH0031 | C32: =IFERROR(VLOOKUP(B32,Customers!$B$2:$L$81,11,FALSE),"") -> EMP007 | D32: =IFERROR(__xludf.DUMMYFUNCTION("IFERROR(A32-MAX(FILTER(Orders!$D$2:$D$201,Orders!$I$2:$I$201=B32,Orders!$T$2:$T$201=TRUE)),"""")"),467.9645138888882) -> 467.96451 | E32: =COUNTIFS(Orders!$I$2:$I$201,B32,Orders!$T$2:$T$201,TRUE) -> 1 | F32: =SUMIFS(Orders!$R$2:$R$201,Orders!$I$2:$I$201,B32,Orders!$T$2:$T$201,TRUE) -> 996000 | G32: =IFERROR(F32/E32,0) -> 996000 | H32: =IFERROR(__xludf.DUMMYFUNCTION("IF(E32<2,"""",IFERROR((MAX(FILTER(Orders!$D$2:$D$201,Orders!$I$2:$I$201=B32,Orders!$T$2:$T$201=TRUE))-MIN(FILTER(Orders!$D$2:$D$201,Orders!$I$2:$I$201=B32,Orders!$T$2:$T$201=TRUE)))/(E32-1),""""))"),"") | I32: =IFERROR(AVERAGEIF(Reviews!$H$2:$H$142,B32,Reviews!$C$2:$C$142),"") -> 1.6666667 | J32: =SUMIF(Interactions!$B$2:$B$481,B32,Interactions!$I$2:$I$481) -> 12 | K32: =IF(D32="","",MAX(1,MIN(5,6-ROUNDUP(PERCENTRANK($D$2:$D$81,D32)*4+1,0)))) -> 1 | L32: =MAX(1,MIN(5,ROUNDUP(PERCENTRANK($E$2:$E$81,E32)*4+1,0))) -> 3 | M32: =MAX(1,MIN(5,ROUNDUP(PERCENTRANK($F$2:$F$81,F32)*4+1,0))) -> 3 | N32: =IF(K32="","",ROUND((K32*35+L32*30+M32*20+(1+4*(J32-MIN($J$2:$J$81))/MAX(1,MAX($J$2:$J$81)-MIN($J$2:$J$81)))*15)/5,1)) -> 44.8 | O32: =IF(N32="","Chưa đủ dữ liệu",IF(N32>=80,"Tiềm năng cao",IF(N32>=60,"Tiềm năng","Thông thường"))) -> Thông thường | P32: Rule-based prototype
A33: 46247 | B33: KH0032 | C33: =IFERROR(VLOOKUP(B33,Customers!$B$2:$L$81,11,FALSE),"") -> EMP008 | D33: =IFERROR(__xludf.DUMMYFUNCTION("IFERROR(A33-MAX(FILTER(Orders!$D$2:$D$201,Orders!$I$2:$I$201=B33,Orders!$T$2:$T$201=TRUE)),"""")"),82.60910879629955) -> 82.609109 | E33: =COUNTIFS(Orders!$I$2:$I$201,B33,Orders!$T$2:$T$201,TRUE) -> 9 | F33: =SUMIFS(Orders!$R$2:$R$201,Orders!$I$2:$I$201,B33,Orders!$T$2:$T$201,TRUE) -> 11101000 | G33: =IFERROR(F33/E33,0) -> 1233444.4 | H33: =IFERROR(__xludf.DUMMYFUNCTION("IF(E33<2,"""",IFERROR((MAX(FILTER(Orders!$D$2:$D$201,Orders!$I$2:$I$201=B33,Orders!$T$2:$T$201=TRUE))-MIN(FILTER(Orders!$D$2:$D$201,Orders!$I$2:$I$201=B33,Orders!$T$2:$T$201=TRUE)))/(E33-1),""""))"),80.55700376157347) -> 80.557004 | I33: =IFERROR(AVERAGEIF(Reviews!$H$2:$H$142,B33,Reviews!$C$2:$C$142),"") -> 4.125 | J33: =SUMIF(Interactions!$B$2:$B$481,B33,Interactions!$I$2:$I$481) -> 13 | K33: =IF(D33="","",MAX(1,MIN(5,6-ROUNDUP(PERCENTRANK($D$2:$D$81,D33)*4+1,0)))) -> 4 | L33: =MAX(1,MIN(5,ROUNDUP(PERCENTRANK($E$2:$E$81,E33)*4+1,0))) -> 5 | M33: =MAX(1,MIN(5,ROUNDUP(PERCENTRANK($F$2:$F$81,F33)*4+1,0))) -> 5 | N33: =IF(K33="","",ROUND((K33*35+L33*30+M33*20+(1+4*(J33-MIN($J$2:$J$81))/MAX(1,MAX($J$2:$J$81)-MIN($J$2:$J$81)))*15)/5,1)) -> 88.2 | O33: =IF(N33="","Chưa đủ dữ liệu",IF(N33>=80,"Tiềm năng cao",IF(N33>=60,"Tiềm năng","Thông thường"))) -> Tiềm năng cao | P33: Rule-based prototype
A34: 46247 | B34: KH0033 | C34: =IFERROR(VLOOKUP(B34,Customers!$B$2:$L$81,11,FALSE),"") -> EMP001 | D34: =IFERROR(__xludf.DUMMYFUNCTION("IFERROR(A34-MAX(FILTER(Orders!$D$2:$D$201,Orders!$I$2:$I$201=B34,Orders!$T$2:$T$201=TRUE)),"""")"),77.94567129629286) -> 77.945671 | E34: =COUNTIFS(Orders!$I$2:$I$201,B34,Orders!$T$2:$T$201,TRUE) -> 3 | F34: =SUMIFS(Orders!$R$2:$R$201,Orders!$I$2:$I$201,B34,Orders!$T$2:$T$201,TRUE) -> 2863000 | G34: =IFERROR(F34/E34,0) -> 954333.33 | H34: =IFERROR(__xludf.DUMMYFUNCTION("IF(E34<2,"""",IFERROR((MAX(FILTER(Orders!$D$2:$D$201,Orders!$I$2:$I$201=B34,Orders!$T$2:$T$201=TRUE))-MIN(FILTER(Orders!$D$2:$D$201,Orders!$I$2:$I$201=B34,Orders!$T$2:$T$201=TRUE)))/(E34-1),""""))"),352.67263310185444) -> 352.67263 | I34: =IFERROR(AVERAGEIF(Reviews!$H$2:$H$142,B34,Reviews!$C$2:$C$142),"") -> 2.75 | J34: =SUMIF(Interactions!$B$2:$B$481,B34,Interactions!$I$2:$I$481) -> 13 | K34: =IF(D34="","",MAX(1,MIN(5,6-ROUNDUP(PERCENTRANK($D$2:$D$81,D34)*4+1,0)))) -> 4 | L34: =MAX(1,MIN(5,ROUNDUP(PERCENTRANK($E$2:$E$81,E34)*4+1,0))) -> 4 | M34: =MAX(1,MIN(5,ROUNDUP(PERCENTRANK($F$2:$F$81,F34)*4+1,0))) -> 4 | N34: =IF(K34="","",ROUND((K34*35+L34*30+M34*20+(1+4*(J34-MIN($J$2:$J$81))/MAX(1,MAX($J$2:$J$81)-MIN($J$2:$J$81)))*15)/5,1)) -> 78.2 | O34: =IF(N34="","Chưa đủ dữ liệu",IF(N34>=80,"Tiềm năng cao",IF(N34>=60,"Tiềm năng","Thông thường"))) -> Tiềm năng | P34: Rule-based prototype
A35: 46247 | B35: KH0034 | C35: =IFERROR(VLOOKUP(B35,Customers!$B$2:$L$81,11,FALSE),"") -> EMP002 | D35: =IFERROR(__xludf.DUMMYFUNCTION("IFERROR(A35-MAX(FILTER(Orders!$D$2:$D$201,Orders!$I$2:$I$201=B35,Orders!$T$2:$T$201=TRUE)),"""")"),414.1937615740753) -> 414.19376 | E35: =COUNTIFS(Orders!$I$2:$I$201,B35,Orders!$T$2:$T$201,TRUE) -> 1 | F35: =SUMIFS(Orders!$R$2:$R$201,Orders!$I$2:$I$201,B35,Orders!$T$2:$T$201,TRUE) -> 2210000 | G35: =IFERROR(F35/E35,0) -> 2210000 | H35: =IFERROR(__xludf.DUMMYFUNCTION("IF(E35<2,"""",IFERROR((MAX(FILTER(Orders!$D$2:$D$201,Orders!$I$2:$I$201=B35,Orders!$T$2:$T$201=TRUE))-MIN(FILTER(Orders!$D$2:$D$201,Orders!$I$2:$I$201=B35,Orders!$T$2:$T$201=TRUE)))/(E35-1),""""))"),"") | I35: =IFERROR(AVERAGEIF(Reviews!$H$2:$H$142,B35,Reviews!$C$2:$C$142),"") -> 2.5 | J35: =SUMIF(Interactions!$B$2:$B$481,B35,Interactions!$I$2:$I$481) -> 10 | K35: =IF(D35="","",MAX(1,MIN(5,6-ROUNDUP(PERCENTRANK($D$2:$D$81,D35)*4+1,0)))) -> 1 | L35: =MAX(1,MIN(5,ROUNDUP(PERCENTRANK($E$2:$E$81,E35)*4+1,0))) -> 3 | M35: =MAX(1,MIN(5,ROUNDUP(PERCENTRANK($F$2:$F$81,F35)*4+1,0))) -> 3 | N35: =IF(K35="","",ROUND((K35*35+L35*30+M35*20+(1+4*(J35-MIN($J$2:$J$81))/MAX(1,MAX($J$2:$J$81)-MIN($J$2:$J$81)))*15)/5,1)) -> 40 | O35: =IF(N35="","Chưa đủ dữ liệu",IF(N35>=80,"Tiềm năng cao",IF(N35>=60,"Tiềm năng","Thông thường"))) -> Thông thường | P35: Rule-based prototype
A36: 46247 | B36: KH0035 | C36: =IFERROR(VLOOKUP(B36,Customers!$B$2:$L$81,11,FALSE),"") -> EMP003 | D36: =IFERROR(__xludf.DUMMYFUNCTION("IFERROR(A36-MAX(FILTER(Orders!$D$2:$D$201,Orders!$I$2:$I$201=B36,Orders!$T$2:$T$201=TRUE)),"""")"),73.86202546296408) -> 73.862025 | E36: =COUNTIFS(Orders!$I$2:$I$201,B36,Orders!$T$2:$T$201,TRUE) -> 4 | F36: =SUMIFS(Orders!$R$2:$R$201,Orders!$I$2:$I$201,B36,Orders!$T$2:$T$201,TRUE) -> 2773000 | G36: =IFERROR(F36/E36,0) -> 693250 | H36: =IFERROR(__xludf.DUMMYFUNCTION("IF(E36<2,"""",IFERROR((MAX(FILTER(Orders!$D$2:$D$201,Orders!$I$2:$I$201=B36,Orders!$T$2:$T$201=TRUE))-MIN(FILTER(Orders!$D$2:$D$201,Orders!$I$2:$I$201=B36,Orders!$T$2:$T$201=TRUE)))/(E36-1),""""))"),199.23005015432136) -> 199.23005 | I36: =IFERROR(AVERAGEIF(Reviews!$H$2:$H$142,B36,Reviews!$C$2:$C$142),"") -> 3.75 | J36: =SUMIF(Interactions!$B$2:$B$481,B36,Interactions!$I$2:$I$481) -> 15 | K36: =IF(D36="","",MAX(1,MIN(5,6-ROUNDUP(PERCENTRANK($D$2:$D$81,D36)*4+1,0)))) -> 4 | L36: =MAX(1,MIN(5,ROUNDUP(PERCENTRANK($E$2:$E$81,E36)*4+1,0))) -> 5 | M36: =MAX(1,MIN(5,ROUNDUP(PERCENTRANK($F$2:$F$81,F36)*4+1,0))) -> 4 | N36: =IF(K36="","",ROUND((K36*35+L36*30+M36*20+(1+4*(J36-MIN($J$2:$J$81))/MAX(1,MAX($J$2:$J$81)-MIN($J$2:$J$81)))*15)/5,1)) -> 89 | O36: =IF(N36="","Chưa đủ dữ liệu",IF(N36>=80,"Tiềm năng cao",IF(N36>=60,"Tiềm năng","Thông thường"))) -> Tiềm năng cao | P36: Rule-based prototype
A37: 46247 | B37: KH0036 | C37: =IFERROR(VLOOKUP(B37,Customers!$B$2:$L$81,11,FALSE),"") -> EMP004 | D37: =IFERROR(__xludf.DUMMYFUNCTION("IFERROR(A37-MAX(FILTER(Orders!$D$2:$D$201,Orders!$I$2:$I$201=B37,Orders!$T$2:$T$201=TRUE)),"""")"),267.6656828703708) -> 267.66568 | E37: =COUNTIFS(Orders!$I$2:$I$201,B37,Orders!$T$2:$T$201,TRUE) -> 4 | F37: =SUMIFS(Orders!$R$2:$R$201,Orders!$I$2:$I$201,B37,Orders!$T$2:$T$201,TRUE) -> 2675000 | G37: =IFERROR(F37/E37,0) -> 668750 | H37: =IFERROR(__xludf.DUMMYFUNCTION("IF(E37<2,"""",IFERROR((MAX(FILTER(Orders!$D$2:$D$201,Orders!$I$2:$I$201=B37,Orders!$T$2:$T$201=TRUE))-MIN(FILTER(Orders!$D$2:$D$201,Orders!$I$2:$I$201=B37,Orders!$T$2:$T$201=TRUE)))/(E37-1),""""))"),209.40783179012215) -> 209.40783 | I37: =IFERROR(AVERAGEIF(Reviews!$H$2:$H$142,B37,Reviews!$C$2:$C$142),"") -> 4 | J37: =SUMIF(Interactions!$B$2:$B$481,B37,Interactions!$I$2:$I$481) -> 14 | K37: =IF(D37="","",MAX(1,MIN(5,6-ROUNDUP(PERCENTRANK($D$2:$D$81,D37)*4+1,0)))) -> 2 | L37: =MAX(1,MIN(5,ROUNDUP(PERCENTRANK($E$2:$E$81,E37)*4+1,0))) -> 5 | M37: =MAX(1,MIN(5,ROUNDUP(PERCENTRANK($F$2:$F$81,F37)*4+1,0))) -> 4 | N37: =IF(K37="","",ROUND((K37*35+L37*30+M37*20+(1+4*(J37-MIN($J$2:$J$81))/MAX(1,MAX($J$2:$J$81)-MIN($J$2:$J$81)))*15)/5,1)) -> 72.6 | O37: =IF(N37="","Chưa đủ dữ liệu",IF(N37>=80,"Tiềm năng cao",IF(N37>=60,"Tiềm năng","Thông thường"))) -> Tiềm năng | P37: Rule-based prototype
A38: 46247 | B38: KH0037 | C38: =IFERROR(VLOOKUP(B38,Customers!$B$2:$L$81,11,FALSE),"") -> EMP005 | D38: =IFERROR(__xludf.DUMMYFUNCTION("IFERROR(A38-MAX(FILTER(Orders!$D$2:$D$201,Orders!$I$2:$I$201=B38,Orders!$T$2:$T$201=TRUE)),"""")"),105.55846064814978) -> 105.55846 | E38: =COUNTIFS(Orders!$I$2:$I$201,B38,Orders!$T$2:$T$201,TRUE) -> 1 | F38: =SUMIFS(Orders!$R$2:$R$201,Orders!$I$2:$I$201,B38,Orders!$T$2:$T$201,TRUE) -> 987000 | G38: =IFERROR(F38/E38,0) -> 987000 | H38: =IFERROR(__xludf.DUMMYFUNCTION("IF(E38<2,"""",IFERROR((MAX(FILTER(Orders!$D$2:$D$201,Orders!$I$2:$I$201=B38,Orders!$T$2:$T$201=TRUE))-MIN(FILTER(Orders!$D$2:$D$201,Orders!$I$2:$I$201=B38,Orders!$T$2:$T$201=TRUE)))/(E38-1),""""))"),"") | I38: =IFERROR(AVERAGEIF(Reviews!$H$2:$H$142,B38,Reviews!$C$2:$C$142),"") -> 3 | J38: =SUMIF(Interactions!$B$2:$B$481,B38,Interactions!$I$2:$I$481) -> 11 | K38: =IF(D38="","",MAX(1,MIN(5,6-ROUNDUP(PERCENTRANK($D$2:$D$81,D38)*4+1,0)))) -> 3 | L38: =MAX(1,MIN(5,ROUNDUP(PERCENTRANK($E$2:$E$81,E38)*4+1,0))) -> 3 | M38: =MAX(1,MIN(5,ROUNDUP(PERCENTRANK($F$2:$F$81,F38)*4+1,0))) -> 3 | N38: =IF(K38="","",ROUND((K38*35+L38*30+M38*20+(1+4*(J38-MIN($J$2:$J$81))/MAX(1,MAX($J$2:$J$81)-MIN($J$2:$J$81)))*15)/5,1)) -> 56.4 | O38: =IF(N38="","Chưa đủ dữ liệu",IF(N38>=80,"Tiềm năng cao",IF(N38>=60,"Tiềm năng","Thông thường"))) -> Thông thường | P38: Rule-based prototype
A39: 46247 | B39: KH0038 | C39: =IFERROR(VLOOKUP(B39,Customers!$B$2:$L$81,11,FALSE),"") -> EMP006 | D39: =IFERROR(__xludf.DUMMYFUNCTION("IFERROR(A39-MAX(FILTER(Orders!$D$2:$D$201,Orders!$I$2:$I$201=B39,Orders!$T$2:$T$201=TRUE)),"""")"),156.5748611111121) -> 156.57486 | E39: =COUNTIFS(Orders!$I$2:$I$201,B39,Orders!$T$2:$T$201,TRUE) -> 1 | F39: =SUMIFS(Orders!$R$2:$R$201,Orders!$I$2:$I$201,B39,Orders!$T$2:$T$201,TRUE) -> 2598000 | G39: =IFERROR(F39/E39,0) -> 2598000 | H39: =IFERROR(__xludf.DUMMYFUNCTION("IF(E39<2,"""",IFERROR((MAX(FILTER(Orders!$D$2:$D$201,Orders!$I$2:$I$201=B39,Orders!$T$2:$T$201=TRUE))-MIN(FILTER(Orders!$D$2:$D$201,Orders!$I$2:$I$201=B39,Orders!$T$2:$T$201=TRUE)))/(E39-1),""""))"),"") | I39: =IFERROR(AVERAGEIF(Reviews!$H$2:$H$142,B39,Reviews!$C$2:$C$142),"") -> 4 | J39: =SUMIF(Interactions!$B$2:$B$481,B39,Interactions!$I$2:$I$481) -> 14 | K39: =IF(D39="","",MAX(1,MIN(5,6-ROUNDUP(PERCENTRANK($D$2:$D$81,D39)*4+1,0)))) -> 3 | L39: =MAX(1,MIN(5,ROUNDUP(PERCENTRANK($E$2:$E$81,E39)*4+1,0))) -> 3 | M39: =MAX(1,MIN(5,ROUNDUP(PERCENTRANK($F$2:$F$81,F39)*4+1,0))) -> 4 | N39: =IF(K39="","",ROUND((K39*35+L39*30+M39*20+(1+4*(J39-MIN($J$2:$J$81))/MAX(1,MAX($J$2:$J$81)-MIN($J$2:$J$81)))*15)/5,1)) -> 67.6 | O39: =IF(N39="","Chưa đủ dữ liệu",IF(N39>=80,"Tiềm năng cao",IF(N39>=60,"Tiềm năng","Thông thường"))) -> Tiềm năng | P39: Rule-based prototype
A40: 46247 | B40: KH0039 | C40: =IFERROR(VLOOKUP(B40,Customers!$B$2:$L$81,11,FALSE),"") -> EMP007 | D40: =IFERROR(__xludf.DUMMYFUNCTION("IFERROR(A40-MAX(FILTER(Orders!$D$2:$D$201,Orders!$I$2:$I$201=B40,Orders!$T$2:$T$201=TRUE)),"""")"),301.5201736111121) -> 301.52017 | E40: =COUNTIFS(Orders!$I$2:$I$201,B40,Orders!$T$2:$T$201,TRUE) -> 1 | F40: =SUMIFS(Orders!$R$2:$R$201,Orders!$I$2:$I$201,B40,Orders!$T$2:$T$201,TRUE) -> 1154000 | G40: =IFERROR(F40/E40,0) -> 1154000 | H40: =IFERROR(__xludf.DUMMYFUNCTION("IF(E40<2,"""",IFERROR((MAX(FILTER(Orders!$D$2:$D$201,Orders!$I$2:$I$201=B40,Orders!$T$2:$T$201=TRUE))-MIN(FILTER(Orders!$D$2:$D$201,Orders!$I$2:$I$201=B40,Orders!$T$2:$T$201=TRUE)))/(E40-1),""""))"),"") | I40: =IFERROR(AVERAGEIF(Reviews!$H$2:$H$142,B40,Reviews!$C$2:$C$142),"") | J40: =SUMIF(Interactions!$B$2:$B$481,B40,Interactions!$I$2:$I$481) -> 12 | K40: =IF(D40="","",MAX(1,MIN(5,6-ROUNDUP(PERCENTRANK($D$2:$D$81,D40)*4+1,0)))) -> 2 | L40: =MAX(1,MIN(5,ROUNDUP(PERCENTRANK($E$2:$E$81,E40)*4+1,0))) -> 3 | M40: =MAX(1,MIN(5,ROUNDUP(PERCENTRANK($F$2:$F$81,F40)*4+1,0))) -> 3 | N40: =IF(K40="","",ROUND((K40*35+L40*30+M40*20+(1+4*(J40-MIN($J$2:$J$81))/MAX(1,MAX($J$2:$J$81)-MIN($J$2:$J$81)))*15)/5,1)) -> 51.8 | O40: =IF(N40="","Chưa đủ dữ liệu",IF(N40>=80,"Tiềm năng cao",IF(N40>=60,"Tiềm năng","Thông thường"))) -> Thông thường | P40: Rule-based prototype
A41: 46247 | B41: KH0040 | C41: =IFERROR(VLOOKUP(B41,Customers!$B$2:$L$81,11,FALSE),"") -> EMP008 | D41: =IFERROR(__xludf.DUMMYFUNCTION("IFERROR(A41-MAX(FILTER(Orders!$D$2:$D$201,Orders!$I$2:$I$201=B41,Orders!$T$2:$T$201=TRUE)),"""")"),94.85784722222161) -> 94.857847 | E41: =COUNTIFS(Orders!$I$2:$I$201,B41,Orders!$T$2:$T$201,TRUE) -> 2 | F41: =SUMIFS(Orders!$R$2:$R$201,Orders!$I$2:$I$201,B41,Orders!$T$2:$T$201,TRUE) -> 666000 | G41: =IFERROR(F41/E41,0) -> 333000 | H41: =IFERROR(__xludf.DUMMYFUNCTION("IF(E41<2,"""",IFERROR((MAX(FILTER(Orders!$D$2:$D$201,Orders!$I$2:$I$201=B41,Orders!$T$2:$T$201=TRUE))-MIN(FILTER(Orders!$D$2:$D$201,Orders!$I$2:$I$201=B41,Orders!$T$2:$T$201=TRUE)))/(E41-1),""""))"),231.08486111111415) -> 231.08486 | I41: =IFERROR(AVERAGEIF(Reviews!$H$2:$H$142,B41,Reviews!$C$2:$C$142),"") -> 3.6666667 | J41: =SUMIF(Interactions!$B$2:$B$481,B41,Interactions!$I$2:$I$481) -> 13 | K41: =IF(D41="","",MAX(1,MIN(5,6-ROUNDUP(PERCENTRANK($D$2:$D$81,D41)*4+1,0)))) -> 3 | L41: =MAX(1,MIN(5,ROUNDUP(PERCENTRANK($E$2:$E$81,E41)*4+1,0))) -> 4 | M41: =MAX(1,MIN(5,ROUNDUP(PERCENTRANK($F$2:$F$81,F41)*4+1,0))) -> 3 | N41: =IF(K41="","",ROUND((K41*35+L41*30+M41*20+(1+4*(J41-MIN($J$2:$J$81))/MAX(1,MAX($J$2:$J$81)-MIN($J$2:$J$81)))*15)/5,1)) -> 67.2 | O41: =IF(N41="","Chưa đủ dữ liệu",IF(N41>=80,"Tiềm năng cao",IF(N41>=60,"Tiềm năng","Thông thường"))) -> Tiềm năng | P41: Rule-based prototype
A42: 46247 | B42: KH0041 | C42: =IFERROR(VLOOKUP(B42,Customers!$B$2:$L$81,11,FALSE),"") -> EMP001 | D42: =IFERROR(__xludf.DUMMYFUNCTION("IFERROR(A42-MAX(FILTER(Orders!$D$2:$D$201,Orders!$I$2:$I$201=B42,Orders!$T$2:$T$201=TRUE)),"""")"),153.67476851851825) -> 153.67477 | E42: =COUNTIFS(Orders!$I$2:$I$201,B42,Orders!$T$2:$T$201,TRUE) -> 3 | F42: =SUMIFS(Orders!$R$2:$R$201,Orders!$I$2:$I$201,B42,Orders!$T$2:$T$201,TRUE) -> 6917000 | G42: =IFERROR(F42/E42,0) -> 2305666.7 | H42: =IFERROR(__xludf.DUMMYFUNCTION("IF(E42<2,"""",IFERROR((MAX(FILTER(Orders!$D$2:$D$201,Orders!$I$2:$I$201=B42,Orders!$T$2:$T$201=TRUE))-MIN(FILTER(Orders!$D$2:$D$201,Orders!$I$2:$I$201=B42,Orders!$T$2:$T$201=TRUE)))/(E42-1),""""))"),193.87000578703737) -> 193.87001 | I42: =IFERROR(AVERAGEIF(Reviews!$H$2:$H$142,B42,Reviews!$C$2:$C$142),"") -> 3.5 | J42: =SUMIF(Interactions!$B$2:$B$481,B42,Interactions!$I$2:$I$481) -> 13 | K42: =IF(D42="","",MAX(1,MIN(5,6-ROUNDUP(PERCENTRANK($D$2:$D$81,D42)*4+1,0)))) -> 3 | L42: =MAX(1,MIN(5,ROUNDUP(PERCENTRANK($E$2:$E$81,E42)*4+1,0))) -> 4 | M42: =MAX(1,MIN(5,ROUNDUP(PERCENTRANK($F$2:$F$81,F42)*4+1,0))) -> 5 | N42: =IF(K42="","",ROUND((K42*35+L42*30+M42*20+(1+4*(J42-MIN($J$2:$J$81))/MAX(1,MAX($J$2:$J$81)-MIN($J$2:$J$81)))*15)/5,1)) -> 75.2 | O42: =IF(N42="","Chưa đủ dữ liệu",IF(N42>=80,"Tiềm năng cao",IF(N42>=60,"Tiềm năng","Thông thường"))) -> Tiềm năng | P42: Rule-based prototype
A43: 46247 | B43: KH0042 | C43: =IFERROR(VLOOKUP(B43,Customers!$B$2:$L$81,11,FALSE),"") -> EMP002 | D43: =IFERROR(__xludf.DUMMYFUNCTION("IFERROR(A43-MAX(FILTER(Orders!$D$2:$D$201,Orders!$I$2:$I$201=B43,Orders!$T$2:$T$201=TRUE)),"""")"),322.4688541666692) -> 322.46885 | E43: =COUNTIFS(Orders!$I$2:$I$201,B43,Orders!$T$2:$T$201,TRUE) -> 3 | F43: =SUMIFS(Orders!$R$2:$R$201,Orders!$I$2:$I$201,B43,Orders!$T$2:$T$201,TRUE) -> 5591000 | G43: =IFERROR(F43/E43,0) -> 1863666.7 | H43: =IFERROR(__xludf.DUMMYFUNCTION("IF(E43<2,"""",IFERROR((MAX(FILTER(Orders!$D$2:$D$201,Orders!$I$2:$I$201=B43,Orders!$T$2:$T$201=TRUE))-MIN(FILTER(Orders!$D$2:$D$201,Orders!$I$2:$I$201=B43,Orders!$T$2:$T$201=TRUE)))/(E43-1),""""))"),288.764334490741) -> 288.76433 | I43: =IFERROR(AVERAGEIF(Reviews!$H$2:$H$142,B43,Reviews!$C$2:$C$142),"") -> 4.6666667 | J43: =SUMIF(Interactions!$B$2:$B$481,B43,Interactions!$I$2:$I$481) -> 10 | K43: =IF(D43="","",MAX(1,MIN(5,6-ROUNDUP(PERCENTRANK($D$2:$D$81,D43)*4+1,0)))) -> 2 | L43: =MAX(1,MIN(5,ROUNDUP(PERCENTRANK($E$2:$E$81,E43)*4+1,0))) -> 4 | M43: =MAX(1,MIN(5,ROUNDUP(PERCENTRANK($F$2:$F$81,F43)*4+1,0))) -> 5 | N43: =IF(K43="","",ROUND((K43*35+L43*30+M43*20+(1+4*(J43-MIN($J$2:$J$81))/MAX(1,MAX($J$2:$J$81)-MIN($J$2:$J$81)))*15)/5,1)) -> 61 | O43: =IF(N43="","Chưa đủ dữ liệu",IF(N43>=80,"Tiềm năng cao",IF(N43>=60,"Tiềm năng","Thông thường"))) -> Tiềm năng | P43: Rule-based prototype
A44: 46247 | B44: KH0043 | C44: =IFERROR(VLOOKUP(B44,Customers!$B$2:$L$81,11,FALSE),"") -> EMP003 | D44: =IFERROR(__xludf.DUMMYFUNCTION("IFERROR(A44-MAX(FILTER(Orders!$D$2:$D$201,Orders!$I$2:$I$201=B44,Orders!$T$2:$T$201=TRUE)),"""")"),148.7449074074102) -> 148.74491 | E44: =COUNTIFS(Orders!$I$2:$I$201,B44,Orders!$T$2:$T$201,TRUE) -> 2 | F44: =SUMIFS(Orders!$R$2:$R$201,Orders!$I$2:$I$201,B44,Orders!$T$2:$T$201,TRUE) -> 5571000 | G44: =IFERROR(F44/E44,0) -> 2785500 | H44: =IFERROR(__xludf.DUMMYFUNCTION("IF(E44<2,"""",IFERROR((MAX(FILTER(Orders!$D$2:$D$201,Orders!$I$2:$I$201=B44,Orders!$T$2:$T$201=TRUE))-MIN(FILTER(Orders!$D$2:$D$201,Orders!$I$2:$I$201=B44,Orders!$T$2:$T$201=TRUE)))/(E44-1),""""))"),95.38633101851883) -> 95.386331 | I44: =IFERROR(AVERAGEIF(Reviews!$H$2:$H$142,B44,Reviews!$C$2:$C$142),"") -> 5 | J44: =SUMIF(Interactions!$B$2:$B$481,B44,Interactions!$I$2:$I$481) -> 15 | K44: =IF(D44="","",MAX(1,MIN(5,6-ROUNDUP(PERCENTRANK($D$2:$D$81,D44)*4+1,0)))) -> 3 | L44: =MAX(1,MIN(5,ROUNDUP(PERCENTRANK($E$2:$E$81,E44)*4+1,0))) -> 4 | M44: =MAX(1,MIN(5,ROUNDUP(PERCENTRANK($F$2:$F$81,F44)*4+1,0))) -> 5 | N44: =IF(K44="","",ROUND((K44*35+L44*30+M44*20+(1+4*(J44-MIN($J$2:$J$81))/MAX(1,MAX($J$2:$J$81)-MIN($J$2:$J$81)))*15)/5,1)) -> 80 | O44: =IF(N44="","Chưa đủ dữ liệu",IF(N44>=80,"Tiềm năng cao",IF(N44>=60,"Tiềm năng","Thông thường"))) -> Tiềm năng cao | P44: Rule-based prototype
A45: 46247 | B45: KH0044 | C45: =IFERROR(VLOOKUP(B45,Customers!$B$2:$L$81,11,FALSE),"") -> EMP004 | D45: =IFERROR(__xludf.DUMMYFUNCTION("IFERROR(A45-MAX(FILTER(Orders!$D$2:$D$201,Orders!$I$2:$I$201=B45,Orders!$T$2:$T$201=TRUE)),"""")"),276.8178935185206) -> 276.81789 | E45: =COUNTIFS(Orders!$I$2:$I$201,B45,Orders!$T$2:$T$201,TRUE) -> 3 | F45: =SUMIFS(Orders!$R$2:$R$201,Orders!$I$2:$I$201,B45,Orders!$T$2:$T$201,TRUE) -> 3037000 | G45: =IFERROR(F45/E45,0) -> 1012333.3 | H45: =IFERROR(__xludf.DUMMYFUNCTION("IF(E45<2,"""",IFERROR((MAX(FILTER(Orders!$D$2:$D$201,Orders!$I$2:$I$201=B45,Orders!$T$2:$T$201=TRUE))-MIN(FILTER(Orders!$D$2:$D$201,Orders!$I$2:$I$201=B45,Orders!$T$2:$T$201=TRUE)))/(E45-1),""""))"),272.62190972222015) -> 272.62191 | I45: =IFERROR(AVERAGEIF(Reviews!$H$2:$H$142,B45,Reviews!$C$2:$C$142),"") -> 4 | J45: =SUMIF(Interactions!$B$2:$B$481,B45,Interactions!$I$2:$I$481) -> 14 | K45: =IF(D45="","",MAX(1,MIN(5,6-ROUNDUP(PERCENTRANK($D$2:$D$81,D45)*4+1,0)))) -> 2 | L45: =MAX(1,MIN(5,ROUNDUP(PERCENTRANK($E$2:$E$81,E45)*4+1,0))) -> 4 | M45: =MAX(1,MIN(5,ROUNDUP(PERCENTRANK($F$2:$F$81,F45)*4+1,0))) -> 4 | N45: =IF(K45="","",ROUND((K45*35+L45*30+M45*20+(1+4*(J45-MIN($J$2:$J$81))/MAX(1,MAX($J$2:$J$81)-MIN($J$2:$J$81)))*15)/5,1)) -> 66.6 | O45: =IF(N45="","Chưa đủ dữ liệu",IF(N45>=80,"Tiềm năng cao",IF(N45>=60,"Tiềm năng","Thông thường"))) -> Tiềm năng | P45: Rule-based prototype
A46: 46247 | B46: KH0045 | C46: =IFERROR(VLOOKUP(B46,Customers!$B$2:$L$81,11,FALSE),"") -> EMP005 | D46: =IFERROR(__xludf.DUMMYFUNCTION("IFERROR(A46-MAX(FILTER(Orders!$D$2:$D$201,Orders!$I$2:$I$201=B46,Orders!$T$2:$T$201=TRUE)),"""")"),461.90135416666453) -> 461.90135 | E46: =COUNTIFS(Orders!$I$2:$I$201,B46,Orders!$T$2:$T$201,TRUE) -> 3 | F46: =SUMIFS(Orders!$R$2:$R$201,Orders!$I$2:$I$201,B46,Orders!$T$2:$T$201,TRUE) -> 2158000 | G46: =IFERROR(F46/E46,0) -> 719333.33 | H46: =IFERROR(__xludf.DUMMYFUNCTION("IF(E46<2,"""",IFERROR((MAX(FILTER(Orders!$D$2:$D$201,Orders!$I$2:$I$201=B46,Orders!$T$2:$T$201=TRUE))-MIN(FILTER(Orders!$D$2:$D$201,Orders!$I$2:$I$201=B46,Orders!$T$2:$T$201=TRUE)))/(E46-1),""""))"),119.29697916666919) -> 119.29698 | I46: =IFERROR(AVERAGEIF(Reviews!$H$2:$H$142,B46,Reviews!$C$2:$C$142),"") -> 3.6666667 | J46: =SUMIF(Interactions!$B$2:$B$481,B46,Interactions!$I$2:$I$481) -> 11 | K46: =IF(D46="","",MAX(1,MIN(5,6-ROUNDUP(PERCENTRANK($D$2:$D$81,D46)*4+1,0)))) -> 1 | L46: =MAX(1,MIN(5,ROUNDUP(PERCENTRANK($E$2:$E$81,E46)*4+1,0))) -> 4 | M46: =MAX(1,MIN(5,ROUNDUP(PERCENTRANK($F$2:$F$81,F46)*4+1,0))) -> 3 | N46: =IF(K46="","",ROUND((K46*35+L46*30+M46*20+(1+4*(J46-MIN($J$2:$J$81))/MAX(1,MAX($J$2:$J$81)-MIN($J$2:$J$81)))*15)/5,1)) -> 48.4 | O46: =IF(N46="","Chưa đủ dữ liệu",IF(N46>=80,"Tiềm năng cao",IF(N46>=60,"Tiềm năng","Thông thường"))) -> Thông thường | P46: Rule-based prototype
A47: 46247 | B47: KH0046 | C47: =IFERROR(VLOOKUP(B47,Customers!$B$2:$L$81,11,FALSE),"") -> EMP006 | D47: =IFERROR(__xludf.DUMMYFUNCTION("IFERROR(A47-MAX(FILTER(Orders!$D$2:$D$201,Orders!$I$2:$I$201=B47,Orders!$T$2:$T$201=TRUE)),"""")"),258.66006944444234) -> 258.66007 | E47: =COUNTIFS(Orders!$I$2:$I$201,B47,Orders!$T$2:$T$201,TRUE) -> 3 | F47: =SUMIFS(Orders!$R$2:$R$201,Orders!$I$2:$I$201,B47,Orders!$T$2:$T$201,TRUE) -> 4379000 | G47: =IFERROR(F47/E47,0) -> 1459666.7 | H47: =IFERROR(__xludf.DUMMYFUNCTION("IF(E47<2,"""",IFERROR((MAX(FILTER(Orders!$D$2:$D$201,Orders!$I$2:$I$201=B47,Orders!$T$2:$T$201=TRUE))-MIN(FILTER(Orders!$D$2:$D$201,Orders!$I$2:$I$201=B47,Orders!$T$2:$T$201=TRUE)))/(E47-1),""""))"),306.0898206018537) -> 306.08982 | I47: =IFERROR(AVERAGEIF(Reviews!$H$2:$H$142,B47,Reviews!$C$2:$C$142),"") -> 2.6666667 | J47: =SUMIF(Interactions!$B$2:$B$481,B47,Interactions!$I$2:$I$481) -> 14 | K47: =IF(D47="","",MAX(1,MIN(5,6-ROUNDUP(PERCENTRANK($D$2:$D$81,D47)*4+1,0)))) -> 3 | L47: =MAX(1,MIN(5,ROUNDUP(PERCENTRANK($E$2:$E$81,E47)*4+1,0))) -> 4 | M47: =MAX(1,MIN(5,ROUNDUP(PERCENTRANK($F$2:$F$81,F47)*4+1,0))) -> 5 | N47: =IF(K47="","",ROUND((K47*35+L47*30+M47*20+(1+4*(J47-MIN($J$2:$J$81))/MAX(1,MAX($J$2:$J$81)-MIN($J$2:$J$81)))*15)/5,1)) -> 77.6 | O47: =IF(N47="","Chưa đủ dữ liệu",IF(N47>=80,"Tiềm năng cao",IF(N47>=60,"Tiềm năng","Thông thường"))) -> Tiềm năng | P47: Rule-based prototype
A48: 46247 | B48: KH0047 | C48: =IFERROR(VLOOKUP(B48,Customers!$B$2:$L$81,11,FALSE),"") -> EMP007 | D48: =IFERROR(__xludf.DUMMYFUNCTION("IFERROR(A48-MAX(FILTER(Orders!$D$2:$D$201,Orders!$I$2:$I$201=B48,Orders!$T$2:$T$201=TRUE)),"""")"),24.061168981483206) -> 24.061169 | E48: =COUNTIFS(Orders!$I$2:$I$201,B48,Orders!$T$2:$T$201,TRUE) -> 2 | F48: =SUMIFS(Orders!$R$2:$R$201,Orders!$I$2:$I$201,B48,Orders!$T$2:$T$201,TRUE) -> 4378000 | G48: =IFERROR(F48/E48,0) -> 2189000 | H48: =IFERROR(__xludf.DUMMYFUNCTION("IF(E48<2,"""",IFERROR((MAX(FILTER(Orders!$D$2:$D$201,Orders!$I$2:$I$201=B48,Orders!$T$2:$T$201=TRUE))-MIN(FILTER(Orders!$D$2:$D$201,Orders!$I$2:$I$201=B48,Orders!$T$2:$T$201=TRUE)))/(E48-1),""""))"),892.4212152777764) -> 892.42122 | I48: =IFERROR(AVERAGEIF(Reviews!$H$2:$H$142,B48,Reviews!$C$2:$C$142),"") -> 5 | J48: =SUMIF(Interactions!$B$2:$B$481,B48,Interactions!$I$2:$I$481) -> 12 | K48: =IF(D48="","",MAX(1,MIN(5,6-ROUNDUP(PERCENTRANK($D$2:$D$81,D48)*4+1,0)))) -> 5 | L48: =MAX(1,MIN(5,ROUNDUP(PERCENTRANK($E$2:$E$81,E48)*4+1,0))) -> 4 | M48: =MAX(1,MIN(5,ROUNDUP(PERCENTRANK($F$2:$F$81,F48)*4+1,0))) -> 4 | N48: =IF(K48="","",ROUND((K48*35+L48*30+M48*20+(1+4*(J48-MIN($J$2:$J$81))/MAX(1,MAX($J$2:$J$81)-MIN($J$2:$J$81)))*15)/5,1)) -> 82.8 | O48: =IF(N48="","Chưa đủ dữ liệu",IF(N48>=80,"Tiềm năng cao",IF(N48>=60,"Tiềm năng","Thông thường"))) -> Tiềm năng cao | P48: Rule-based prototype
A49: 46247 | B49: KH0048 | C49: =IFERROR(VLOOKUP(B49,Customers!$B$2:$L$81,11,FALSE),"") -> EMP008 | D49: =IFERROR(__xludf.DUMMYFUNCTION("IFERROR(A49-MAX(FILTER(Orders!$D$2:$D$201,Orders!$I$2:$I$201=B49,Orders!$T$2:$T$201=TRUE)),"""")"),610.271967592591) -> 610.27197 | E49: =COUNTIFS(Orders!$I$2:$I$201,B49,Orders!$T$2:$T$201,TRUE) -> 2 | F49: =SUMIFS(Orders!$R$2:$R$201,Orders!$I$2:$I$201,B49,Orders!$T$2:$T$201,TRUE) -> 4457000 | G49: =IFERROR(F49/E49,0) -> 2228500 | H49: =IFERROR(__xludf.DUMMYFUNCTION("IF(E49<2,"""",IFERROR((MAX(FILTER(Orders!$D$2:$D$201,Orders!$I$2:$I$201=B49,Orders!$T$2:$T$201=TRUE))-MIN(FILTER(Orders!$D$2:$D$201,Orders!$I$2:$I$201=B49,Orders!$T$2:$T$201=TRUE)))/(E49-1),""""))"),62.047303240738984) -> 62.047303 | I49: =IFERROR(AVERAGEIF(Reviews!$H$2:$H$142,B49,Reviews!$C$2:$C$142),"") -> 3 | J49: =SUMIF(Interactions!$B$2:$B$481,B49,Interactions!$I$2:$I$481) -> 13 | K49: =IF(D49="","",MAX(1,MIN(5,6-ROUNDUP(PERCENTRANK($D$2:$D$81,D49)*4+1,0)))) -> 1 | L49: =MAX(1,MIN(5,ROUNDUP(PERCENTRANK($E$2:$E$81,E49)*4+1,0))) -> 4 | M49: =MAX(1,MIN(5,ROUNDUP(PERCENTRANK($F$2:$F$81,F49)*4+1,0))) -> 5 | N49: =IF(K49="","",ROUND((K49*35+L49*30+M49*20+(1+4*(J49-MIN($J$2:$J$81))/MAX(1,MAX($J$2:$J$81)-MIN($J$2:$J$81)))*15)/5,1)) -> 61.2 | O49: =IF(N49="","Chưa đủ dữ liệu",IF(N49>=80,"Tiềm năng cao",IF(N49>=60,"Tiềm năng","Thông thường"))) -> Tiềm năng | P49: Rule-based prototype
A50: 46247 | B50: KH0049 | C50: =IFERROR(VLOOKUP(B50,Customers!$B$2:$L$81,11,FALSE),"") -> EMP001 | D50: =IFERROR(__xludf.DUMMYFUNCTION("IFERROR(A50-MAX(FILTER(Orders!$D$2:$D$201,Orders!$I$2:$I$201=B50,Orders!$T$2:$T$201=TRUE)),"""")"),"") | E50: =COUNTIFS(Orders!$I$2:$I$201,B50,Orders!$T$2:$T$201,TRUE) -> 0 | F50: =SUMIFS(Orders!$R$2:$R$201,Orders!$I$2:$I$201,B50,Orders!$T$2:$T$201,TRUE) -> 0 | G50: =IFERROR(F50/E50,0) -> 0 | H50: =IFERROR(__xludf.DUMMYFUNCTION("IF(E50<2,"""",IFERROR((MAX(FILTER(Orders!$D$2:$D$201,Orders!$I$2:$I$201=B50,Orders!$T$2:$T$201=TRUE))-MIN(FILTER(Orders!$D$2:$D$201,Orders!$I$2:$I$201=B50,Orders!$T$2:$T$201=TRUE)))/(E50-1),""""))"),"") | I50: =IFERROR(AVERAGEIF(Reviews!$H$2:$H$142,B50,Reviews!$C$2:$C$142),"") | J50: =SUMIF(Interactions!$B$2:$B$481,B50,Interactions!$I$2:$I$481) -> 13 | K50: =IF(D50="","",MAX(1,MIN(5,6-ROUNDUP(PERCENTRANK($D$2:$D$81,D50)*4+1,0)))) | L50: =MAX(1,MIN(5,ROUNDUP(PERCENTRANK($E$2:$E$81,E50)*4+1,0))) -> 1 | M50: =MAX(1,MIN(5,ROUNDUP(PERCENTRANK($F$2:$F$81,F50)*4+1,0))) -> 1 | N50: =IF(K50="","",ROUND((K50*35+L50*30+M50*20+(1+4*(J50-MIN($J$2:$J$81))/MAX(1,MAX($J$2:$J$81)-MIN($J$2:$J$81)))*15)/5,1)) | O50: =IF(N50="","Chưa đủ dữ liệu",IF(N50>=80,"Tiềm năng cao",IF(N50>=60,"Tiềm năng","Thông thường"))) -> Chưa đủ dữ liệu | P50: Rule-based prototype
A51: 46247 | B51: KH0050 | C51: =IFERROR(VLOOKUP(B51,Customers!$B$2:$L$81,11,FALSE),"") -> EMP002 | D51: =IFERROR(__xludf.DUMMYFUNCTION("IFERROR(A51-MAX(FILTER(Orders!$D$2:$D$201,Orders!$I$2:$I$201=B51,Orders!$T$2:$T$201=TRUE)),"""")"),370.6144675925898) -> 370.61447 | E51: =COUNTIFS(Orders!$I$2:$I$201,B51,Orders!$T$2:$T$201,TRUE) -> 3 | F51: =SUMIFS(Orders!$R$2:$R$201,Orders!$I$2:$I$201,B51,Orders!$T$2:$T$201,TRUE) -> 4044000 | G51: =IFERROR(F51/E51,0) -> 1348000 | H51: =IFERROR(__xludf.DUMMYFUNCTION("IF(E51<2,"""",IFERROR((MAX(FILTER(Orders!$D$2:$D$201,Orders!$I$2:$I$201=B51,Orders!$T$2:$T$201=TRUE))-MIN(FILTER(Orders!$D$2:$D$201,Orders!$I$2:$I$201=B51,Orders!$T$2:$T$201=TRUE)))/(E51-1),""""))"),98.44269097222423) -> 98.442691 | I51: =IFERROR(AVERAGEIF(Reviews!$H$2:$H$142,B51,Reviews!$C$2:$C$142),"") -> 5 | J51: =SUMIF(Interactions!$B$2:$B$481,B51,Interactions!$I$2:$I$481) -> 10 | K51: =IF(D51="","",MAX(1,MIN(5,6-ROUNDUP(PERCENTRANK($D$2:$D$81,D51)*4+1,0)))) -> 2 | L51: =MAX(1,MIN(5,ROUNDUP(PERCENTRANK($E$2:$E$81,E51)*4+1,0))) -> 4 | M51: =MAX(1,MIN(5,ROUNDUP(PERCENTRANK($F$2:$F$81,F51)*4+1,0))) -> 4 | N51: =IF(K51="","",ROUND((K51*35+L51*30+M51*20+(1+4*(J51-MIN($J$2:$J$81))/MAX(1,MAX($J$2:$J$81)-MIN($J$2:$J$81)))*15)/5,1)) -> 57 | O51: =IF(N51="","Chưa đủ dữ liệu",IF(N51>=80,"Tiềm năng cao",IF(N51>=60,"Tiềm năng","Thông thường"))) -> Thông thường | P51: Rule-based prototype
A52: 46247 | B52: KH0051 | C52: =IFERROR(VLOOKUP(B52,Customers!$B$2:$L$81,11,FALSE),"") -> EMP003 | D52: =IFERROR(__xludf.DUMMYFUNCTION("IFERROR(A52-MAX(FILTER(Orders!$D$2:$D$201,Orders!$I$2:$I$201=B52,Orders!$T$2:$T$201=TRUE)),"""")"),"") | E52: =COUNTIFS(Orders!$I$2:$I$201,B52,Orders!$T$2:$T$201,TRUE) -> 0 | F52: =SUMIFS(Orders!$R$2:$R$201,Orders!$I$2:$I$201,B52,Orders!$T$2:$T$201,TRUE) -> 0 | G52: =IFERROR(F52/E52,0) -> 0 | H52: =IFERROR(__xludf.DUMMYFUNCTION("IF(E52<2,"""",IFERROR((MAX(FILTER(Orders!$D$2:$D$201,Orders!$I$2:$I$201=B52,Orders!$T$2:$T$201=TRUE))-MIN(FILTER(Orders!$D$2:$D$201,Orders!$I$2:$I$201=B52,Orders!$T$2:$T$201=TRUE)))/(E52-1),""""))"),"") | I52: =IFERROR(AVERAGEIF(Reviews!$H$2:$H$142,B52,Reviews!$C$2:$C$142),"") | J52: =SUMIF(Interactions!$B$2:$B$481,B52,Interactions!$I$2:$I$481) -> 15 | K52: =IF(D52="","",MAX(1,MIN(5,6-ROUNDUP(PERCENTRANK($D$2:$D$81,D52)*4+1,0)))) | L52: =MAX(1,MIN(5,ROUNDUP(PERCENTRANK($E$2:$E$81,E52)*4+1,0))) -> 1 | M52: =MAX(1,MIN(5,ROUNDUP(PERCENTRANK($F$2:$F$81,F52)*4+1,0))) -> 1 | N52: =IF(K52="","",ROUND((K52*35+L52*30+M52*20+(1+4*(J52-MIN($J$2:$J$81))/MAX(1,MAX($J$2:$J$81)-MIN($J$2:$J$81)))*15)/5,1)) | O52: =IF(N52="","Chưa đủ dữ liệu",IF(N52>=80,"Tiềm năng cao",IF(N52>=60,"Tiềm năng","Thông thường"))) -> Chưa đủ dữ liệu | P52: Rule-based prototype
A53: 46247 | B53: KH0052 | C53: =IFERROR(VLOOKUP(B53,Customers!$B$2:$L$81,11,FALSE),"") -> EMP004 | D53: =IFERROR(__xludf.DUMMYFUNCTION("IFERROR(A53-MAX(FILTER(Orders!$D$2:$D$201,Orders!$I$2:$I$201=B53,Orders!$T$2:$T$201=TRUE)),"""")"),328.80321759259095) -> 328.80322 | E53: =COUNTIFS(Orders!$I$2:$I$201,B53,Orders!$T$2:$T$201,TRUE) -> 3 | F53: =SUMIFS(Orders!$R$2:$R$201,Orders!$I$2:$I$201,B53,Orders!$T$2:$T$201,TRUE) -> 4955000 | G53: =IFERROR(F53/E53,0) -> 1651666.7 | H53: =IFERROR(__xludf.DUMMYFUNCTION("IF(E53<2,"""",IFERROR((MAX(FILTER(Orders!$D$2:$D$201,Orders!$I$2:$I$201=B53,Orders!$T$2:$T$201=TRUE))-MIN(FILTER(Orders!$D$2:$D$201,Orders!$I$2:$I$201=B53,Orders!$T$2:$T$201=TRUE)))/(E53-1),""""))"),198.72207754629562) -> 198.72208 | I53: =IFERROR(AVERAGEIF(Reviews!$H$2:$H$142,B53,Reviews!$C$2:$C$142),"") -> 3.6666667 | J53: =SUMIF(Interactions!$B$2:$B$481,B53,Interactions!$I$2:$I$481) -> 14 | K53: =IF(D53="","",MAX(1,MIN(5,6-ROUNDUP(PERCENTRANK($D$2:$D$81,D53)*4+1,0)))) -> 2 | L53: =MAX(1,MIN(5,ROUNDUP(PERCENTRANK($E$2:$E$81,E53)*4+1,0))) -> 4 | M53: =MAX(1,MIN(5,ROUNDUP(PERCENTRANK($F$2:$F$81,F53)*4+1,0))) -> 5 | N53: =IF(K53="","",ROUND((K53*35+L53*30+M53*20+(1+4*(J53-MIN($J$2:$J$81))/MAX(1,MAX($J$2:$J$81)-MIN($J$2:$J$81)))*15)/5,1)) -> 70.6 | O53: =IF(N53="","Chưa đủ dữ liệu",IF(N53>=80,"Tiềm năng cao",IF(N53>=60,"Tiềm năng","Thông thường"))) -> Tiềm năng | P53: Rule-based prototype
A54: 46247 | B54: KH0053 | C54: =IFERROR(VLOOKUP(B54,Customers!$B$2:$L$81,11,FALSE),"") -> EMP005 | D54: =IFERROR(__xludf.DUMMYFUNCTION("IFERROR(A54-MAX(FILTER(Orders!$D$2:$D$201,Orders!$I$2:$I$201=B54,Orders!$T$2:$T$201=TRUE)),"""")"),240.1283449074108) -> 240.12834 | E54: =COUNTIFS(Orders!$I$2:$I$201,B54,Orders!$T$2:$T$201,TRUE) -> 4 | F54: =SUMIFS(Orders!$R$2:$R$201,Orders!$I$2:$I$201,B54,Orders!$T$2:$T$201,TRUE) -> 2581000 | G54: =IFERROR(F54/E54,0) -> 645250 | H54: =IFERROR(__xludf.DUMMYFUNCTION("IF(E54<2,"""",IFERROR((MAX(FILTER(Orders!$D$2:$D$201,Orders!$I$2:$I$201=B54,Orders!$T$2:$T$201=TRUE))-MIN(FILTER(Orders!$D$2:$D$201,Orders!$I$2:$I$201=B54,Orders!$T$2:$T$201=TRUE)))/(E54-1),""""))"),193.2136766975309) -> 193.21368 | I54: =IFERROR(AVERAGEIF(Reviews!$H$2:$H$142,B54,Reviews!$C$2:$C$142),"") -> 3.8 | J54: =SUMIF(Interactions!$B$2:$B$481,B54,Interactions!$I$2:$I$481) -> 11 | K54: =IF(D54="","",MAX(1,MIN(5,6-ROUNDUP(PERCENTRANK($D$2:$D$81,D54)*4+1,0)))) -> 3 | L54: =MAX(1,MIN(5,ROUNDUP(PERCENTRANK($E$2:$E$81,E54)*4+1,0))) -> 5 | M54: =MAX(1,MIN(5,ROUNDUP(PERCENTRANK($F$2:$F$81,F54)*4+1,0))) -> 4 | N54: =IF(K54="","",ROUND((K54*35+L54*30+M54*20+(1+4*(J54-MIN($J$2:$J$81))/MAX(1,MAX($J$2:$J$81)-MIN($J$2:$J$81)))*15)/5,1)) -> 72.4 | O54: =IF(N54="","Chưa đủ dữ liệu",IF(N54>=80,"Tiềm năng cao",IF(N54>=60,"Tiềm năng","Thông thường"))) -> Tiềm năng | P54: Rule-based prototype
A55: 46247 | B55: KH0054 | C55: =IFERROR(VLOOKUP(B55,Customers!$B$2:$L$81,11,FALSE),"") -> EMP006 | D55: =IFERROR(__xludf.DUMMYFUNCTION("IFERROR(A55-MAX(FILTER(Orders!$D$2:$D$201,Orders!$I$2:$I$201=B55,Orders!$T$2:$T$201=TRUE)),"""")"),84.05750000000262) -> 84.0575 | E55: =COUNTIFS(Orders!$I$2:$I$201,B55,Orders!$T$2:$T$201,TRUE) -> 1 | F55: =SUMIFS(Orders!$R$2:$R$201,Orders!$I$2:$I$201,B55,Orders!$T$2:$T$201,TRUE) -> 921000 | G55: =IFERROR(F55/E55,0) -> 921000 | H55: =IFERROR(__xludf.DUMMYFUNCTION("IF(E55<2,"""",IFERROR((MAX(FILTER(Orders!$D$2:$D$201,Orders!$I$2:$I$201=B55,Orders!$T$2:$T$201=TRUE))-MIN(FILTER(Orders!$D$2:$D$201,Orders!$I$2:$I$201=B55,Orders!$T$2:$T$201=TRUE)))/(E55-1),""""))"),"") | I55: =IFERROR(AVERAGEIF(Reviews!$H$2:$H$142,B55,Reviews!$C$2:$C$142),"") -> 2 | J55: =SUMIF(Interactions!$B$2:$B$481,B55,Interactions!$I$2:$I$481) -> 14 | K55: =IF(D55="","",MAX(1,MIN(5,6-ROUNDUP(PERCENTRANK($D$2:$D$81,D55)*4+1,0)))) -> 4 | L55: =MAX(1,MIN(5,ROUNDUP(PERCENTRANK($E$2:$E$81,E55)*4+1,0))) -> 3 | M55: =MAX(1,MIN(5,ROUNDUP(PERCENTRANK($F$2:$F$81,F55)*4+1,0))) -> 3 | N55: =IF(K55="","",ROUND((K55*35+L55*30+M55*20+(1+4*(J55-MIN($J$2:$J$81))/MAX(1,MAX($J$2:$J$81)-MIN($J$2:$J$81)))*15)/5,1)) -> 70.6 | O55: =IF(N55="","Chưa đủ dữ liệu",IF(N55>=80,"Tiềm năng cao",IF(N55>=60,"Tiềm năng","Thông thường"))) -> Tiềm năng | P55: Rule-based prototype
A56: 46247 | B56: KH0055 | C56: =IFERROR(VLOOKUP(B56,Customers!$B$2:$L$81,11,FALSE),"") -> EMP007 | D56: =IFERROR(__xludf.DUMMYFUNCTION("IFERROR(A56-MAX(FILTER(Orders!$D$2:$D$201,Orders!$I$2:$I$201=B56,Orders!$T$2:$T$201=TRUE)),"""")"),608.1821180555562) -> 608.18212 | E56: =COUNTIFS(Orders!$I$2:$I$201,B56,Orders!$T$2:$T$201,TRUE) -> 1 | F56: =SUMIFS(Orders!$R$2:$R$201,Orders!$I$2:$I$201,B56,Orders!$T$2:$T$201,TRUE) -> 995000 | G56: =IFERROR(F56/E56,0) -> 995000 | H56: =IFERROR(__xludf.DUMMYFUNCTION("IF(E56<2,"""",IFERROR((MAX(FILTER(Orders!$D$2:$D$201,Orders!$I$2:$I$201=B56,Orders!$T$2:$T$201=TRUE))-MIN(FILTER(Orders!$D$2:$D$201,Orders!$I$2:$I$201=B56,Orders!$T$2:$T$201=TRUE)))/(E56-1),""""))"),"") | I56: =IFERROR(AVERAGEIF(Reviews!$H$2:$H$142,B56,Reviews!$C$2:$C$142),"") -> 4 | J56: =SUMIF(Interactions!$B$2:$B$481,B56,Interactions!$I$2:$I$481) -> 12 | K56: =IF(D56="","",MAX(1,MIN(5,6-ROUNDUP(PERCENTRANK($D$2:$D$81,D56)*4+1,0)))) -> 1 | L56: =MAX(1,MIN(5,ROUNDUP(PERCENTRANK($E$2:$E$81,E56)*4+1,0))) -> 3 | M56: =MAX(1,MIN(5,ROUNDUP(PERCENTRANK($F$2:$F$81,F56)*4+1,0))) -> 3 | N56: =IF(K56="","",ROUND((K56*35+L56*30+M56*20+(1+4*(J56-MIN($J$2:$J$81))/MAX(1,MAX($J$2:$J$81)-MIN($J$2:$J$81)))*15)/5,1)) -> 44.8 | O56: =IF(N56="","Chưa đủ dữ liệu",IF(N56>=80,"Tiềm năng cao",IF(N56>=60,"Tiềm năng","Thông thường"))) -> Thông thường | P56: Rule-based prototype
A57: 46247 | B57: KH0056 | C57: =IFERROR(VLOOKUP(B57,Customers!$B$2:$L$81,11,FALSE),"") -> EMP008 | D57: =IFERROR(__xludf.DUMMYFUNCTION("IFERROR(A57-MAX(FILTER(Orders!$D$2:$D$201,Orders!$I$2:$I$201=B57,Orders!$T$2:$T$201=TRUE)),"""")"),73.29244212962658) -> 73.292442 | E57: =COUNTIFS(Orders!$I$2:$I$201,B57,Orders!$T$2:$T$201,TRUE) -> 4 | F57: =SUMIFS(Orders!$R$2:$R$201,Orders!$I$2:$I$201,B57,Orders!$T$2:$T$201,TRUE) -> 8371000 | G57: =IFERROR(F57/E57,0) -> 2092750 | H57: =IFERROR(__xludf.DUMMYFUNCTION("IF(E57<2,"""",IFERROR((MAX(FILTER(Orders!$D$2:$D$201,Orders!$I$2:$I$201=B57,Orders!$T$2:$T$201=TRUE))-MIN(FILTER(Orders!$D$2:$D$201,Orders!$I$2:$I$201=B57,Orders!$T$2:$T$201=TRUE)))/(E57-1),""""))"),263.16552469135786) -> 263.16552 | I57: =IFERROR(AVERAGEIF(Reviews!$H$2:$H$142,B57,Reviews!$C$2:$C$142),"") -> 4.3333333 | J57: =SUMIF(Interactions!$B$2:$B$481,B57,Interactions!$I$2:$I$481) -> 13 | K57: =IF(D57="","",MAX(1,MIN(5,6-ROUNDUP(PERCENTRANK($D$2:$D$81,D57)*4+1,0)))) -> 4 | L57: =MAX(1,MIN(5,ROUNDUP(PERCENTRANK($E$2:$E$81,E57)*4+1,0))) -> 5 | M57: =MAX(1,MIN(5,ROUNDUP(PERCENTRANK($F$2:$F$81,F57)*4+1,0))) -> 5 | N57: =IF(K57="","",ROUND((K57*35+L57*30+M57*20+(1+4*(J57-MIN($J$2:$J$81))/MAX(1,MAX($J$2:$J$81)-MIN($J$2:$J$81)))*15)/5,1)) -> 88.2 | O57: =IF(N57="","Chưa đủ dữ liệu",IF(N57>=80,"Tiềm năng cao",IF(N57>=60,"Tiềm năng","Thông thường"))) -> Tiềm năng cao | P57: Rule-based prototype
A58: 46247 | B58: KH0057 | C58: =IFERROR(VLOOKUP(B58,Customers!$B$2:$L$81,11,FALSE),"") -> EMP001 | D58: =IFERROR(__xludf.DUMMYFUNCTION("IFERROR(A58-MAX(FILTER(Orders!$D$2:$D$201,Orders!$I$2:$I$201=B58,Orders!$T$2:$T$201=TRUE)),"""")"),341.68664351852203) -> 341.68664 | E58: =COUNTIFS(Orders!$I$2:$I$201,B58,Orders!$T$2:$T$201,TRUE) -> 3 | F58: =SUMIFS(Orders!$R$2:$R$201,Orders!$I$2:$I$201,B58,Orders!$T$2:$T$201,TRUE) -> 5182000 | G58: =IFERROR(F58/E58,0) -> 1727333.3 | H58: =IFERROR(__xludf.DUMMYFUNCTION("IF(E58<2,"""",IFERROR((MAX(FILTER(Orders!$D$2:$D$201,Orders!$I$2:$I$201=B58,Orders!$T$2:$T$201=TRUE))-MIN(FILTER(Orders!$D$2:$D$201,Orders!$I$2:$I$201=B58,Orders!$T$2:$T$201=TRUE)))/(E58-1),""""))"),263.42714120370147) -> 263.42714 | I58: =IFERROR(AVERAGEIF(Reviews!$H$2:$H$142,B58,Reviews!$C$2:$C$142),"") -> 3.6666667 | J58: =SUMIF(Interactions!$B$2:$B$481,B58,Interactions!$I$2:$I$481) -> 13 | K58: =IF(D58="","",MAX(1,MIN(5,6-ROUNDUP(PERCENTRANK($D$2:$D$81,D58)*4+1,0)))) -> 2 | L58: =MAX(1,MIN(5,ROUNDUP(PERCENTRANK($E$2:$E$81,E58)*4+1,0))) -> 4 | M58: =MAX(1,MIN(5,ROUNDUP(PERCENTRANK($F$2:$F$81,F58)*4+1,0))) -> 5 | N58: =IF(K58="","",ROUND((K58*35+L58*30+M58*20+(1+4*(J58-MIN($J$2:$J$81))/MAX(1,MAX($J$2:$J$81)-MIN($J$2:$J$81)))*15)/5,1)) -> 68.2 | O58: =IF(N58="","Chưa đủ dữ liệu",IF(N58>=80,"Tiềm năng cao",IF(N58>=60,"Tiềm năng","Thông thường"))) -> Tiềm năng | P58: Rule-based prototype
